src/sigmoid_lut.v
// File         : sigmoid_lut.v
// Description  : Sigmoid LUT for Q16.16 format (High Precision)

module sigmoid_lut (
    input  signed [31:0] z_in,   // Q16.16
    output signed [31:0] a_sigmoid // Q16.16
);
    localparam ADDRESS_BITS = 10;
    localparam DATA_WIDTH   = 32;
    localparam ROM_DEPTH    = 1 << ADDRESS_BITS;

    // Saturation values (Q16.16)
    localparam signed [31:0] SIGMOID_MAX_VAL = 32'h00010000; // 1.0
    localparam signed [31:0] SIGMOID_MIN_VAL = 32'h00000000; // 0.0

    // Clamp input magnitude at +/-6.0 (Q16.16)
    // LUT covers up to 8.0, so 6.0 is safe.
    localparam signed [31:0] POS_CLAMP_THRESHOLD = 32'h00060000; // +6.0
    localparam signed [31:0] NEG_CLAMP_THRESHOLD = 32'hFFFA0000; // -6.0

    reg [DATA_WIDTH-1:0] SIGMOID_ROM [0:ROM_DEPTH-1];

    initial begin
        // Ensure path matches Python script output
        $readmemh("./mem/sigmoid_lut_mem.hex", SIGMOID_ROM);
    end

    // Use symmetry: compute abs(z) for lookup
    // Sigmoid(-x) = 1 - Sigmoid(x)
    wire is_negative = z_in[31];
    wire signed [31:0] z_abs = is_negative ? -z_in : z_in;

    // Address bits selected from fractional range
    // Bit 9 corresponds to 2^-7 (0.0078125)
    // Slice [18:9] = 10 bits
    wire [ADDRESS_BITS-1:0] rom_address = z_abs[18:9];
    
    wire signed [31:0] rom_data = SIGMOID_ROM[rom_address];

    assign a_sigmoid =
        (z_in >= POS_CLAMP_THRESHOLD) ? SIGMOID_MAX_VAL :
        (z_in <= NEG_CLAMP_THRESHOLD) ? SIGMOID_MIN_VAL :
        (is_negative ? (SIGMOID_MAX_VAL - rom_data) : rom_data);

endmodule

src/tanh_lut.v
// File         : tanh_lut.v
// Description  : Tanh LUT for Q1.15.16 format (32-bit).

module tanh_lut (
    input  signed [31:0] z_in,   // Q16.16
    output signed [31:0] a_tanh  // Q16.16
);
    localparam ADDRESS_BITS = 10;
    localparam DATA_WIDTH   = 32;
    localparam ROM_DEPTH    = 1 << ADDRESS_BITS;

    // Output saturation values (Q16.16)
    localparam MAX_POSITIVE_VAL = 32'h00010000; // +1.0
    localparam MAX_NEGATIVE_VAL = 32'hFFFF0000; // -1.0

    // Clamp thresholds (+/-6.0 in Q16.16)
    localparam CLAMP_POS = 32'h00060000;
    localparam CLAMP_NEG = 32'hFFFA0000;

    reg [DATA_WIDTH-1:0] TANH_ROM [0:ROM_DEPTH-1];

    initial begin
        // ROM contents loaded from hex file
        $readmemh("mem/tanh_lut_mem.hex", TANH_ROM);
    end

    // Use absolute value for table lookup
    wire signed [31:0] z_abs = z_in[31] ? -z_in : z_in;

    // Address bits taken from fractional region (resolution ~0.125)
    wire [ADDRESS_BITS-1:0] rom_address = z_abs[15:6];
    wire signed [31:0] rom_data = TANH_ROM[rom_address];

    // Output with clamping and symmetry
    assign a_tanh =
        (z_in >= $signed(CLAMP_POS)) ? MAX_POSITIVE_VAL :
        (z_in <= $signed(CLAMP_NEG)) ? MAX_NEGATIVE_VAL :
        (z_in[31] ? -rom_data : rom_data);

endmodule

src/pe_neuron.v
// File         : pe_neuron.v
// Description  : Processing Element (Neuron) module


// Clock/Edge analysis krn ternyata salah pipe_wait
// sum_reg is on clock edge
// sig_out and tanh_out is combinational
// y_out and y_final_reg is clocked
// So for a single pass, it needs 1 clock (on any edge)


`include "tanh_lut.v"
`include "sigmoid_lut.v"

module pe_neuron #(
    parameter DATA_WIDTH = 32
) (
    input wire clk,
    input wire rst,
    input signed [DATA_WIDTH-1:0] x1, x2, x3, x4,
    input signed [DATA_WIDTH-1:0] w1, w2, w3, w4,
    input signed [DATA_WIDTH-1:0] bias,
    input wire pe_accumulate,
    input wire signed [DATA_WIDTH-1:0] partial_sum_in,
    input wire [1:0] act_sel,
    output signed [DATA_WIDTH-1:0] y_out
);

    // Multiplication (Clocked)
    reg signed [DATA_WIDTH-1:0] p1_reg, p2_reg, p3_reg, p4_reg;
    
    // Multipliers (Combinational part)
    wire signed [2*DATA_WIDTH-1:0] p1_long = x1 * w1;
    wire signed [2*DATA_WIDTH-1:0] p2_long = x2 * w2;
    wire signed [2*DATA_WIDTH-1:0] p3_long = x3 * w3;
    wire signed [2*DATA_WIDTH-1:0] p4_long = x4 * w4;

    always @(posedge clk or negedge rst) begin
        if (!rst) begin
            p1_reg <= 0; p2_reg <= 0; p3_reg <= 0; p4_reg <= 0;
        end else begin
            // Shift down to Q16.16 immediately and register
            p1_reg <= p1_long >>> 16;
            p2_reg <= p2_long >>> 16;
            p3_reg <= p3_long >>> 16;
            p4_reg <= p4_long >>> 16;
        end
    end

    // Summation (Clocked)
    reg signed [DATA_WIDTH-1:0] sum_reg;
    reg [1:0] act_sel_d1, act_sel_d2; // Delay activation select signal to match pipeline
    
    always @(posedge clk or negedge rst) begin
        if (!rst) begin
            sum_reg <= 0;
            act_sel_d1 <= 0;
        end else begin
            if (pe_accumulate)
                sum_reg <= p1_reg + p2_reg + p3_reg + p4_reg + bias + partial_sum_in;
            else
                sum_reg <= p1_reg + p2_reg + p3_reg + p4_reg + bias;
            
            // Pipeline the control signal
            act_sel_d1 <= act_sel; 
        end
    end
    
    // Activation / LUT (Clocked Output)
    wire signed [DATA_WIDTH-1:0] tanh_out, sig_out;
    reg signed [DATA_WIDTH-1:0] y_final_reg;

    // Combinational Activation Function before getting outputted to y_out/y_final_reg clocked
    tanh_lut u_tanh (.z_in(sum_reg), .a_tanh(tanh_out));
    sigmoid_lut u_sig (.z_in(sum_reg), .a_sigmoid(sig_out));

    always @(posedge clk or negedge rst) begin
        if (!rst) y_final_reg <= 0;
        else begin
            case (act_sel_d1) // Use the delayed control signal
                2'd0: y_final_reg <= tanh_out;
                2'd1: y_final_reg <= sig_out;
                default: y_final_reg <= sum_reg;
            endcase
        end
    end

    assign y_out = y_final_reg;

endmodule

src/memory.v
// File: memory.v
// Description: memory module reading weights and biases from hex files

`timescale 1ns/1ps

module memory #(
    parameter DATA_WIDTH = 32,
    parameter ADDR_WIDTH = 10,
    parameter MEM_DEPTH  = 32
)(
    input wire clk,
    input wire [ADDR_WIDTH-1:0] addr,
    output reg signed [DATA_WIDTH-1:0] w1, w2, w3, w4, bias
);

    // Internal RAM
    reg [DATA_WIDTH-1:0] mem_w1   [0:MEM_DEPTH-1];
    reg [DATA_WIDTH-1:0] mem_w2   [0:MEM_DEPTH-1];
    reg [DATA_WIDTH-1:0] mem_w3   [0:MEM_DEPTH-1];
    reg [DATA_WIDTH-1:0] mem_w4   [0:MEM_DEPTH-1];
    reg [DATA_WIDTH-1:0] mem_bias [0:MEM_DEPTH-1];

    // Load contents from hex files
    initial begin
        $readmemh("mem/w1.hex",   mem_w1);
        $readmemh("mem/w2.hex",   mem_w2);
        $readmemh("mem/w3.hex",   mem_w3);
        $readmemh("mem/w4.hex",   mem_w4);
        $readmemh("mem/bias.hex", mem_bias);
    end

    // Combinational read
    always @(*) begin
        if (addr < MEM_DEPTH) begin
            w1   = mem_w1[addr];
            w2   = mem_w2[addr];
            w3   = mem_w3[addr];
            w4   = mem_w4[addr];
            bias = mem_bias[addr];
        end else begin
            w1 = 0; w2 = 0; w3 = 0; w4 = 0; bias = 0;
        end
    end

endmodule

src/discriminator_3x3.v
// File: discriminator_3x3.v
`timescale 1ns/1ps

`include "memory.v"
`include "pe_neuron.v"

module discriminator_3x3 #(
    parameter DATA_WIDTH = 32,
    parameter ADDR_WIDTH = 10
)(
    input wire clk,
    input wire rst,
    input wire start,
    // Input: 3x3 Flattened Image (9 pixels)
    input wire signed [DATA_WIDTH-1:0] p1, p2, p3,
    input wire signed [DATA_WIDTH-1:0] p4, p5, p6,
    input wire signed [DATA_WIDTH-1:0] p7, p8, p9,
    
    output reg signed [DATA_WIDTH-1:0] disc_out,
    output reg done
);

    // --- Internal Memory for Intermediate Results ---
    // 0-2: Discriminator Hidden Layer Outputs (D2)
    reg signed [DATA_WIDTH-1:0] hidden_ram [0:2]; 
    
    // --- Input Buffer ---
    reg signed [DATA_WIDTH-1:0] img_buffer [0:8];

    // --- State Machine ---
    localparam S_IDLE       = 3'd0;
    localparam S_LOAD       = 3'd1;
    localparam S_D_HIDDEN   = 3'd2;
    localparam S_D_OUTPUT   = 3'd3;
    localparam S_DONE       = 3'd4;
    
    reg [2:0] state;
    reg [3:0] loop_cnt;  // Neuron counter
    reg [1:0] acc_step;  // Accumulation step for PE

    // --- PE and Memory Signals ---
    reg [ADDR_WIDTH-1:0] mem_addr;
    wire signed [DATA_WIDTH-1:0] w1, w2, w3, w4, bias;
    
    reg signed [DATA_WIDTH-1:0] pe_x1, pe_x2, pe_x3, pe_x4;
    reg signed [DATA_WIDTH-1:0] pe_partial_sum;
    reg pe_accumulate;
    reg [1:0] pe_act_sel; // 0:None, 1:Tanh, 2:Sigmoid
    wire signed [DATA_WIDTH-1:0] pe_result;

    // --- Instantiations ---

    // Weight Memory (Assumed existing module)
    memory u_mem (
        .clk(clk),
        .addr(mem_addr),
        .w1(w1), .w2(w2), .w3(w3), .w4(w4), .bias(bias)
    );

    // Processing Element (Assumed existing module)
    pe_neuron u_pe (
        .clk(clk),
        .rst(rst),
        .x1(pe_x1), .x2(pe_x2), .x3(pe_x3), .x4(pe_x4),
        .w1(w1), .w2(w2), .w3(w3), .w4(w4),
        .bias(bias),
        .pe_accumulate(pe_accumulate),
        .partial_sum_in(pe_partial_sum),
        .act_sel(pe_act_sel),
        .y_out(pe_result)
    );

    // --- Logic ---

    always @(posedge clk or posedge rst) begin
        if (rst) begin
            state <= S_IDLE;
            done <= 0;
            loop_cnt <= 0;
            acc_step <= 0;
            mem_addr <= 0;
            disc_out <= 0;
        end else begin
            case (state)
                S_IDLE: begin
                    done <= 0;
                    if (start) state <= S_LOAD;
                end

                // Latch inputs into buffer
                S_LOAD: begin
                    img_buffer[0] <= p1; img_buffer[1] <= p2; img_buffer[2] <= p3;
                    img_buffer[3] <= p4; img_buffer[4] <= p5; img_buffer[5] <= p6;
                    img_buffer[6] <= p7; img_buffer[7] <= p8; img_buffer[8] <= p9;
                    
                    state <= S_D_HIDDEN;
                    loop_cnt <= 0; // Target 3 hidden neurons
                    acc_step <= 0;
                    // Start address for D-Hidden weights (Assuming offset 12 based on original code usage)
                    mem_addr <= 12; 
                end

                // Calculate D Hidden Layer (3 Neurons, 9 Inputs each)
                S_D_HIDDEN: begin
                    // Activation: Tanh (1)
                    pe_act_sel <= 1; 

                    // Step 0: Inputs 0-3
                    if (acc_step == 0) begin
                        pe_accumulate <= 0;
                        pe_partial_sum <= 0;
                        pe_x1 <= img_buffer[0]; pe_x2 <= img_buffer[1]; 
                        pe_x3 <= img_buffer[2]; pe_x4 <= img_buffer[3];
                        acc_step <= 1;
                    end 
                    // Step 1: Inputs 4-7
                    else if (acc_step == 1) begin
                        pe_accumulate <= 1;
                        pe_partial_sum <= pe_result; // Feed back previous result
                        pe_x1 <= img_buffer[4]; pe_x2 <= img_buffer[5]; 
                        pe_x3 <= img_buffer[6]; pe_x4 <= img_buffer[7];
                        acc_step <= 2;
                    end 
                    // Step 2: Input 8 (Pad rest with 0)
                    else if (acc_step == 2) begin
                        pe_accumulate <= 1;
                        pe_partial_sum <= pe_result;
                        pe_x1 <= img_buffer[8]; pe_x2 <= 0; 
                        pe_x3 <= 0; pe_x4 <= 0;
                        
                        // Latch result to hidden RAM
                        hidden_ram[loop_cnt] <= pe_result;
                        
                        // Prepare for next neuron or next state
                        if (loop_cnt == 2) begin
                            state <= S_D_OUTPUT;
                            loop_cnt <= 0;
                            acc_step <= 0;
                            mem_addr <= 15; // Address for Output neuron weights
                        end else begin
                            loop_cnt <= loop_cnt + 1;
                            mem_addr <= mem_addr + 1;
                            acc_step <= 0;
                        end
                    end
                end

                // Calculate D Output Layer (1 Neuron, 3 Inputs)
                S_D_OUTPUT: begin
                    // Activation: Sigmoid (2)
                    pe_act_sel <= 2;
                    
                    // Single step computation (3 inputs fit in one PE cycle)
                    pe_accumulate <= 0;
                    pe_partial_sum <= 0;
                    pe_x1 <= hidden_ram[0];
                    pe_x2 <= hidden_ram[1];
                    pe_x3 <= hidden_ram[2];
                    pe_x4 <= 0;

                    // Note: We need one cycle for the PE to compute the final result
                    if (acc_step == 0) begin
                        acc_step <= 1; 
                    end else begin
                        disc_out <= pe_result;
                        state <= S_DONE;
                    end
                end

                S_DONE: begin
                    done <= 1;
                    state <= S_IDLE;
                end
            endcase
        end
    end

endmodule

src/tb_discriminator.v
// File: tb_discriminator.v
`timescale 1ns/1ps

`include "discriminator_3x3.v"

module tb_discriminator;
    parameter DATA_WIDTH = 32;

    reg clk;
    reg rst;
    reg start;

    // 9 Pixel Inputs
    reg signed [DATA_WIDTH-1:0] p1, p2, p3;
    reg signed [DATA_WIDTH-1:0] p4, p5, p6;
    reg signed [DATA_WIDTH-1:0] p7, p8, p9;

    wire signed [DATA_WIDTH-1:0] disc_out;
    wire done;

    real float_prob;

    // Instantiate DUT
    discriminator_3x3 #(
        .DATA_WIDTH(DATA_WIDTH)
    ) u_dut (
        .clk(clk),
        .rst(rst),
        .start(start),
        .p1(p1), .p2(p2), .p3(p3),
        .p4(p4), .p5(p5), .p6(p6),
        .p7(p7), .p8(p8), .p9(p9),
        .disc_out(disc_out),
        .done(done)
    );

    // Clock Generation
    always #5 clk = ~clk;

    initial begin
        // Init
        clk = 0;
        rst = 1;
        start = 0;
        p1=0; p2=0; p3=0;
        p4=0; p5=0; p6=0;
        p7=0; p8=0; p9=0;

        $display("--- Isolated Discriminator Simulation ---");
        
        // Reset
        #50;
        @(negedge clk);
        rst = 0;

        // Apply Input Data (From Prompt)
        // Row 1
        p1 = 32'h00010000; p2 = 32'hffff0000; p3 = 32'h00010000;
        // Row 2
        p4 = 32'h0000ffff; p5 = 32'hffff0000; p6 = 32'h00010000;
        // Row 3
        p7 = 32'h0000ffff; p8 = 32'hffff0000; p9 = 32'h00010000;

        // Start Processing
        @(negedge clk);
        start = 1;
        @(negedge clk);
        start = 0;

        // Wait for completion
        wait(done);
        @(negedge clk);

        // Calculate Probability (Fixed Point 16.16 conversion)
        float_prob = $signed(disc_out) / 65536.0;

        // Display Results
        $display("\n[Input Image]");
        $display("[ %h  %h  %h ]", p1, p2, p3);
        $display("[ %h  %h  %h ]", p4, p5, p6);
        $display("[ %h  %h  %h ]", p7, p8, p9);

        $display("\n[Discriminator Output]");
        $display("Raw Hex: %h", disc_out);
        $display("Probability: %0.4f", float_prob);

        $finish;
    end

    // Waveform Dump
    initial begin
        $dumpfile("discriminator_isolated.vcd");
        $dumpvars(0, tb_discriminator);
    end

endmodule

src/discriminator_isolated.vcd
$date
	Fri Jan 09 21:04:28 2026
$end
$version
	Icarus Verilog
$end
$timescale
	1ps
$end
$scope module tb_discriminator $end
$var wire 1 ! done $end
$var wire 32 " disc_out [31:0] $end
$var parameter 32 # DATA_WIDTH $end
$var reg 1 $ clk $end
$var reg 32 % p1 [31:0] $end
$var reg 32 & p2 [31:0] $end
$var reg 32 ' p3 [31:0] $end
$var reg 32 ( p4 [31:0] $end
$var reg 32 ) p5 [31:0] $end
$var reg 32 * p6 [31:0] $end
$var reg 32 + p7 [31:0] $end
$var reg 32 , p8 [31:0] $end
$var reg 32 - p9 [31:0] $end
$var reg 1 . rst $end
$var reg 1 / start $end
$var real 1 0 float_prob $end
$scope module u_dut $end
$var wire 1 $ clk $end
$var wire 32 1 p1 [31:0] $end
$var wire 32 2 p2 [31:0] $end
$var wire 32 3 p3 [31:0] $end
$var wire 32 4 p4 [31:0] $end
$var wire 32 5 p5 [31:0] $end
$var wire 32 6 p6 [31:0] $end
$var wire 32 7 p7 [31:0] $end
$var wire 32 8 p8 [31:0] $end
$var wire 32 9 p9 [31:0] $end
$var wire 1 . rst $end
$var wire 1 / start $end
$var wire 32 : w4 [31:0] $end
$var wire 32 ; w3 [31:0] $end
$var wire 32 < w2 [31:0] $end
$var wire 32 = w1 [31:0] $end
$var wire 32 > pe_result [31:0] $end
$var wire 32 ? bias [31:0] $end
$var parameter 32 @ ADDR_WIDTH $end
$var parameter 32 A DATA_WIDTH $end
$var parameter 3 B S_DONE $end
$var parameter 3 C S_D_HIDDEN $end
$var parameter 3 D S_D_OUTPUT $end
$var parameter 3 E S_IDLE $end
$var parameter 3 F S_LOAD $end
$var reg 2 G acc_step [1:0] $end
$var reg 32 H disc_out [31:0] $end
$var reg 1 ! done $end
$var reg 4 I loop_cnt [3:0] $end
$var reg 10 J mem_addr [9:0] $end
$var reg 1 K pe_accumulate $end
$var reg 2 L pe_act_sel [1:0] $end
$var reg 32 M pe_partial_sum [31:0] $end
$var reg 32 N pe_x1 [31:0] $end
$var reg 32 O pe_x2 [31:0] $end
$var reg 32 P pe_x3 [31:0] $end
$var reg 32 Q pe_x4 [31:0] $end
$var reg 3 R state [2:0] $end
$scope module u_mem $end
$var wire 10 S addr [9:0] $end
$var wire 1 $ clk $end
$var parameter 32 T ADDR_WIDTH $end
$var parameter 32 U DATA_WIDTH $end
$var parameter 32 V MEM_DEPTH $end
$var reg 32 W bias [31:0] $end
$var reg 32 X w1 [31:0] $end
$var reg 32 Y w2 [31:0] $end
$var reg 32 Z w3 [31:0] $end
$var reg 32 [ w4 [31:0] $end
$upscope $end
$scope module u_pe $end
$var wire 2 \ act_sel [1:0] $end
$var wire 32 ] bias [31:0] $end
$var wire 1 $ clk $end
$var wire 32 ^ partial_sum_in [31:0] $end
$var wire 1 K pe_accumulate $end
$var wire 1 . rst $end
$var wire 32 _ w1 [31:0] $end
$var wire 32 ` w2 [31:0] $end
$var wire 32 a w3 [31:0] $end
$var wire 32 b w4 [31:0] $end
$var wire 32 c x1 [31:0] $end
$var wire 32 d x2 [31:0] $end
$var wire 32 e x3 [31:0] $end
$var wire 32 f x4 [31:0] $end
$var wire 32 g y_out [31:0] $end
$var wire 32 h tanh_out [31:0] $end
$var wire 32 i sig_out [31:0] $end
$var wire 64 j p4_long [63:0] $end
$var wire 64 k p3_long [63:0] $end
$var wire 64 l p2_long [63:0] $end
$var wire 64 m p1_long [63:0] $end
$var parameter 32 n DATA_WIDTH $end
$var reg 2 o act_sel_d1 [1:0] $end
$var reg 32 p p1_reg [31:0] $end
$var reg 32 q p2_reg [31:0] $end
$var reg 32 r p3_reg [31:0] $end
$var reg 32 s p4_reg [31:0] $end
$var reg 32 t sum_reg [31:0] $end
$var reg 32 u y_final_reg [31:0] $end
$scope module u_sig $end
$var wire 32 v rom_data [31:0] $end
$var wire 32 w z_in [31:0] $end
$var wire 32 x z_abs [31:0] $end
$var wire 10 y rom_address [9:0] $end
$var wire 1 z is_negative $end
$var wire 32 { a_sigmoid [31:0] $end
$var parameter 32 | ADDRESS_BITS $end
$var parameter 32 } DATA_WIDTH $end
$var parameter 32 ~ NEG_CLAMP_THRESHOLD $end
$var parameter 32 !" POS_CLAMP_THRESHOLD $end
$var parameter 42 "" ROM_DEPTH $end
$var parameter 32 #" SIGMOID_MAX_VAL $end
$var parameter 32 $" SIGMOID_MIN_VAL $end
$upscope $end
$scope module u_tanh $end
$var wire 32 %" rom_data [31:0] $end
$var wire 32 &" z_in [31:0] $end
$var wire 32 '" z_abs [31:0] $end
$var wire 10 (" rom_address [9:0] $end
$var wire 32 )" a_tanh [31:0] $end
$var parameter 32 *" ADDRESS_BITS $end
$var parameter 32 +" CLAMP_NEG $end
$var parameter 32 ," CLAMP_POS $end
$var parameter 32 -" DATA_WIDTH $end
$var parameter 32 ." MAX_NEGATIVE_VAL $end
$var parameter 32 /" MAX_POSITIVE_VAL $end
$var parameter 42 0" ROM_DEPTH $end
$upscope $end
$upscope $end
$upscope $end
$upscope $end
$enddefinitions $end
$comment Show the parameter values. $end
$dumpall
b10000000000 0"
b10000000000000000 /"
b11111111111111110000000000000000 ."
b100000 -"
b1100000000000000000 ,"
b11111111111110100000000000000000 +"
b1010 *"
b0 $"
b10000000000000000 #"
b10000000000 ""
b1100000000000000000 !"
b11111111111110100000000000000000 ~
b100000 }
b1010 |
b100000 n
b100000 V
b100000 U
b1010 T
b1 F
b0 E
b11 D
b10 C
b100 B
b100000 A
b1010 @
b100000 #
$end
#0
$dumpvars
bx )"
bx ("
bx '"
bx &"
bx %"
bx {
xz
bx y
bx x
bx w
bx v
bx u
bx t
bx s
bx r
bx q
bx p
bx o
bx m
bx l
bx k
bx j
bx i
bx h
bx g
bx f
bx e
bx d
bx c
b0 b
b0 a
b1011011110 `
b10111011 _
bx ^
b11111010100101010 ]
bx \
b0 [
b0 Z
b1011011110 Y
b10111011 X
b11111010100101010 W
b0 S
b0 R
bx Q
bx P
bx O
bx N
bx M
bx L
xK
b0 J
b0 I
b0 H
b0 G
b11111010100101010 ?
bx >
b10111011 =
b1011011110 <
b0 ;
b0 :
b0 9
b0 8
b0 7
b0 6
b0 5
b0 4
b0 3
b0 2
b0 1
r0 0
0/
1.
b0 -
b0 ,
b0 +
b0 *
b0 )
b0 (
b0 '
b0 &
b0 %
0$
b0 "
0!
$end
#5000
1$
#10000
0$
#15000
1$
#20000
0$
#25000
1$
#30000
0$
#35000
1$
#40000
0$
#45000
1$
#50000
b0 h
b0 )"
b1000000000000000 i
b1000000000000000 {
b1000000000000000 v
b0 y
b0 %"
b0 ("
0z
b0 x
b0 '"
b0 >
b0 g
b0 u
b0 o
b0 t
b0 w
b0 &"
b0 s
b0 r
b0 q
b0 p
b10000000000000000 -
b10000000000000000 9
b11111111111111110000000000000000 ,
b11111111111111110000000000000000 8
b1111111111111111 +
b1111111111111111 7
b10000000000000000 *
b10000000000000000 6
b11111111111111110000000000000000 )
b11111111111111110000000000000000 5
b1111111111111111 (
b1111111111111111 4
b10000000000000000 '
b10000000000000000 3
b11111111111111110000000000000000 &
b11111111111111110000000000000000 2
b10000000000000000 %
b10000000000000000 1
0.
0$
#55000
1$
#60000
1/
0$
#65000
b1 R
1$
#70000
0/
0$
#75000
b0 ?
b0 W
b0 ]
b11111111111111111010101101100100 :
b11111111111111111010101101100100 [
b11111111111111111010101101100100 b
b11111111111111111001011011110001 ;
b11111111111111111001011011110001 Z
b11111111111111111001011011110001 a
b110001101010000 <
b110001101010000 Y
b110001101010000 `
b11111111111111111011111001101000 =
b11111111111111111011111001101000 X
b11111111111111111011111001101000 _
b1100 J
b1100 S
b10 R
1$
#80000
0$
#85000
b1 G
b1111111111111111111111111111111110101011011001000101010010011100 j
b1111111111111111 Q
b1111111111111111 f
b1111111111111111111111111111111110010110111100010000000000000000 k
b10000000000000000 P
b10000000000000000 e
b1111111111111111111111111111111110011100101100000000000000000000 l
b11111111111111110000000000000000 O
b11111111111111110000000000000000 d
b1111111111111111111111111111111110111110011010000000000000000000 m
b10000000000000000 N
b10000000000000000 c
b0 M
b0 ^
0K
b1 L
b1 \
1$
#90000
0$
#95000
b10 G
b1010100100111000000000000000000 j
b11111111111111110000000000000000 Q
b11111111111111110000000000000000 f
b1111111111111111111111111111111110010110111100010110100100001111 k
b1111111111111111 P
b1111111111111111 e
b1100011010100000000000000000000 l
b10000000000000000 O
b10000000000000000 d
b1000001100110000000000000000000 m
b11111111111111110000000000000000 N
b11111111111111110000000000000000 c
1K
1$
#100000
0$
#105000
b100010111010111 :
b100010111010111 [
b100010111010111 b
b11111111111111111011011110110011 ;
b11111111111111111011011110110011 Z
b11111111111111111011011110110011 a
b11111111111111111010100100001101 <
b11111111111111111010100100001101 Y
b11111111111111111010100100001101 `
b101110100110001 =
b101110100110001 X
b101110100110001 _
b0 G
b1101 J
b1101 S
b1 I
b0 j
b0 Q
b0 f
b0 k
b0 P
b0 e
b0 l
b0 O
b0 d
b1011101001100010000000000000000 m
b10000000000000000 N
b10000000000000000 c
1$
#110000
0$
#115000
b1 G
b1000101110101101011101000101001 j
b1111111111111111 Q
b1111111111111111 f
b1111111111111111111111111111111110110111101100110000000000000000 k
b10000000000000000 P
b10000000000000000 e
b1010110111100110000000000000000 l
b11111111111111110000000000000000 O
b11111111111111110000000000000000 d
0K
1$
#120000
0$
#125000
b10 G
b1111111111111111111111111111111110111010001010010000000000000000 j
b11111111111111110000000000000000 Q
b11111111111111110000000000000000 f
b1111111111111111111111111111111110110111101100110100100001001101 k
b1111111111111111 P
b1111111111111111 e
b1111111111111111111111111111111110101001000011010000000000000000 l
b10000000000000000 O
b10000000000000000 d
b1111111111111111111111111111111110100010110011110000000000000000 m
b11111111111111110000000000000000 N
b11111111111111110000000000000000 c
1K
1$
#130000
0$
#135000
b101101100001111000 ?
b101101100001111000 W
b101101100001111000 ]
b0 :
b0 [
b0 b
b0 ;
b0 Z
b0 a
b0 <
b0 Y
b0 `
b11111111111111111010111110111111 =
b11111111111111111010111110111111 X
b11111111111111111010111110111111 _
b0 G
b1110 J
b1110 S
b10 I
b0 j
b0 Q
b0 f
b0 k
b0 P
b0 e
b0 l
b0 O
b0 d
b1111111111111111111111111111111110101111101111110000000000000000 m
b10000000000000000 N
b10000000000000000 c
1$
#140000
0$
#145000
b1 G
b1111111111111111 Q
b1111111111111111 f
b10000000000000000 P
b10000000000000000 e
b11111111111111110000000000000000 O
b11111111111111110000000000000000 d
0K
1$
#150000
0$
#155000
b10 G
b11111111111111110000000000000000 Q
b11111111111111110000000000000000 f
b1111111111111111 P
b1111111111111111 e
b10000000000000000 O
b10000000000000000 d
b1010000010000010000000000000000 m
b11111111111111110000000000000000 N
b11111111111111110000000000000000 c
1K
1$
#160000
0$
#165000
b0 ?
b0 W
b0 ]
b11111111111111111011111011000111 :
b11111111111111111011111011000111 [
b11111111111111111011111011000111 b
b11111111111111111101000001100011 ;
b11111111111111111101000001100011 Z
b11111111111111111101000001100011 a
b11010010011101 <
b11010010011101 Y
b11010010011101 `
b11111111111111111001010111011000 =
b11111111111111111001010111011000 X
b11111111111111111001010111011000 _
b1111 J
b1111 S
b0 G
b0 I
b11 R
b0 Q
b0 f
b0 P
b0 e
b0 O
b0 d
b1111111111111111111111111111111110010101110110000000000000000000 m
b10000000000000000 N
b10000000000000000 c
1$
#170000
0$
#175000
b1 G
b0 m
b0 N
b0 c
0K
b10 L
b10 \
1$
#180000
0$
#185000
b100 R
1$
#190000
0$
#195000
b0 R
1!
1$
