src/sigmoid_lut.v
// File         : sigmoid_lut.v
// Description  : Sigmoid LUT for Q16.16 format (High Precision)

module sigmoid_lut (
    input  signed [31:0] z_in,   // Q16.16
    output signed [31:0] a_sigmoid // Q16.16
);
    localparam ADDRESS_BITS = 10;
    localparam DATA_WIDTH   = 32;
    localparam ROM_DEPTH    = 1 << ADDRESS_BITS;

    // Saturation values (Q16.16)
    localparam signed [31:0] SIGMOID_MAX_VAL = 32'h00010000; // 1.0
    localparam signed [31:0] SIGMOID_MIN_VAL = 32'h00000000; // 0.0

    // Clamp input magnitude at +/-6.0 (Q16.16)
    // LUT covers up to 8.0, so 6.0 is safe.
    localparam signed [31:0] POS_CLAMP_THRESHOLD = 32'h00060000; // +6.0
    localparam signed [31:0] NEG_CLAMP_THRESHOLD = 32'hFFFA0000; // -6.0

    reg [DATA_WIDTH-1:0] SIGMOID_ROM [0:ROM_DEPTH-1];

    initial begin
        // Ensure path matches Python script output
        $readmemh("./mem/sigmoid_lut_mem.hex", SIGMOID_ROM);
    end

    // Use symmetry: compute abs(z) for lookup
    // Sigmoid(-x) = 1 - Sigmoid(x)
    wire is_negative = z_in[31];
    wire signed [31:0] z_abs = is_negative ? -z_in : z_in;

    // Address bits selected from fractional range
    // Bit 9 corresponds to 2^-7 (0.0078125)
    // Slice [18:9] = 10 bits
    wire [ADDRESS_BITS-1:0] rom_address = z_abs[18:9];
    
    wire signed [31:0] rom_data = SIGMOID_ROM[rom_address];

    assign a_sigmoid =
        (z_in >= POS_CLAMP_THRESHOLD) ? SIGMOID_MAX_VAL :
        (z_in <= NEG_CLAMP_THRESHOLD) ? SIGMOID_MIN_VAL :
        (is_negative ? (SIGMOID_MAX_VAL - rom_data) : rom_data);

endmodule

src/tanh_lut.v
// File: tanh_lut.v
// Description: Tanh LUT for Q1.15.16 format (32-bit).

module tanh_lut (
    input  signed [31:0] z_in,   // Input Q16.16
    output signed [31:0] a_tanh  // Output Q16.16
);
    localparam ADDRESS_BITS = 10;
    localparam DATA_WIDTH   = 32;
    localparam ROM_DEPTH    = 1 << ADDRESS_BITS;

    // Q16.16 Constants
    // 1.0 = 65536 (0x00010000)
    localparam MAX_POSITIVE_VAL = 32'h00010000;
    localparam MAX_NEGATIVE_VAL = 32'hFFFF0000; // -1.0
    
    // Clamping Thresholds (+/- 6.0)
    // 6.0 * 65536 = 393216 = 0x00060000
    localparam POS_CLAMP_THRESHOLD = 32'h00060000;
    localparam NEG_CLAMP_THRESHOLD = 32'hFFAA0000; // -6.0 (Two's comp roughly) 
    // Actually -6.0 in hex: ~0x00060000 + 1 = 0xFFFA0000
    // Let's use rigorous hex for -6.0:
    // 6.0 = 0x00060000. -6.0 = 0xFFFA0000.
    
    localparam CLAMP_POS = 32'h00060000;
    localparam CLAMP_NEG = 32'hFFFA0000; 

    reg [DATA_WIDTH-1:0] TANH_ROM [0:ROM_DEPTH-1];

    initial begin
        // Ensure you generated this file using the Python script provided
        $readmemh("mem/tanh_lut_mem.hex", TANH_ROM); 
    end

    // --- Address Generation ---
    // Q16.16 format: [31] Sign, [30:16] Integer, [15:0] Fraction.
    // Bit 16 is 2^0. Bit 13 is 2^-3 (0.125).
    // To match previous resolution logic, we look at the integer and high fraction bits.
    // We take the absolute value for addressing if the ROM is 0..Max.
    // However, Tanh is odd symmetric. We often read |z| and flip sign of output if z < 0.
    // Or, if the ROM contains data for positive inputs:
    
    wire signed [31:0] z_abs = (z_in[31]) ? -z_in : z_in;
    
    // Slice [22:13] gives us 10 bits.
    // Max index 1023 corresponds to 1023 * 0.125 = 127.8 (covers the 6.0 clamp range easily).
    wire [ADDRESS_BITS-1:0] rom_address = z_abs[18:9];
    
    wire signed [31:0] rom_data = TANH_ROM[rom_address];

    // --- Output Logic ---
    assign a_tanh = 
        (z_in >= $signed(CLAMP_POS)) ? MAX_POSITIVE_VAL :
        (z_in <= $signed(CLAMP_NEG)) ? MAX_NEGATIVE_VAL :
        // Symmetry: Tanh(-x) = -Tanh(x)
        (z_in[31] ? -rom_data : rom_data);

endmodule

src/pe_neuron.v
// File         : pe_neuron.v
// Description  : Processing Element (Neuron) module

`timescale 1ns/1ps
`include "sigmoid_lut.v"
`include "tanh_lut.v"

module pe_neuron #(
    parameter DATA_WIDTH = 32
) (
    input wire clk,
    input wire rst,
    input signed [DATA_WIDTH-1:0] x1, x2, x3, x4,
    input signed [DATA_WIDTH-1:0] w1, w2, w3, w4,
    input signed [DATA_WIDTH-1:0] bias,
    
    input wire pe_accumulate,
    input wire signed [DATA_WIDTH-1:0] partial_sum_in,
    input wire [1:0] act_sel,

    output reg signed [DATA_WIDTH-1:0] y_out
);
    // Multiply: Q16.16 inputs * Q16.16 weights -> Q32.32 products
    wire signed [2*DATA_WIDTH-1:0] p1_long = x1 * w1;
    wire signed [2*DATA_WIDTH-1:0] p2_long = x2 * w2;
    wire signed [2*DATA_WIDTH-1:0] p3_long = x3 * w3;
    wire signed [2*DATA_WIDTH-1:0] p4_long = x4 * w4;

    // Shift right by 16 to get back to Q16.16
    wire signed [DATA_WIDTH-1:0] p1 = p1_long >>> 16;
    wire signed [DATA_WIDTH-1:0] p2 = p2_long >>> 16;
    wire signed [DATA_WIDTH-1:0] p3 = p3_long >>> 16;
    wire signed [DATA_WIDTH-1:0] p4 = p4_long >>> 16;

    // Sum products and bias. If accumulating, add partial_sum_in.
    reg signed [DATA_WIDTH-1:0] sum_raw;
    always @(*) begin
        sum_raw = p1 + p2 + p3 + p4 + bias;
        if (pe_accumulate) begin
            sum_raw = sum_raw + partial_sum_in;
        end
    end

    // Convert summed Q16.16 value using LUTs (tanh and sigmoid)
    wire signed [31:0] tanh_out_32, sig_out_32;

    // Pass full 32-bit Q16.16 sum to the LUTs
    tanh_lut u_tanh (
        .z_in(sum_raw),
        .a_tanh(tanh_out_32)
    );

    sigmoid_lut u_sig (
        .z_in(sum_raw), 
        .a_sigmoid(sig_out_32)
    );

    // Select activation output (0=tanh, 1=sigmoid, default=linear)
    always @(*) begin
        case (act_sel)
            2'd0: y_out = tanh_out_32; // Tanh
            2'd1: y_out = sig_out_32;  // Sigmoid
            default: y_out = sum_raw;  // Linear (passthrough)
        endcase
    end

endmodule

src/memory.v
// File: memory.v
// Description: memory module reading weights and biases from hex files

`timescale 1ns/1ps

module memory #(
    parameter DATA_WIDTH = 32,
    parameter ADDR_WIDTH = 10,
    parameter MEM_DEPTH  = 32
)(
    input wire clk,
    input wire [ADDR_WIDTH-1:0] addr,
    output reg signed [DATA_WIDTH-1:0] w1, w2, w3, w4, bias
);

    // Internal RAM
    reg [DATA_WIDTH-1:0] mem_w1   [0:MEM_DEPTH-1];
    reg [DATA_WIDTH-1:0] mem_w2   [0:MEM_DEPTH-1];
    reg [DATA_WIDTH-1:0] mem_w3   [0:MEM_DEPTH-1];
    reg [DATA_WIDTH-1:0] mem_w4   [0:MEM_DEPTH-1];
    reg [DATA_WIDTH-1:0] mem_bias [0:MEM_DEPTH-1];

    // Load contents from hex files
    initial begin
        $readmemh("mem/w1.hex",   mem_w1);
        $readmemh("mem/w2.hex",   mem_w2);
        $readmemh("mem/w3.hex",   mem_w3);
        $readmemh("mem/w4.hex",   mem_w4);
        $readmemh("mem/bias.hex", mem_bias);
    end

    // Combinational read
    always @(*) begin
        if (addr < MEM_DEPTH) begin
            w1   = mem_w1[addr];
            w2   = mem_w2[addr];
            w3   = mem_w3[addr];
            w4   = mem_w4[addr];
            bias = mem_bias[addr];
        end else begin
            w1 = 0; w2 = 0; w3 = 0; w4 = 0; bias = 0;
        end
    end

endmodule

src/gan3x3.v
`timescale 1ns/1ps

`include "memory.v"
`include "pe_neuron.v"

module gan3x3 #(
    parameter DATA_WIDTH = 32
) (
    input wire clk,
    input wire rst,
    input wire start,
    input wire signed [DATA_WIDTH-1:0] noise_in1,
    input wire signed [DATA_WIDTH-1:0] noise_in2,
    output reg signed [DATA_WIDTH-1:0] disc_out,
    output reg done
);
    // RAM
    reg signed [DATA_WIDTH-1:0] internal_ram [0:15];
    reg [9:0] mem_addr;

    // Weights & PE signals
    wire signed [DATA_WIDTH-1:0] w1, w2, w3, w4, bias;
    reg signed [DATA_WIDTH-1:0] pe_x1, pe_x2, pe_x3, pe_x4;
    reg signed [DATA_WIDTH-1:0] pe_partial_sum;
    wire signed [DATA_WIDTH-1:0] pe_result;

    // Control
    reg pe_accumulate;
    reg [1:0] pe_act_sel; // 0 -> tanh, 1 -> sigmoid

    memory #(.DATA_WIDTH(DATA_WIDTH)) u_mem (
        .clk (clk), .addr(mem_addr),
        .w1(w1), .w2(w2), .w3(w3), .w4(w4), .bias(bias)
    );

    pe_neuron #(.DATA_WIDTH(DATA_WIDTH)) u_pe (
        .clk(clk),
        .rst(rst),
        .x1(pe_x1), .x2(pe_x2), .x3(pe_x3), .x4(pe_x4),
        .w1(w1), .w2(w2), .w3(w3), .w4(w4),
        .bias(bias),
        .pe_accumulate(pe_accumulate),
        .partial_sum_in(pe_partial_sum),
        .act_sel(pe_act_sel),
        .y_out(pe_result)
    );

    // States
    localparam S_IDLE = 3'd0;
    localparam S_GEN_HIDDEN = 3'd1;
    localparam S_GEN_OUTPUT = 3'd2;
    localparam S_DIS_HIDDEN = 3'd3;
    localparam S_DIS_OUTPUT = 3'd4;
    localparam S_DONE = 3'd5;

    reg [2:0] state;
    reg [3:0] loop_cnt;
    reg [1:0] acc_step;

    always @(posedge clk or negedge rst) begin
        if (!rst) begin
            state <= S_IDLE;
            mem_addr <= 0;
            done <= 0;
            loop_cnt <= 0;
            acc_step <= 0;
            pe_partial_sum <= 0;
            pe_x1 <= 0;
            pe_x2 <= 0;
            pe_x3 <= 0;
            pe_x4 <= 0;
            pe_accumulate <= 0;
            pe_act_sel <= 0;
        end else begin
            case (state)
                S_IDLE: begin
                    done <= 0;
                    if(start) begin
                        state <= S_GEN_HIDDEN;
                        mem_addr <= 0;
                        loop_cnt <= 0;
                        
                        // --- FIX 1: Pre-load inputs for first layer ---
                        pe_x1 <= noise_in1;
                        pe_x2 <= noise_in2;
                        pe_x3 <= 0;
                        pe_x4 <= 0;
                        pe_act_sel <= 0; // Tanh
                        pe_accumulate <= 0;
                        // ----------------------------------------------
                    end
                end
            
                S_GEN_HIDDEN: begin
                    // Inputs are already valid from previous cycle (IDLE or Loop)
                    
                    internal_ram[loop_cnt] <= pe_result;

                    if (loop_cnt == 2) begin
                        state <= S_GEN_OUTPUT;
                        loop_cnt <= 0;
                        mem_addr <= mem_addr+1;
                        
                        // --- FIX 2: Pre-load inputs for Generator Output Layer ---
                        // Note: internal_ram[2] is being written NOW (pe_result), so we bypass
                        pe_x1 <= internal_ram[0];
                        pe_x2 <= internal_ram[1];
                        pe_x3 <= pe_result; // Bypass: Use current result for x3
                        pe_x4 <= 0;
                        pe_act_sel <= 0; // Tanh
                        // ---------------------------------------------------------
                    end else begin
                        loop_cnt <= loop_cnt+1;
                        mem_addr <= mem_addr+1;
                        // Keep inputs stable (Noise) for next neuron
                        pe_x1 <= noise_in1;
                        pe_x2 <= noise_in2;
                    end
                end

                S_GEN_OUTPUT: begin
                    // Cycle 0: Inputs are valid (Pre-loaded from GEN_HIDDEN)
                    // Cycle 1+: Inputs must be re-loaded from RAM
                    
                    internal_ram[3+loop_cnt] <= pe_result;
                    
                    if (loop_cnt == 8) begin
                        state <= S_DIS_HIDDEN;
                        loop_cnt <= 0;
                        acc_step <= 0;
                        mem_addr <= mem_addr+1;
                        
                        // --- FIX 3: Pre-load inputs for Discriminator Hidden ---
                        // Note: internal_ram[11] is being written NOW (pe_result)
                        // This corresponds to Pixel 9.
                        // Discrim inputs: Pixels 1,2,3,4. These are already in RAM [3]..[6]
                        pe_x1 <= internal_ram[3];
                        pe_x2 <= internal_ram[4];
                        pe_x3 <= internal_ram[5];
                        pe_x4 <= internal_ram[6];
                        pe_accumulate <= 0;
                        // --------------------------------------------------------
                    end else begin
                        loop_cnt <= loop_cnt + 1;
                        mem_addr <= mem_addr + 1;
                        
                        // Sustain inputs for next pixel? 
                        // Wait, for Generator Output, the inputs (Hidden Layer) 
                        // are THE SAME for every pixel!
                        // So we don't need to change pe_x here.
                        // However, we must ensure we didn't clear them.
                        // Re-assert them just in case:
                        pe_x1 <= internal_ram[0];
                        pe_x2 <= internal_ram[1];
                        pe_x3 <= internal_ram[2];
                    end
                end

                S_DIS_HIDDEN: begin
                    // Discriminator Hidden logic implies accumulation over 3 passes.
                    // Passes use different input sets from RAM.
                    
                    case (acc_step)
                        0: begin
                            // Current inputs were pre-loaded in previous state (S_GEN_OUTPUT end)
                            // Just save partial sum
                            pe_partial_sum <= pe_result;
                            
                            // Prep next inputs
                            acc_step <= 1;
                            mem_addr <= mem_addr + 1;
                            
                            pe_x1 <= internal_ram[7];
                            pe_x2 <= internal_ram[8];
                            pe_x3 <= internal_ram[9];
                            pe_x4 <= internal_ram[10]; // Pixel 8
                            pe_accumulate <= 1;
                        end

                        1: begin
                            pe_partial_sum <= pe_result;
                            
                            acc_step <= 2;
                            mem_addr <= mem_addr + 1;
                            
                            pe_x1 <= internal_ram[11]; // Pixel 9
                            pe_x2 <= 0;
                            pe_x3 <= 0;
                            pe_x4 <= 0;
                            pe_accumulate <= 1;
                        end
                        
                        2: begin
                            // Final pass for this neuron
                            internal_ram[12+loop_cnt] <= pe_result;
                            
                            if(loop_cnt == 2) begin
                                state <= S_DIS_OUTPUT;
                                loop_cnt <= 0;
                                mem_addr <= mem_addr + 1;
                                
                                // --- FIX 4: Pre-load inputs for Discrim Output ---
                                // Discrim Output uses Discrim Hidden results (RAM 12, 13, 14)
                                // RAM 14 is being written NOW (pe_result)
                                pe_x1 <= internal_ram[12];
                                pe_x2 <= internal_ram[13];
                                pe_x3 <= pe_result; // Bypass
                                pe_x4 <= 0;
                                pe_act_sel <= 1; // Sigmoid
                                pe_accumulate <= 0;
                                // -------------------------------------------------
                            end else begin
                                loop_cnt <= loop_cnt+1;
                                acc_step <= 0;
                                mem_addr <= mem_addr+1;
                                
                                // Prepare inputs for Next Neuron (Pass 0)
                                pe_x1 <= internal_ram[3];
                                pe_x2 <= internal_ram[4];
                                pe_x3 <= internal_ram[5];
                                pe_x4 <= internal_ram[6];
                                pe_accumulate <= 0;
                            end
                        end
                    endcase
                end

                S_DIS_OUTPUT: begin
                    // Inputs valid from pre-load
                    disc_out <= pe_result;
                    state <= S_DONE;
                end

                S_DONE: begin
                    done <= 1;
                    if (!start) state <= S_IDLE;
                end
            endcase
        end
    end

endmodule

src/tb_gan3x3.v
// File: tb_gan3x3.v
`timescale 1ns/1ps
`include "gan3x3.v"

module tb_gan3x3;

    parameter DATA_WIDTH = 32;
    real float_out; 

    reg clk;
    reg rst;
    reg start;
    reg signed [DATA_WIDTH-1:0] noise_in1;
    reg signed [DATA_WIDTH-1:0] noise_in2;

    wire signed [DATA_WIDTH-1:0] disc_out;
    wire done;

    gan3x3 #(.DATA_WIDTH(DATA_WIDTH)) u_dut (
        .clk(clk),
        .rst(rst),
        .start(start),
        .noise_in1(noise_in1),
        .noise_in2(noise_in2),
        .disc_out(disc_out),
        .done(done)
    );

    // Clock Generation
    always #5 clk = ~clk;

    initial begin
        clk = 0;
        rst = 0;
        start = 0;
        noise_in1 = 0;
        noise_in2 = 0;

        $display("--- Simulation Start ---");

        // Reset Sequence
        #50;
        @(negedge clk);
        rst = 1; // Release Reset
        
        // --------------------------------------------------------
        // Test Case 1: Noise [0.5, -0.2]
        // --------------------------------------------------------
        #20;
        @(negedge clk);
        $display("\n--- Test Case 1: Noise [0.5, -0.2] ---");
        noise_in1 = 32'h0000_FFFF;  // 0.5
        noise_in2 = 32'hFFFF_CCCD;  // -0.2
        start = 1;
        
        @(negedge clk);
        start = 0;

        wait(done);
        @(negedge clk);

        // --- Print Results for Test Case 1 ---
        $display("Done Signal Received!");
        
        // 1. Generator Hidden Layer (G2) - stored in RAM [0..2]
        $display("\n[G2] Generator Hidden Layer Outputs:");
        $display("N1: %h", u_dut.internal_ram[0]);
        $display("N2: %h", u_dut.internal_ram[1]);
        $display("N3: %h", u_dut.internal_ram[2]);

        // 2. Generator Output Layer (G3) - stored in RAM [3..11]
        $display("\n[G3] Generated Fake Image (3x3):");
        $display("[ %h  %h  %h ]", u_dut.internal_ram[3], u_dut.internal_ram[4], u_dut.internal_ram[5]);
        $display("[ %h  %h  %h ]", u_dut.internal_ram[6], u_dut.internal_ram[7], u_dut.internal_ram[8]);
        $display("[ %h  %h  %h ]", u_dut.internal_ram[9], u_dut.internal_ram[10], u_dut.internal_ram[11]);

        // 3. Discriminator Hidden Layer (D2) - stored in RAM [12..14]
        $display("\n[D2] Discriminator Hidden Layer Outputs:");
        $display("N1: %h", u_dut.internal_ram[12]);
        $display("N2: %h", u_dut.internal_ram[13]);
        $display("N3: %h", u_dut.internal_ram[14]);

        // 4. Final Output
        float_out = $signed(disc_out) / 65536.0;
        $display("\n[D3] Discriminator Final Output:");
        $display("Raw Hex: %h", disc_out);
        $display("Probability: %0.4f", float_out);

        // --------------------------------------------------------
        // Test Case 2: Noise [-1.0, 1.0]
        // --------------------------------------------------------
        #50;
        @(negedge clk); 
        $display("\n--- Test Case 2: Noise [-1.0, 1.0] ---");
        noise_in1 = 32'hFFFF_0000; // -1.0
        noise_in2 = 32'h0001_0000; //  1.0
        start = 1;
        
        @(negedge clk);
        start = 0;
        
        wait(done);
        @(negedge clk);
        
        // --- Print Results for Test Case 2 ---
        
        // 1. Generator Hidden Layer (G2)
        $display("\n[G2] Generator Hidden Layer Outputs:");
        $display("N1: %h", u_dut.internal_ram[0]);
        $display("N2: %h", u_dut.internal_ram[1]);
        $display("N3: %h", u_dut.internal_ram[2]);
        
        // 2. Generator Output Layer (G3)
        $display("\n[G3] Generated Fake Image (3x3):");
        $display("[ %h  %h  %h ]", u_dut.internal_ram[3], u_dut.internal_ram[4], u_dut.internal_ram[5]);
        $display("[ %h  %h  %h ]", u_dut.internal_ram[6], u_dut.internal_ram[7], u_dut.internal_ram[8]);
        $display("[ %h  %h  %h ]", u_dut.internal_ram[9], u_dut.internal_ram[10], u_dut.internal_ram[11]);

        // 3. Discriminator Hidden Layer (D2)
        $display("\n[D2] Discriminator Hidden Layer Outputs:");
        $display("N1: %h", u_dut.internal_ram[12]);
        $display("N2: %h", u_dut.internal_ram[13]);
        $display("N3: %h", u_dut.internal_ram[14]);

        // 4. Final Output
        float_out = $signed(disc_out) / 65536.0;
        $display("\n[D3] Discriminator Final Output:");
        $display("Raw Hex: %h", disc_out);
        $display("Probability: %0.4f", float_out);

        #100;
        $display("\n--- Simulation Complete ---");
        $finish;
    end

    // Dump Waveforms
    initial begin
        $dumpfile("gan_waveform.vcd");
        $dumpvars(0, tb_gan3x3);
    end

endmodule

src/gan_waveform.vcd
$date
	Sat Dec 20 21:11:33 2025
$end
$version
	Icarus Verilog
$end
$timescale
	1ps
$end
$scope module tb_gan3x3 $end
$var wire 1 ! done $end
$var wire 32 " disc_out [31:0] $end
$var parameter 32 # DATA_WIDTH $end
$var reg 1 $ clk $end
$var reg 32 % noise_in1 [31:0] $end
$var reg 32 & noise_in2 [31:0] $end
$var reg 1 ' rst $end
$var reg 1 ( start $end
$var real 1 ) float_out $end
$scope module u_dut $end
$var wire 1 $ clk $end
$var wire 32 * noise_in1 [31:0] $end
$var wire 32 + noise_in2 [31:0] $end
$var wire 1 ' rst $end
$var wire 1 ( start $end
$var wire 32 , w4 [31:0] $end
$var wire 32 - w3 [31:0] $end
$var wire 32 . w2 [31:0] $end
$var wire 32 / w1 [31:0] $end
$var wire 32 0 pe_result [31:0] $end
$var wire 32 1 bias [31:0] $end
$var parameter 32 2 DATA_WIDTH $end
$var parameter 3 3 S_DIS_HIDDEN $end
$var parameter 3 4 S_DIS_OUTPUT $end
$var parameter 3 5 S_DONE $end
$var parameter 3 6 S_GEN_HIDDEN $end
$var parameter 3 7 S_GEN_OUTPUT $end
$var parameter 3 8 S_IDLE $end
$var reg 2 9 acc_step [1:0] $end
$var reg 32 : disc_out [31:0] $end
$var reg 1 ! done $end
$var reg 4 ; loop_cnt [3:0] $end
$var reg 10 < mem_addr [9:0] $end
$var reg 1 = pe_accumulate $end
$var reg 2 > pe_act_sel [1:0] $end
$var reg 32 ? pe_partial_sum [31:0] $end
$var reg 32 @ pe_x1 [31:0] $end
$var reg 32 A pe_x2 [31:0] $end
$var reg 32 B pe_x3 [31:0] $end
$var reg 32 C pe_x4 [31:0] $end
$var reg 3 D state [2:0] $end
$scope module u_mem $end
$var wire 10 E addr [9:0] $end
$var wire 1 $ clk $end
$var parameter 32 F ADDR_WIDTH $end
$var parameter 32 G DATA_WIDTH $end
$var reg 32 H bias [31:0] $end
$var reg 32 I w1 [31:0] $end
$var reg 32 J w2 [31:0] $end
$var reg 32 K w3 [31:0] $end
$var reg 32 L w4 [31:0] $end
$upscope $end
$scope module u_pe $end
$var wire 2 M act_sel [1:0] $end
$var wire 32 N bias [31:0] $end
$var wire 1 $ clk $end
$var wire 32 O partial_sum_in [31:0] $end
$var wire 1 = pe_accumulate $end
$var wire 1 ' rst $end
$var wire 32 P w1 [31:0] $end
$var wire 32 Q w2 [31:0] $end
$var wire 32 R w3 [31:0] $end
$var wire 32 S w4 [31:0] $end
$var wire 32 T x1 [31:0] $end
$var wire 32 U x2 [31:0] $end
$var wire 32 V x3 [31:0] $end
$var wire 32 W x4 [31:0] $end
$var wire 32 X tanh_out_32 [31:0] $end
$var wire 32 Y sig_out_32 [31:0] $end
$var wire 64 Z p4_long [63:0] $end
$var wire 32 [ p4 [31:0] $end
$var wire 64 \ p3_long [63:0] $end
$var wire 32 ] p3 [31:0] $end
$var wire 64 ^ p2_long [63:0] $end
$var wire 32 _ p2 [31:0] $end
$var wire 64 ` p1_long [63:0] $end
$var wire 32 a p1 [31:0] $end
$var parameter 32 b DATA_WIDTH $end
$var reg 32 c sum_raw [31:0] $end
$var reg 32 d y_out [31:0] $end
$scope module u_sig $end
$var wire 32 e rom_data [31:0] $end
$var wire 32 f z_in [31:0] $end
$var wire 32 g z_abs [31:0] $end
$var wire 10 h rom_address [9:0] $end
$var wire 1 i is_negative $end
$var wire 32 j a_sigmoid [31:0] $end
$var parameter 32 k ADDRESS_BITS $end
$var parameter 32 l DATA_WIDTH $end
$var parameter 32 m NEG_CLAMP_THRESHOLD $end
$var parameter 32 n POS_CLAMP_THRESHOLD $end
$var parameter 42 o ROM_DEPTH $end
$var parameter 32 p SIGMOID_MAX_VAL $end
$var parameter 32 q SIGMOID_MIN_VAL $end
$upscope $end
$scope module u_tanh $end
$var wire 32 r rom_data [31:0] $end
$var wire 32 s z_in [31:0] $end
$var wire 32 t z_abs [31:0] $end
$var wire 10 u rom_address [9:0] $end
$var wire 32 v a_tanh [31:0] $end
$var parameter 32 w ADDRESS_BITS $end
$var parameter 32 x CLAMP_NEG $end
$var parameter 32 y CLAMP_POS $end
$var parameter 32 z DATA_WIDTH $end
$var parameter 32 { MAX_NEGATIVE_VAL $end
$var parameter 32 | MAX_POSITIVE_VAL $end
$var parameter 32 } NEG_CLAMP_THRESHOLD $end
$var parameter 32 ~ POS_CLAMP_THRESHOLD $end
$var parameter 42 !" ROM_DEPTH $end
$upscope $end
$upscope $end
$upscope $end
$upscope $end
$enddefinitions $end
$comment Show the parameter values. $end
$dumpall
b10000000000 !"
b1100000000000000000 ~
b11111111101010100000000000000000 }
b10000000000000000 |
b11111111111111110000000000000000 {
b100000 z
b1100000000000000000 y
b11111111111110100000000000000000 x
b1010 w
b0 q
b10000000000000000 p
b10000000000 o
b1100000000000000000 n
b11111111111110100000000000000000 m
b100000 l
b1010 k
b100000 b
b100000 G
b1010 F
b0 8
b10 7
b1 6
b101 5
b100 4
b11 3
b100000 2
b100000 #
$end
#0
$dumpvars
b1111011111111010 v
b100001001 u
b100001001110010001 t
b100001001110010001 s
b1111011111111010 r
b1110000101111011 j
0i
b10000 h
b100001001110010001 g
b100001001110010001 f
b1110000101111011 e
b1111011111111010 d
b100001001110010001 c
b0 a
b0 `
b0 _
b0 ^
b0 ]
b0 \
b0 [
b0 Z
b1110000101111011 Y
b1111011111111010 X
b0 W
b0 V
b0 U
b0 T
b0 S
b0 R
b1010011001 Q
b1101101000 P
b0 O
b100001001110010001 N
b0 M
b0 L
b0 K
b1010011001 J
b1101101000 I
b100001001110010001 H
b0 E
b0 D
b0 C
b0 B
b0 A
b0 @
b0 ?
b0 >
0=
b0 <
b0 ;
bx :
b0 9
b100001001110010001 1
b1111011111111010 0
b1101101000 /
b1010011001 .
b0 -
b0 ,
b0 +
b0 *
r0 )
0(
0'
b0 &
b0 %
0$
bx "
0!
$end
#5000
1$
#10000
0$
#15000
1$
#20000
0$
#25000
1$
#30000
0$
#35000
1$
#40000
0$
#45000
1$
#50000
1'
0$
#55000
1$
#60000
0$
#65000
1$
#70000
1(
b11111111111111111100110011001101 &
b11111111111111111100110011001101 +
b1111111111111111 %
b1111111111111111 *
0$
#75000
b1111100000111001 0
b1111100000111001 d
b1111100000111001 X
b1111100000111001 v
b1111100000111001 r
b100001011 u
b100001011001110011 g
b100001011001110011 t
b100001011001110011 c
b100001011001110011 f
b100001011001110011 s
b11111111111111111111111101111011 _
b1101100111 a
b1111111111111111111111111111111111111111011110110000000010000101 ^
b11111111111111111100110011001101 A
b11111111111111111100110011001101 U
b11011001111111110010011000 `
b1111111111111111 @
b1111111111111111 T
b1 D
1$
#80000
0(
0$
#85000
b11111111111111111110111000001000 0
b11111111111111111110111000001000 d
b1000000000000000 Y
b1000000000000000 j
b11111111111111111110111000001000 X
b11111111111111111110111000001000 v
b1000000000000000 e
b0 h
b1000111111000 r
b1001 u
1i
b1001110111011 g
b1001110111011 t
b11111111111111111111111100111100 _
b10000000101101 a
b11111111111111111110110001000101 c
b11111111111111111110110001000101 f
b11111111111111111110110001000101 s
b11111111111111111100110011011100 1
b11111111111111111100110011011100 H
b11111111111111111100110011011100 N
b1111111111111111111111111111111111111111001111000110011100101010 ^
b1111010010 .
b1111010010 J
b1111010010 Q
b100000001011011101111111010010 `
b10000000101110 /
b10000000101110 I
b10000000101110 P
b1 <
b1 E
b1 ;
1$
#90000
0$
#95000
b110011000000100 0
b110011000000100 d
b1001011110111000 Y
b1001011110111000 j
b110011000000100 X
b110011000000100 v
b1001011110111000 e
b11 h
b110011000000100 r
b110110 u
0i
b110110011011000 g
b110110011011000 t
b10001100101 _
b11111111111111111101110001010111 a
b110110011011000 c
b110110011011000 f
b110110011011000 s
b1000110000011100 1
b1000110000011100 H
b1000110000011100 N
b100011001011001010100110100 ^
b11111111111111111110101000000100 .
b11111111111111111110101000000100 J
b11111111111111111110101000000100 Q
b1111111111111111111111111111111111011100010101110010001110101001 `
b11111111111111111101110001010111 /
b11111111111111111101110001010111 I
b11111111111111111101110001010111 P
b10 <
b10 E
b10 ;
1$
#100000
0$
#105000
b11111111111111110000000100010010 0
b11111111111111110000000100010010 d
b110000100101 Y
b110000100101 j
b11111111111111110000000100010010 X
b11111111111111110000000100010010 v
b1111001111011011 e
b11000 h
b1111111011101110 r
b110001011 u
1i
b110001011011010101 g
b110001011011010101 t
b11111111111111111111000100011111 ]
b11111111111111111111111100001011 _
b11111111111111101100110011110110 a
b11111111111111001110100100101011 c
b11111111111111001110100100101011 f
b11111111111111001110100100101011 s
b11111111111111100010110000001011 1
b11111111111111100010110000001011 H
b11111111111111100010110000001011 N
b1111111111111111111111111111111111110001000111110010011010101000 \
b11111111111111111101101010101010 -
b11111111111111111101101010101010 K
b11111111111111111101101010101010 R
b110110100010 .
b110110100010 J
b110110100010 Q
b11111111111111101100001101011000 /
b11111111111111101100001101011000 I
b11111111111111101100001101011000 P
b110011000000100 B
b110011000000100 V
b1111111111111111111111111111111111111111000010110000100100010000 ^
b11111111111111111110111000001000 A
b11111111111111111110111000001000 U
b1111111111111111111111111111111011001100111101101011111010011000 `
b1111100000111001 @
b1111100000111001 T
b11 <
b11 E
b0 ;
b10 D
1$
#110000
0$
#115000
b1111111011010100 0
b1111111011010100 d
b1111001111011011 Y
b1111001111011011 j
b1111111011010100 X
b1111111011010100 v
b1111001111011011 e
b11000 h
b1111111011010100 r
b110000101 u
0i
b110000101100100010 g
b110000101100100010 t
b1101011111001 ]
b101001010 _
b10011110110100110 a
b110000101100100010 c
b110000101100100010 f
b110000101100100010 s
b11011000100111001 1
b11011000100111001 H
b11011000100111001 N
b11010111110010010111011000000 \
b100001110110000 -
b100001110110000 K
b100001110110000 R
b1010010100010110100000000 ^
b11111111111111111110110110100000 .
b11111111111111111110110110100000 J
b11111111111111111110110110100000 Q
b100111101101001100010000101001010 `
b10100011110011010 /
b10100011110011010 I
b10100011110011010 P
b100 <
b100 E
b1 ;
1$
#120000
0$
#125000
b1111111011110111 0
b1111111011110111 d
b1111001111011011 Y
b1111001111011011 j
b1111111011110111 X
b1111111011110111 v
b1111001111011011 e
b11000 h
b1111111011110111 r
b110001101 u
b110001101001010111 g
b110001101001010111 t
b1101010010111 ]
b11111111111111111111111010011110 _
b10110101110101110 a
b110001101001010111 c
b110001101001010111 f
b110001101001010111 s
b11001010101110100 1
b11001010101110100 H
b11001010101110100 N
b11010100101111000110011101100 \
b100001010111011 -
b100001010111011 K
b100001010111011 R
b1111111111111111111111111111111111111110100111100111001101101000 ^
b1001110101101 .
b1001110101101 J
b1001110101101 Q
b101101011101011101110001101110100 `
b10111011100010100 /
b10111011100010100 I
b10111011100010100 P
b101 <
b101 E
b10 ;
1$
#130000
0$
