src/sigmoid_lut.v
// File         : sigmoid_lut.v
// Description  : Sigmoid lookup table for Parameterized Fixed Point

module sigmoid_lut #(
    parameter DATA_WIDTH = 32,
    parameter FRAC_WIDTH = 24
)(
    input  signed [DATA_WIDTH-1:0] z_in,
    output signed [DATA_WIDTH-1:0] a_sigmoid
);
    localparam ADDRESS_BITS = 10;
    localparam ROM_DEPTH    = 1 << ADDRESS_BITS;

    // Saturation limits
    localparam signed [DATA_WIDTH-1:0] SIGMOID_MAX_VAL = (1 <<< FRAC_WIDTH); // 1.0
    localparam signed [DATA_WIDTH-1:0] SIGMOID_MIN_VAL = {DATA_WIDTH{1'b0}}; // 0.0

    // Clamp thresholds (±6.0)
    localparam signed [DATA_WIDTH-1:0] POS_CLAMP_THRESHOLD = (6 <<< FRAC_WIDTH);
    localparam signed [DATA_WIDTH-1:0] NEG_CLAMP_THRESHOLD = -(6 <<< FRAC_WIDTH);

    reg [DATA_WIDTH-1:0] SIGMOID_ROM [0:ROM_DEPTH-1];

    // Load ROM
    initial begin
        $readmemh("./mem/sigmoid_lut_mem.hex", SIGMOID_ROM);
    end

    // Use symmetry: sigmoid(-x) = 1 - sigmoid(x)
    wire is_negative = z_in[DATA_WIDTH-1];
    wire signed [DATA_WIDTH-1:0] z_abs = is_negative ? -z_in : z_in;

    // Address bits Logic:
    // Matches the range logic of the Tanh LUT (Bits [FRAC+2 : FRAC-7])
    wire [ADDRESS_BITS-1:0] rom_address = z_abs[FRAC_WIDTH+2 : FRAC_WIDTH-7];
    wire signed [DATA_WIDTH-1:0] rom_data = SIGMOID_ROM[rom_address];

    assign a_sigmoid =
        (z_in >= POS_CLAMP_THRESHOLD) ? SIGMOID_MAX_VAL :
        (z_in <= NEG_CLAMP_THRESHOLD) ? SIGMOID_MIN_VAL :
        (is_negative ? (SIGMOID_MAX_VAL - rom_data) : rom_data);

endmodule

src/tanh_lut.v
// File         : tanh_lut.v
// Description  : Tanh LUT for Parameterized Fixed Point

module tanh_lut #(
    parameter DATA_WIDTH = 32,
    parameter FRAC_WIDTH = 24
)(
    input  signed [DATA_WIDTH-1:0] z_in,
    output signed [DATA_WIDTH-1:0] a_tanh
);
    localparam ADDRESS_BITS = 10; 
    localparam ROM_DEPTH    = 1 << ADDRESS_BITS;

    // Saturation limits calculated dynamically
    // 1.0 represented as 1 shifted by FRAC_WIDTH
    localparam signed [DATA_WIDTH-1:0] MAX_POSITIVE_VAL = (1 <<< FRAC_WIDTH); 
    localparam signed [DATA_WIDTH-1:0] MAX_NEGATIVE_VAL = -(1 <<< FRAC_WIDTH);

    // Clamp thresholds (±6.0)
    localparam signed [DATA_WIDTH-1:0] CLAMP_POS = (6 <<< FRAC_WIDTH);
    localparam signed [DATA_WIDTH-1:0] CLAMP_NEG = -(6 <<< FRAC_WIDTH);

    reg [DATA_WIDTH-1:0] TANH_ROM [0:ROM_DEPTH-1];

    // Load ROM from hex
    initial begin
        $readmemh("./mem/tanh_lut_mem.hex", TANH_ROM);
    end
    
    // Use absolute value (symmetric LUT)
    wire signed [DATA_WIDTH-1:0] z_abs = z_in[DATA_WIDTH-1] ? -z_in : z_in;

    // Address Indexing Logic:
    // We want to capture the integer part and the most significant fractional bits.
    // For Q8.24, we used bits [26:17].
    // 26 = FRAC_WIDTH + 2
    // 17 = FRAC_WIDTH - 7
    // This maintains the same input range mapping for the LUT regardless of Q format.
    wire [ADDRESS_BITS-1:0] rom_address = z_abs[FRAC_WIDTH+2 : FRAC_WIDTH-7];
    
    wire signed [DATA_WIDTH-1:0] rom_data = TANH_ROM[rom_address];

    // Output: clamp then apply sign
    assign a_tanh =
        (z_in >= CLAMP_POS) ? MAX_POSITIVE_VAL :
        (z_in <= CLAMP_NEG) ? MAX_NEGATIVE_VAL :
        (z_in[DATA_WIDTH-1] ? -rom_data : rom_data);

endmodule

src/pe_neuron.v
// File         : pe_neuron.v
// Description  : Processing Element (Neuron) module
// Fixed point  : Parameterized (Default Q8.24)

`include "tanh_lut.v"
`include "sigmoid_lut.v"

module pe_neuron #(
    parameter DATA_WIDTH = 32,
    parameter FRAC_WIDTH = 28  // Number of fractional bits (e.g., 24 for Q8.24, 16 for Q16.16)
) (
    input wire clk,
    input wire rst,
    input signed [DATA_WIDTH-1:0] x1, x2, x3, x4,
    input signed [DATA_WIDTH-1:0] w1, w2, w3, w4,
    input signed [DATA_WIDTH-1:0] bias,
    input wire pe_accumulate,
    input wire signed [DATA_WIDTH-1:0] partial_sum_in,
    input wire [1:0] act_sel,
    output signed [DATA_WIDTH-1:0] y_out
);

    // Multiplication (Clocked)
    reg signed [DATA_WIDTH-1:0] p1_reg, p2_reg, p3_reg, p4_reg;
    
    // Multipliers (Combinational part)
    wire signed [2*DATA_WIDTH-1:0] p1_long = x1 * w1;
    wire signed [2*DATA_WIDTH-1:0] p2_long = x2 * w2;
    wire signed [2*DATA_WIDTH-1:0] p3_long = x3 * w3;
    wire signed [2*DATA_WIDTH-1:0] p4_long = x4 * w4;

    always @(posedge clk or negedge rst) begin
        if (!rst) begin
            p1_reg <= 0; p2_reg <= 0; p3_reg <= 0; p4_reg <= 0;
        end else begin
            // Shift down based on FRAC_WIDTH to maintain fixed-point alignment
            p1_reg <= p1_long >>> FRAC_WIDTH;
            p2_reg <= p2_long >>> FRAC_WIDTH;
            p3_reg <= p3_long >>> FRAC_WIDTH;
            p4_reg <= p4_long >>> FRAC_WIDTH;
        end
    end

    // Summation (Clocked)
    reg signed [DATA_WIDTH-1:0] sum_reg;
    reg [1:0] act_sel_d1; // Delay activation select signal to match pipeline
    
    always @(posedge clk or negedge rst) begin
        if (!rst) begin
            sum_reg <= 0;
            act_sel_d1 <= 0;
        end else begin
            if (pe_accumulate)
                sum_reg <= p1_reg + p2_reg + p3_reg + p4_reg + bias + partial_sum_in;
            else
                sum_reg <= p1_reg + p2_reg + p3_reg + p4_reg + bias;
            
            // Pipeline the control signal
            act_sel_d1 <= act_sel; 
        end
    end
    
    // Activation / LUT (Clocked Output)
    wire signed [DATA_WIDTH-1:0] tanh_out, sig_out;
    reg signed [DATA_WIDTH-1:0] y_final_reg;

    // Instantiate LUTs with parameters
    tanh_lut #(
        .DATA_WIDTH(DATA_WIDTH), 
        .FRAC_WIDTH(FRAC_WIDTH)
    ) u_tanh (
        .z_in(sum_reg), 
        .a_tanh(tanh_out)
    );

    sigmoid_lut #(
        .DATA_WIDTH(DATA_WIDTH), 
        .FRAC_WIDTH(FRAC_WIDTH)
    ) u_sig (
        .z_in(sum_reg), 
        .a_sigmoid(sig_out)
    );

    always @(posedge clk or negedge rst) begin
        if (!rst) y_final_reg <= 0;
        else begin
            case (act_sel_d1) // Use the delayed control signal
                2'd0: y_final_reg <= tanh_out;
                2'd1: y_final_reg <= sig_out;
                default: y_final_reg <= sum_reg;
            endcase
        end
    end

    assign y_out = y_final_reg;

endmodule

src/memory.v
// File: memory.v
// Description: memory module reading weights and biases from hex files

`timescale 1ns/1ps

module memory #(
    parameter DATA_WIDTH = 32,
    parameter ADDR_WIDTH = 10,
    parameter MEM_DEPTH  = 32
)(
    input wire clk,
    input wire [ADDR_WIDTH-1:0] addr,
    output reg signed [DATA_WIDTH-1:0] w1, w2, w3, w4, bias
);

    // Internal RAM
    reg [DATA_WIDTH-1:0] mem_w1   [0:MEM_DEPTH-1];
    reg [DATA_WIDTH-1:0] mem_w2   [0:MEM_DEPTH-1];
    reg [DATA_WIDTH-1:0] mem_w3   [0:MEM_DEPTH-1];
    reg [DATA_WIDTH-1:0] mem_w4   [0:MEM_DEPTH-1];
    reg [DATA_WIDTH-1:0] mem_bias [0:MEM_DEPTH-1];

    // Load contents from hex files
    initial begin
        $readmemh("mem/w1.hex",   mem_w1);
        $readmemh("mem/w2.hex",   mem_w2);
        $readmemh("mem/w3.hex",   mem_w3);
        $readmemh("mem/w4.hex",   mem_w4);
        $readmemh("mem/bias.hex", mem_bias);
    end

    // Combinational read
    always @(*) begin
        if (addr < MEM_DEPTH) begin
            w1   = mem_w1[addr];
            w2   = mem_w2[addr];
            w3   = mem_w3[addr];
            w4   = mem_w4[addr];
            bias = mem_bias[addr];
        end else begin
            w1 = 0; w2 = 0; w3 = 0; w4 = 0; bias = 0;
        end
    end

endmodule

src/gan3x3.v
// File         : gan3x3.v
// Description  : GAN 3x3 module (Parameterized)

`timescale 1ns/1ps

`include "memory.v"
`include "pe_neuron.v"

module gan3x3 #(
    parameter DATA_WIDTH = 32,
    parameter FRAC_WIDTH = 24  // Default Q8.24
) (
    input wire clk,
    input wire rst,
    input wire start,
    input wire signed [DATA_WIDTH-1:0] noise_in1,
    input wire signed [DATA_WIDTH-1:0] noise_in2,
    output reg signed [DATA_WIDTH-1:0] disc_out,
    output reg done
);
    // --- RAM ---
    reg signed [DATA_WIDTH-1:0] internal_ram [0:15];
    reg [9:0] mem_addr;
    
    // Weights & PE signals
    wire signed [DATA_WIDTH-1:0] w1, w2, w3, w4, bias;
    reg signed [DATA_WIDTH-1:0] pe_x1, pe_x2, pe_x3, pe_x4;
    reg signed [DATA_WIDTH-1:0] pe_partial_sum;
    wire signed [DATA_WIDTH-1:0] pe_result;
    
    // Control
    reg pe_accumulate;
    reg [1:0] pe_act_sel; // 0 -> tanh, 1 -> sigmoid

    // Pipeline Control
    reg [1:0] pipe_cnt;
    localparam [1:0] PIPE_WAIT = 2'd3; // Kontrol pipeline

    // Instantiations
    memory #(.DATA_WIDTH(DATA_WIDTH)) u_mem (
        .clk (clk), .addr(mem_addr),
        .w1(w1), .w2(w2), .w3(w3), .w4(w4), .bias(bias)
    );
    
    pe_neuron #(
        .DATA_WIDTH(DATA_WIDTH),
        .FRAC_WIDTH(FRAC_WIDTH)
    ) u_pe (
        .clk(clk),
        .rst(rst),
        .x1(pe_x1), .x2(pe_x2), .x3(pe_x3), .x4(pe_x4),
        .w1(w1), .w2(w2), .w3(w3), .w4(w4),
        .bias(bias),
        .pe_accumulate(pe_accumulate),
        .partial_sum_in(pe_partial_sum),
        .act_sel(pe_act_sel),
        .y_out(pe_result)
    );

    // State
    localparam S_IDLE       = 3'd0;
    localparam S_GEN_HIDDEN = 3'd1;
    localparam S_GEN_OUTPUT = 3'd2;
    localparam S_DIS_HIDDEN = 3'd3;
    localparam S_DIS_OUTPUT = 3'd4;
    localparam S_DONE       = 3'd5;

    reg [2:0] state;
    reg [3:0] loop_cnt;
    reg [1:0] acc_step;

    always @(posedge clk or negedge rst) begin
        if (!rst) begin
            state <= S_IDLE;
            mem_addr <= 0;
            done <= 0;
            loop_cnt <= 0;
            acc_step <= 0;
            pipe_cnt <= 0;
            pe_partial_sum <= 0;
            pe_x1 <= 0; pe_x2 <= 0; pe_x3 <= 0; pe_x4 <= 0;
            pe_accumulate <= 0;
            pe_act_sel <= 0;
        end else begin
            case (state)
                S_IDLE: begin
                    done <= 0;
                    if(start) begin
                        state <= S_GEN_HIDDEN;
                        mem_addr <= 0;
                        loop_cnt <= 0;
                        pipe_cnt <= 0; // Reset pipe counter
                        
                        pe_x1 <= noise_in1;
                        pe_x2 <= noise_in2;
                        pe_x3 <= 0;
                        pe_x4 <= 0;
                        pe_act_sel <= 0; // Tanh
                        pe_accumulate <= 0;
                    end
                end
            
                S_GEN_HIDDEN: begin
                    // Tunggu pipeline
                    if (pipe_cnt < PIPE_WAIT) begin
                        pipe_cnt <= pipe_cnt + 1;
                    end else begin
                        internal_ram[loop_cnt] <= pe_result;
                        pipe_cnt <= 0; // Reset counter pipeline

                        if (loop_cnt == 2) begin
                            state <= S_GEN_OUTPUT;
                            loop_cnt <= 0;
                            mem_addr <= mem_addr + 1;
                            
                            pe_x1 <= internal_ram[0];
                            pe_x2 <= internal_ram[1];
                            pe_x3 <= pe_result; // preload
                            pe_x4 <= 0;
                            pe_act_sel <= 0;
                            pe_accumulate <= 0;
                        end else begin
                            loop_cnt <= loop_cnt + 1;
                            mem_addr <= mem_addr + 1;
                            
                            pe_x1 <= noise_in1;
                            pe_x2 <= noise_in2;
                            pe_x3 <= 0;
                            pe_x4 <= 0;
                        end
                    end
                end

                S_GEN_OUTPUT: begin
                    if (pipe_cnt < PIPE_WAIT) begin
                        pipe_cnt <= pipe_cnt + 1;
                    end else begin
                        internal_ram[3+loop_cnt] <= pe_result;
                        pipe_cnt <= 0; 

                        if (loop_cnt == 8) begin
                            state <= S_DIS_HIDDEN;
                            loop_cnt <= 0;
                            acc_step <= 0;
                            mem_addr <= mem_addr + 1;
                            
                            // Inputs: Pixel 0-3 (RAM 3,4,5,6)
                            pe_x1 <= internal_ram[3];
                            pe_x2 <= internal_ram[4];
                            pe_x3 <= internal_ram[5];
                            pe_x4 <= internal_ram[6];
                            pe_act_sel <= 2; // bypass
                            pe_accumulate <= 0;
                        end else begin
                            loop_cnt <= loop_cnt + 1;
                            mem_addr <= mem_addr + 1;
                            
                            pe_x1 <= internal_ram[0];
                            pe_x2 <= internal_ram[1];
                            pe_x3 <= internal_ram[2];
                            pe_x4 <= 0;
                        end
                    end
                end

                S_DIS_HIDDEN: begin
                    if (pipe_cnt < PIPE_WAIT) begin
                        pipe_cnt <= pipe_cnt + 1;
                    end else begin
                        pipe_cnt <= 0;

                        case (acc_step)
                            0: begin
                                pe_partial_sum <= pe_result;
                                acc_step <= 1;
                                mem_addr <= mem_addr + 1;
                                pe_x1 <= internal_ram[7];
                                pe_x2 <= internal_ram[8];
                                pe_x3 <= internal_ram[9];
                                pe_x4 <= internal_ram[10];
                                pe_accumulate <= 1; // Akumulasi
                            end
                            1: begin
                                pe_partial_sum <= pe_result;
                                acc_step <= 2;
                                mem_addr <= mem_addr + 1;
                                pe_x1 <= internal_ram[11];
                                pe_x2 <= 0;
                                pe_x3 <= 0;
                                pe_x4 <= 0;
                                pe_act_sel <= 0;
                                pe_accumulate <= 1;
                            end
                            2: begin
                                internal_ram[12+loop_cnt] <= pe_result;
                                if(loop_cnt == 2) begin
                                    state <= S_DIS_OUTPUT;
                                    loop_cnt <= 0;
                                    mem_addr <= mem_addr + 1;
                                    pe_x1 <= internal_ram[12];
                                    pe_x2 <= internal_ram[13];
                                    pe_x3 <= pe_result;
                                    pe_x4 <= 0;
                                    pe_act_sel <= 1; // Sigmoid
                                    pe_accumulate <= 0;
                                end else begin
                                    loop_cnt <= loop_cnt + 1;
                                    acc_step <= 0;
                                    mem_addr <= mem_addr + 1;
                                    pe_x1 <= internal_ram[3];
                                    pe_x2 <= internal_ram[4];
                                    pe_x3 <= internal_ram[5];
                                    pe_x4 <= internal_ram[6];
                                    pe_act_sel <= 2;    
                                    pe_accumulate <= 0;
                                end
                            end
                        endcase
                    end
                end

                S_DIS_OUTPUT: begin
                    if (pipe_cnt < PIPE_WAIT) begin
                        pipe_cnt <= pipe_cnt + 1;
                    end else begin
                        disc_out <= pe_result;
                        state <= S_DONE;
                    end
                end

                S_DONE: begin
                    done <= 1;
                    if (!start) state <= S_IDLE;
                end
                
                default: state <= S_IDLE;
            endcase
        end
    end
endmodule

src/tb_gan3x3.v
// File         : tb_gan3x3.v
// Description  : Testbench for the gan3x3 module (Parameterized)

`timescale 1ns/1ps
`include "gan3x3.v"

module tb_gan3x3;

    // Define format parameters here
    parameter DATA_WIDTH = 32;
    parameter FRAC_WIDTH = 28; // Change this to 16, 28, etc.

    real float_out; 
    reg clk;
    reg rst;
    reg start;
    reg signed [DATA_WIDTH-1:0] noise_in1;
    reg signed [DATA_WIDTH-1:0] noise_in2;

    wire signed [DATA_WIDTH-1:0] disc_out;
    wire done;

    gan3x3 #(
        .DATA_WIDTH(DATA_WIDTH),
        .FRAC_WIDTH(FRAC_WIDTH)
    ) u_dut (
        .clk(clk),
        .rst(rst),
        .start(start),
        .noise_in1(noise_in1),
        .noise_in2(noise_in2),
        .disc_out(disc_out),
        .done(done)
    );

    // Clock
    always #5 clk = ~clk;
    
    // Helper: Fixed Point to Real
    function real fixed_to_real;
        input signed [DATA_WIDTH-1:0] val;
        begin
            fixed_to_real = $signed(val) / (2.0 ** FRAC_WIDTH);
        end
    endfunction

    // Helper: Real to Fixed Point
    function signed [DATA_WIDTH-1:0] real_to_fixed;
        input real val;
        begin
            real_to_fixed = $rtoi(val * (2.0 ** FRAC_WIDTH));
        end
    endfunction

    integer i, r, c, idx;

    // Waveform Dump
    initial begin
        $dumpfile("gan_3x3.vcd");
        $dumpvars(0, tb_gan3x3);
    end

    initial begin
        clk = 0;
        rst = 0;
        start = 0;
        noise_in1 = 0;
        noise_in2 = 0;

        $display("Simulation start. Format Q%0d.%0d", DATA_WIDTH-FRAC_WIDTH, FRAC_WIDTH);

        // Reset
        #20; @(negedge clk); rst = 1;

        // Test case: noise [0.5, -0.2]
        #20; @(negedge clk);
        $display("Test case: noise [0.5, -0.2]");
        
        // Generate inputs dynamically using the parameter
        noise_in1 = real_to_fixed(0.5);
        noise_in2 = real_to_fixed(-0.2);
        
        start = 1;
        
        #10;
        @(negedge clk);
        start = 0;

        wait(done);
        @(negedge clk);

        $display("");
        $display("RESULTS");
        $display("");

        // G2: generator hidden (RAM 0..2)
        $display("G2:");
        for (i = 0; i < 3; i = i + 1) begin
            $display("N%0d: %h (%0.6f)", i+1, u_dut.internal_ram[i], fixed_to_real(u_dut.internal_ram[i]));
        end

        // G3: generated image (float)
        $display("");
        $display("G3: image (float)");
        $display("");
        for (r = 0; r < 3; r = r + 1) begin
            idx = 3 + r*3;
            $display("%0.6f %0.6f %0.6f",
                fixed_to_real(u_dut.internal_ram[idx]),
                fixed_to_real(u_dut.internal_ram[idx+1]),
                fixed_to_real(u_dut.internal_ram[idx+2])
            );
        end

        // G3: generated image (raw)
        $display("");
        $display("G3: image (raw)");
        $display("");
        for (r = 0; r < 3; r = r + 1) begin
            idx = 3 + r*3;
            $display("%h %h %h",
                u_dut.internal_ram[idx],
                u_dut.internal_ram[idx+1],
                u_dut.internal_ram[idx+2]
            );
        end

        // D2: discriminator hidden (RAM 12..14)
        $display("");
        $display("D2: hidden");
        $display("");
        for (i = 0; i < 3; i = i + 1) begin
            $display("N%0d: %h (%0.6f)", i+1, u_dut.internal_ram[12 + i], fixed_to_real(u_dut.internal_ram[12 + i]));
        end

        // D3: final output
        float_out = fixed_to_real(disc_out);
        $display("");
        $display("D3: final");
        $display("");
        $display("Raw: %h", disc_out);
        $display("Prob: %0.6f", float_out);

        #100;
        $display("\n--- Simulation Complete ---");
        $finish;
    end
endmodule

src/gan_3x3.vcd
$date
	Mon Jan 12 05:08:25 2026
$end
$version
	Icarus Verilog
$end
$timescale
	1ps
$end
$scope module tb_gan3x3 $end
$var wire 1 ! done $end
$var wire 32 " disc_out [31:0] $end
$var parameter 32 # DATA_WIDTH $end
$var parameter 32 $ FRAC_WIDTH $end
$var reg 1 % clk $end
$var reg 32 & noise_in1 [31:0] $end
$var reg 32 ' noise_in2 [31:0] $end
$var reg 1 ( rst $end
$var reg 1 ) start $end
$var real 1 * float_out $end
$var integer 32 + i [31:0] $end
$var integer 32 , idx [31:0] $end
$var integer 32 - r [31:0] $end
$scope function fixed_to_real $end
$var reg 32 . val [31:0] $end
$upscope $end
$scope function real_to_fixed $end
$var real 1 / val $end
$upscope $end
$scope module u_dut $end
$var wire 1 % clk $end
$var wire 32 0 noise_in1 [31:0] $end
$var wire 32 1 noise_in2 [31:0] $end
$var wire 1 ( rst $end
$var wire 1 ) start $end
$var wire 32 2 w4 [31:0] $end
$var wire 32 3 w3 [31:0] $end
$var wire 32 4 w2 [31:0] $end
$var wire 32 5 w1 [31:0] $end
$var wire 32 6 pe_result [31:0] $end
$var wire 32 7 bias [31:0] $end
$var parameter 32 8 DATA_WIDTH $end
$var parameter 32 9 FRAC_WIDTH $end
$var parameter 2 : PIPE_WAIT $end
$var parameter 3 ; S_DIS_HIDDEN $end
$var parameter 3 < S_DIS_OUTPUT $end
$var parameter 3 = S_DONE $end
$var parameter 3 > S_GEN_HIDDEN $end
$var parameter 3 ? S_GEN_OUTPUT $end
$var parameter 3 @ S_IDLE $end
$var reg 2 A acc_step [1:0] $end
$var reg 32 B disc_out [31:0] $end
$var reg 1 ! done $end
$var reg 4 C loop_cnt [3:0] $end
$var reg 10 D mem_addr [9:0] $end
$var reg 1 E pe_accumulate $end
$var reg 2 F pe_act_sel [1:0] $end
$var reg 32 G pe_partial_sum [31:0] $end
$var reg 32 H pe_x1 [31:0] $end
$var reg 32 I pe_x2 [31:0] $end
$var reg 32 J pe_x3 [31:0] $end
$var reg 32 K pe_x4 [31:0] $end
$var reg 2 L pipe_cnt [1:0] $end
$var reg 3 M state [2:0] $end
$scope module u_mem $end
$var wire 10 N addr [9:0] $end
$var wire 1 % clk $end
$var parameter 32 O ADDR_WIDTH $end
$var parameter 32 P DATA_WIDTH $end
$var parameter 32 Q MEM_DEPTH $end
$var reg 32 R bias [31:0] $end
$var reg 32 S w1 [31:0] $end
$var reg 32 T w2 [31:0] $end
$var reg 32 U w3 [31:0] $end
$var reg 32 V w4 [31:0] $end
$upscope $end
$scope module u_pe $end
$var wire 2 W act_sel [1:0] $end
$var wire 32 X bias [31:0] $end
$var wire 1 % clk $end
$var wire 32 Y partial_sum_in [31:0] $end
$var wire 1 E pe_accumulate $end
$var wire 1 ( rst $end
$var wire 32 Z w1 [31:0] $end
$var wire 32 [ w2 [31:0] $end
$var wire 32 \ w3 [31:0] $end
$var wire 32 ] w4 [31:0] $end
$var wire 32 ^ x1 [31:0] $end
$var wire 32 _ x2 [31:0] $end
$var wire 32 ` x3 [31:0] $end
$var wire 32 a x4 [31:0] $end
$var wire 32 b y_out [31:0] $end
$var wire 32 c tanh_out [31:0] $end
$var wire 32 d sig_out [31:0] $end
$var wire 64 e p4_long [63:0] $end
$var wire 64 f p3_long [63:0] $end
$var wire 64 g p2_long [63:0] $end
$var wire 64 h p1_long [63:0] $end
$var parameter 32 i DATA_WIDTH $end
$var parameter 32 j FRAC_WIDTH $end
$var reg 2 k act_sel_d1 [1:0] $end
$var reg 32 l p1_reg [31:0] $end
$var reg 32 m p2_reg [31:0] $end
$var reg 32 n p3_reg [31:0] $end
$var reg 32 o p4_reg [31:0] $end
$var reg 32 p sum_reg [31:0] $end
$var reg 32 q y_final_reg [31:0] $end
$scope module u_sig $end
$var wire 32 r rom_data [31:0] $end
$var wire 32 s z_in [31:0] $end
$var wire 32 t z_abs [31:0] $end
$var wire 10 u rom_address [9:0] $end
$var wire 1 v is_negative $end
$var wire 32 w a_sigmoid [31:0] $end
$var parameter 32 x ADDRESS_BITS $end
$var parameter 32 y DATA_WIDTH $end
$var parameter 32 z FRAC_WIDTH $end
$var parameter 32 { NEG_CLAMP_THRESHOLD $end
$var parameter 32 | POS_CLAMP_THRESHOLD $end
$var parameter 42 } ROM_DEPTH $end
$var parameter 32 ~ SIGMOID_MAX_VAL $end
$var parameter 32 !" SIGMOID_MIN_VAL $end
$upscope $end
$scope module u_tanh $end
$var wire 32 "" rom_data [31:0] $end
$var wire 32 #" z_in [31:0] $end
$var wire 32 $" z_abs [31:0] $end
$var wire 10 %" rom_address [9:0] $end
$var wire 32 &" a_tanh [31:0] $end
$var parameter 32 '" ADDRESS_BITS $end
$var parameter 32 (" CLAMP_NEG $end
$var parameter 32 )" CLAMP_POS $end
$var parameter 32 *" DATA_WIDTH $end
$var parameter 32 +" FRAC_WIDTH $end
$var parameter 32 ," MAX_NEGATIVE_VAL $end
$var parameter 32 -" MAX_POSITIVE_VAL $end
$var parameter 42 ." ROM_DEPTH $end
$upscope $end
$upscope $end
$upscope $end
$upscope $end
$enddefinitions $end
$comment Show the parameter values. $end
$dumpall
b10000000000 ."
b10000000000000000000000000000 -"
b11110000000000000000000000000000 ,"
b11100 +"
b100000 *"
b1100000000000000000000000000000 )"
b10100000000000000000000000000000 ("
b1010 '"
b0 !"
b10000000000000000000000000000 ~
b10000000000 }
b1100000000000000000000000000000 |
b10100000000000000000000000000000 {
b11100 z
b100000 y
b1010 x
b11100 j
b100000 i
b100000 Q
b100000 P
b1010 O
b0 @
b10 ?
b1 >
b101 =
b100 <
b11 ;
b11 :
b11100 9
b100000 8
b11100 $
b100000 #
$end
#0
$dumpvars
b0 &"
b0 %"
b0 $"
b0 #"
b0 ""
b1000000000000000000000000000 w
0v
b0 u
b0 t
b0 s
b1000000000000000000000000000 r
b0 q
b0 p
b0 o
b0 n
b0 m
b0 l
b0 k
b0 h
b0 g
b0 f
b0 e
b1000000000000000000000000000 d
b0 c
b0 b
b0 a
b0 `
b0 _
b0 ^
b0 ]
b0 \
b11011011111111110010 [
b10001000110001001010 Z
b0 Y
b11001101000100111011101100011 X
b0 W
b0 V
b0 U
b11011011111111110010 T
b10001000110001001010 S
b11001101000100111011101100011 R
b0 N
b0 M
b0 L
b0 K
b0 J
b0 I
b0 H
b0 G
b0 F
0E
b0 D
b0 C
bx B
b0 A
b11001101000100111011101100011 7
b0 6
b10001000110001001010 5
b11011011111111110010 4
b0 3
b0 2
b0 1
b0 0
r0 /
bx .
bx -
bx ,
bx +
r0 *
0)
0(
b0 '
b0 &
0%
bx "
0!
$end
#5000
1%
#10000
0%
#15000
1%
#20000
1(
0%
#25000
b1101010100001101011101100001 d
b1101010100001101011101100001 w
b1110110000000001110111001011 c
b1110110000000001110111001011 &"
b1101010100001101011101100001 r
b11001101 u
b1110110000000001110111001011 ""
b11001101 %"
b11001101000100111011101100011 t
b11001101000100111011101100011 $"
b11001101000100111011101100011 p
b11001101000100111011101100011 s
b11001101000100111011101100011 #"
1%
#30000
0%
#35000
b1110110000000001110111001011 6
b1110110000000001110111001011 b
b1110110000000001110111001011 q
1%
#40000
1)
b11111100110011001100110011001101 '
b11111100110011001100110011001101 1
b1000000000000000000000000000 &
b1000000000000000000000000000 0
r-0.2 /
0%
#45000
b1111111111111111110101000000000000101100110011111000110011001010 g
b11111100110011001100110011001101 I
b11111100110011001100110011001101 _
b10001000110001001010000000000000000000000000000 h
b1000000000000000000000000000 H
b1000000000000000000000000000 ^
b1 M
1%
#50000
0)
0%
#55000
b11111111111111010100000000000010 m
b1000100011000100101 l
b1 L
1%
#60000
0%
#65000
b11001101000111111110110001010 t
b11001101000111111110110001010 $"
b10 L
b11001101000111111110110001010 p
b11001101000111111110110001010 s
b11001101000111111110110001010 #"
1%
#70000
0%
#75000
b11 L
1%
#80000
0%
#85000
b11110111001111000110100100110110 7
b11110111001111000110100100110110 R
b11110111001111000110100100110110 X
b1111111111111110111110001111000110000110011101101101011101001110 g
b10100100011010010000110 4
b10100100011010010000110 T
b10100100011010010000110 [
b1110001000010001110011010000000000000000000000000000 h
b1110001000010001110011010 5
b1110001000010001110011010 S
b1110001000010001110011010 Z
b1 D
b1 N
b1 C
b0 L
1%
#90000
0%
#95000
b101110111011000110100110100 d
b101110111011000110100110100 w
b11111000000001110111101001000001 c
b11111000000001110111101001000001 &"
b1010001000100111001011001100 r
b1000110 u
b111111110001000010110111111 ""
b1000110 %"
1v
b1000110000100001000010100011 t
b1000110000100001000010100011 $"
b11111111111011111000111100011000 m
b111000100001000111001101 l
b11110111001111011110111101011101 p
b11110111001111011110111101011101 s
b11110111001111011110111101011101 #"
b1 L
1%
#100000
0%
#105000
b110000100011110111100010010 d
b110000100011110111100010010 w
b11111000101101000110110011010101 c
b11111000101101000110110011010101 &"
b1001111011100001000011101110 r
b111111 u
b111010010111001001100101011 ""
b111111 %"
b111111100011111010111100101 t
b111111100011111010111100101 $"
b10 L
b11111000000001110111101001000001 6
b11111000000001110111101001000001 b
b11111000000001110111101001000001 q
b11111000000011100000101000011011 p
b11111000000011100000101000011011 s
b11111000000011100000101000011011 #"
1%
#110000
0%
#115000
b11111000101101000110110011010101 6
b11111000101101000110110011010101 b
b11111000101101000110110011010101 q
b11 L
1%
#120000
0%
#125000
b11100110001100011110111110111011 7
b11100110001100011110111110111011 R
b11100110001100011110111110111011 X
b101011011001000111101100110000011111001110101110 g
b11111111110010011100001001100110 4
b11111111110010011100001001100110 T
b11111111110010011100001001100110 [
b1111111111111011111101100101110001001000000000000000000000000000 h
b11111111011111101100101110001001 5
b11111111011111101100101110001001 S
b11111111011111101100101110001001 Z
b10 D
b10 N
b10 C
b0 L
1%
#130000
0%
#135000
b10110010100110001001101111 d
b10110010100110001001101111 w
b11110001010111011111101011110010 c
b11110001010111011111101011110010 &"
b1101001101011001110110010001 r
b11000111 u
b1110101000100000010100001110 ""
b11000111 %"
b11000111111000110111101100000 t
b11000111111000110111101100000 $"
b10101101100100011110 m
b11111111101111110110010111000100 l
b11100111000000111001000010100000 p
b11100111000000111001000010100000 s
b11100111000000111001000010100000 #"
b1 L
1%
#140000
0%
#145000
b10101000011101110000000100 d
b10101000011101110000000100 w
b11110001001100011100100000101001 c
b11110001001100011100100000101001 &"
b1101010111100010001111111100 r
b11010000 u
b1110110011100011011111010111 ""
b11010000 %"
b11010000000111101000101100011 t
b11010000000111101000101100011 $"
b10 L
b11110001010111011111101011110010 6
b11110001010111011111101011110010 b
b11110001010111011111101011110010 q
b11100101111111000010111010011101 p
b11100101111111000010111010011101 s
b11100101111111000010111010011101 #"
1%
#150000
0%
#155000
b11110001001100011100100000101001 6
b11110001001100011100100000101001 b
b11110001001100011100100000101001 q
b11 L
1%
#160000
0%
