src/sigmoid_lut.v
// File: sigmoid_lut.v
// Description: Sigmoid Look-Up Table (LUT) implementation with robust clamping logic.
// Format: Q1.7.8 (16 bits total)
// Size: 1024 entries (10 address bits)

module sigmoid_lut (
    input  [15:0] z_q1_7_8,     // Input Z signal (16-bit scaled integer, Q1.7.8)
    output [15:0] a_sigmoid     // Output A_sigmoid (16-bit scaled integer, Q1.7.8)
);

// Configuration Parameters
localparam ADDRESS_BITS = 10;
localparam DATA_WIDTH   = 16;
localparam ROM_DEPTH    = 1 << ADDRESS_BITS; // 1024 entries

// Q1.7.8 fixed-point values for clamping:
// Sigmoid output max is 1.0, min is 0.0.
localparam SIGMOID_MAX_VAL   = 16'h0100; // +1.0 * 256 = 256
localparam SIGMOID_MIN_VAL   = 16'h0000; // +0.0 * 256 = 0

// Thresholds for Clamping Check (Range: [-6.0, 6.0]):
// 6.0 in Q1.7.8: 16'h0600
localparam POS_CLAMP_THRESHOLD = 16'h0600; 
// -6.0 in Q1.7.8: 16'hFA00
localparam NEG_CLAMP_THRESHOLD = 16'hFA00; 

// Internal ROM array (1024 entries, 16 bits wide)
reg [DATA_WIDTH-1:0] SIGMOID_ROM [0:ROM_DEPTH-1];

// --- 1. Memory Initialization ---
initial begin
    // Load the fixed-point Sigmoid values from the .hex file
    $readmemh("mem/sigmoid_lut_mem.hex", SIGMOID_ROM);
    $display("SIGMOID_ROM initialized successfully with %0d entries.", ROM_DEPTH);
end

// --- 2. Address Generation ---
// The address is derived from the middle 10 bits [14:5] of the input Z.
wire [ADDRESS_BITS-1:0] rom_address = z_q1_7_8[14:5];

// --- 3. Combined Clamping and ROM Read Operation ---
// Uses continuous assign for combinational logic.
assign a_sigmoid = 
    // Case 1: Extreme Positive Saturation (Z >= 6.0)
    // Sigmoid(Z) -> 1.0
    ($signed(z_q1_7_8) >= $signed(POS_CLAMP_THRESHOLD)) ? SIGMOID_MAX_VAL :
    
    // Case 2: Extreme Negative Saturation (Z <= -6.0)
    // Sigmoid(Z) -> 0.0  <-- CORRECTED CLAMP VALUE
    ($signed(z_q1_7_8) <= $signed(NEG_CLAMP_THRESHOLD)) ? SIGMOID_MIN_VAL :
    
    // Case 3: Within the Critical Range (-6.0 < Z < 6.0), use the LUT
    SIGMOID_ROM[rom_address];

endmodule

src/tanh_lut.v
// File: tanh_lut.v
// Description: Tanh Look-Up Table (LUT) implementation with robust clamping logic.
// Format: Q1.7.8 (16 bits total)
// Size: 1024 entries (10 address bits)

module tanh_lut (
    input  [15:0] z_q1_7_8,     // Input Z signal (16-bit scaled integer, Q1.7.8)
    output [15:0] a_tanh        // Output A_tanh (16-bit scaled integer, Q1.7.8)
);

// Configuration Parameters
localparam ADDRESS_BITS = 10;
localparam DATA_WIDTH   = 16;
localparam ROM_DEPTH    = 1 << ADDRESS_BITS; // 1024 entries

// Q1.7.8 fixed-point values for clamping:
// +1.0 * 256 = 256
localparam MAX_POSITIVE_VAL = 16'h0100;
// -1.0 * 256 = -256 (Two's Complement: 16'hFF00)
localparam MAX_NEGATIVE_VAL = 16'hFF00;

// Thresholds for Clamping Check:
// We sampled the LUT up to 5.0. To be safe, we check inputs >= 6.0 and <= -6.0.
// 6.0 in Q1.7.8: 5.0 * 256 = 1280 (16'h0500)
localparam POS_CLAMP_THRESHOLD = 16'h0500;
// -6.0 in Q1.7.8: -5.0 * 256 = -1280 (Two's Complement: 16'hFB00)
localparam NEG_CLAMP_THRESHOLD = 16'hFB00;

// Internal ROM array (1024 entries, 16 bits wide)
reg [DATA_WIDTH-1:0] TANH_ROM [0:ROM_DEPTH-1];

// --- 1. Memory Initialization ---
initial begin
    // Load the fixed-point Tanh values from the .hex file
    $readmemh("mem/tanh_lut_mem.hex", TANH_ROM);
    $display("TANH_ROM initialized successfully with %0d entries.", ROM_DEPTH);
end

// --- 2. Address Generation ---
// The address is derived from the middle 10 bits [14:5] of the input Z.
wire [ADDRESS_BITS-1:0] rom_address = z_q1_7_8[14:5];

// --- 3. Combined Clamping and ROM Read Operation ---
// This uses a continuous assign for purely combinational logic (no clock needed for read).
// Note: $signed() casting is crucial for correct comparison in Verilog.
assign a_tanh = 
    // Case 1: Extreme Positive Saturation (Z >= 6.0)
    ($signed(z_q1_7_8) >= $signed(POS_CLAMP_THRESHOLD)) ? MAX_POSITIVE_VAL :
    
    // Case 2: Extreme Negative Saturation (Z <= -6.0)
    ($signed(z_q1_7_8) <= $signed(NEG_CLAMP_THRESHOLD)) ? MAX_NEGATIVE_VAL :
    
    // Case 3: Within the Critical Range (-6.0 < Z < 6.0), use the LUT
    TANH_ROM[rom_address];

endmodule

src/pe_neuron.v
`timescale 1ns/1ps
`include "sigmoid_lut.v"
`include "tanh_lut.v"

module pe_neuron #(
    parameter DATA_WIDTH = 32
) (
    input wire clk,
    input wire rst,
    input signed [DATA_WIDTH-1:0] x1, x2, x3, x4,
    input signed [DATA_WIDTH-1:0] w1, w2, w3, w4,
    input signed [DATA_WIDTH-1:0] bias,
    
    input wire pe_accumulate,
    input wire signed [DATA_WIDTH-1:0] partial_sum_in,
    input wire [1:0] act_sel,

    output reg signed [DATA_WIDTH-1:0] y_out
);
    // 1. Multiply (FORCE 64-BIT PRECISION)
    // We multiply to 64 bits, then shift, then take the bottom 32 bits
    wire signed [2*DATA_WIDTH-1:0] p1_long = x1 * w1;
    wire signed [2*DATA_WIDTH-1:0] p2_long = x2 * w2;
    wire signed [2*DATA_WIDTH-1:0] p3_long = x3 * w3;
    wire signed [2*DATA_WIDTH-1:0] p4_long = x4 * w4;

    wire signed [DATA_WIDTH-1:0] p1 = p1_long >>> 16;
    wire signed [DATA_WIDTH-1:0] p2 = p2_long >>> 16;
    wire signed [DATA_WIDTH-1:0] p3 = p3_long >>> 16;
    wire signed [DATA_WIDTH-1:0] p4 = p4_long >>> 16;

    // 2. Summation
    reg signed [DATA_WIDTH-1:0] sum_raw;

    always @(*) begin
        sum_raw = p1 + p2 + p3 + p4 + bias;
        if (pe_accumulate) begin
            sum_raw = sum_raw + partial_sum_in;
        end
    end

    // 3. LUT Conversion
    wire signed [31:0] sum_shifted = sum_raw >>> 8;
    wire [15:0] lut_input;
    
    assign lut_input = (sum_shifted > 32'sd32767)  ? 16'h7FFF :
                       (sum_shifted < -32'sd32768) ? 16'h8000 :
                                                     sum_shifted[15:0];

    wire [15:0] tanh_out_16, sig_out_16;
    tanh_lut u_tanh (.z_q1_7_8(lut_input), .a_tanh(tanh_out_16));
    sigmoid_lut u_sig (.z_q1_7_8(lut_input), .a_sigmoid(sig_out_16));

    wire signed [31:0] tanh_out_32 = $signed(tanh_out_16) <<< 8;
    wire signed [31:0] sig_out_32  = $signed(sig_out_16)  <<< 8;

    // 4. Output Logic
    always @(*) begin
        case (act_sel)
            2'd0: y_out = tanh_out_32; // Tanh
            2'd1: y_out = sig_out_32;  // Sigmoid
            default: y_out = sum_raw;  // Linear
        endcase
    end

endmodule

src/memory.v
// File: memory.v
// Description: memory module reading weights and biases from hex files

`timescale 1ns/1ps

module memory #(
    parameter DATA_WIDTH = 32,
    parameter ADDR_WIDTH = 10,
    parameter MEM_DEPTH  = 32
)(
    input wire clk,
    input wire [ADDR_WIDTH-1:0] addr,
    output reg signed [DATA_WIDTH-1:0] w1, w2, w3, w4, bias
);

    // Internal RAM
    reg [DATA_WIDTH-1:0] mem_w1   [0:MEM_DEPTH-1];
    reg [DATA_WIDTH-1:0] mem_w2   [0:MEM_DEPTH-1];
    reg [DATA_WIDTH-1:0] mem_w3   [0:MEM_DEPTH-1];
    reg [DATA_WIDTH-1:0] mem_w4   [0:MEM_DEPTH-1];
    reg [DATA_WIDTH-1:0] mem_bias [0:MEM_DEPTH-1];

    // Load contents from hex files
    initial begin
        $readmemh("mem/w1.hex",   mem_w1);
        $readmemh("mem/w2.hex",   mem_w2);
        $readmemh("mem/w3.hex",   mem_w3);
        $readmemh("mem/w4.hex",   mem_w4);
        $readmemh("mem/bias.hex", mem_bias);
    end

    // Combinational read
    always @(*) begin
        if (addr < MEM_DEPTH) begin
            w1   = mem_w1[addr];
            w2   = mem_w2[addr];
            w3   = mem_w3[addr];
            w4   = mem_w4[addr];
            bias = mem_bias[addr];
        end else begin
            w1 = 0; w2 = 0; w3 = 0; w4 = 0; bias = 0;
        end
    end

endmodule

src/gan3x3.v
`timescale 1ns/1ps

`include "memory.v"
`include "pe_neuron.v"

module gan3x3 #(
    parameter DATA_WIDTH = 32
) (
    input wire clk,
    input wire rst,
    input wire start,
    input wire signed [DATA_WIDTH-1:0] noise_in1,
    input wire signed [DATA_WIDTH-1:0] noise_in2,
    output reg signed [DATA_WIDTH-1:0] disc_out,
    output reg done
);
    // RAM
    reg signed [DATA_WIDTH-1:0] internal_ram [0:15];
    reg [9:0] mem_addr;

    // Weights & PE signals
    wire signed [DATA_WIDTH-1:0] w1, w2, w3, w4, bias;
    reg signed [DATA_WIDTH-1:0] pe_x1, pe_x2, pe_x3, pe_x4;
    reg signed [DATA_WIDTH-1:0] pe_partial_sum;
    wire signed [DATA_WIDTH-1:0] pe_result;

    // Control
    reg pe_accumulate;
    reg [1:0] pe_act_sel; // 0 -> tanh, 1 -> sigmoid

    memory #(.DATA_WIDTH(DATA_WIDTH)) u_mem (
        .clk (clk), .addr(mem_addr),
        .w1(w1), .w2(w2), .w3(w3), .w4(w4), .bias(bias)
    );

    pe_neuron #(.DATA_WIDTH(DATA_WIDTH)) u_pe (
        .clk(clk),
        .rst(rst),
        .x1(pe_x1), .x2(pe_x2), .x3(pe_x3), .x4(pe_x4),
        .w1(w1), .w2(w2), .w3(w3), .w4(w4),
        .bias(bias),
        .pe_accumulate(pe_accumulate),
        .partial_sum_in(pe_partial_sum),
        .act_sel(pe_act_sel),
        .y_out(pe_result)
    );

    // States
    localparam S_IDLE = 3'd0;
    localparam S_GEN_HIDDEN = 3'd1;
    localparam S_GEN_OUTPUT = 3'd2;
    localparam S_DIS_HIDDEN = 3'd3;
    localparam S_DIS_OUTPUT = 3'd4;
    localparam S_DONE = 3'd5;

    reg [2:0] state;
    reg [3:0] loop_cnt;
    reg [1:0] acc_step;

    always @(posedge clk or negedge rst) begin
        if (!rst) begin
            state <= S_IDLE;
            mem_addr <= 0;
            done <= 0;
            loop_cnt <= 0;
            acc_step <= 0;
            pe_partial_sum <= 0;
            pe_x1 <= 0;
            pe_x2 <= 0;
            pe_x3 <= 0;
            pe_x4 <= 0;
            pe_accumulate <= 0;
            pe_act_sel <= 0;
        end else begin
            case (state)
                S_IDLE: begin
                    done <= 0;
                    if(start) begin
                        state <= S_GEN_HIDDEN;
                        mem_addr <= 0;
                        loop_cnt <= 0;
                        
                        // --- FIX 1: Pre-load inputs for first layer ---
                        pe_x1 <= noise_in1;
                        pe_x2 <= noise_in2;
                        pe_x3 <= 0;
                        pe_x4 <= 0;
                        pe_act_sel <= 0; // Tanh
                        pe_accumulate <= 0;
                        // ----------------------------------------------
                    end
                end
            
                S_GEN_HIDDEN: begin
                    // Inputs are already valid from previous cycle (IDLE or Loop)
                    
                    internal_ram[loop_cnt] <= pe_result;

                    if (loop_cnt == 2) begin
                        state <= S_GEN_OUTPUT;
                        loop_cnt <= 0;
                        mem_addr <= mem_addr+1;
                        
                        // --- FIX 2: Pre-load inputs for Generator Output Layer ---
                        // Note: internal_ram[2] is being written NOW (pe_result), so we bypass
                        pe_x1 <= internal_ram[0];
                        pe_x2 <= internal_ram[1];
                        pe_x3 <= pe_result; // Bypass: Use current result for x3
                        pe_x4 <= 0;
                        pe_act_sel <= 0; // Tanh
                        // ---------------------------------------------------------
                    end else begin
                        loop_cnt <= loop_cnt+1;
                        mem_addr <= mem_addr+1;
                        // Keep inputs stable (Noise) for next neuron
                        pe_x1 <= noise_in1;
                        pe_x2 <= noise_in2;
                    end
                end

                S_GEN_OUTPUT: begin
                    // Cycle 0: Inputs are valid (Pre-loaded from GEN_HIDDEN)
                    // Cycle 1+: Inputs must be re-loaded from RAM
                    
                    internal_ram[3+loop_cnt] <= pe_result;
                    
                    if (loop_cnt == 8) begin
                        state <= S_DIS_HIDDEN;
                        loop_cnt <= 0;
                        acc_step <= 0;
                        mem_addr <= mem_addr+1;
                        
                        // --- FIX 3: Pre-load inputs for Discriminator Hidden ---
                        // Note: internal_ram[11] is being written NOW (pe_result)
                        // This corresponds to Pixel 9.
                        // Discrim inputs: Pixels 1,2,3,4. These are already in RAM [3]..[6]
                        pe_x1 <= internal_ram[3];
                        pe_x2 <= internal_ram[4];
                        pe_x3 <= internal_ram[5];
                        pe_x4 <= internal_ram[6];
                        pe_accumulate <= 0;
                        // --------------------------------------------------------
                    end else begin
                        loop_cnt <= loop_cnt + 1;
                        mem_addr <= mem_addr + 1;
                        
                        // Sustain inputs for next pixel? 
                        // Wait, for Generator Output, the inputs (Hidden Layer) 
                        // are THE SAME for every pixel!
                        // So we don't need to change pe_x here.
                        // However, we must ensure we didn't clear them.
                        // Re-assert them just in case:
                        pe_x1 <= internal_ram[0];
                        pe_x2 <= internal_ram[1];
                        pe_x3 <= internal_ram[2];
                    end
                end

                S_DIS_HIDDEN: begin
                    // Discriminator Hidden logic implies accumulation over 3 passes.
                    // Passes use different input sets from RAM.
                    
                    case (acc_step)
                        0: begin
                            // Current inputs were pre-loaded in previous state (S_GEN_OUTPUT end)
                            // Just save partial sum
                            pe_partial_sum <= pe_result;
                            
                            // Prep next inputs
                            acc_step <= 1;
                            mem_addr <= mem_addr + 1;
                            
                            pe_x1 <= internal_ram[7];
                            pe_x2 <= internal_ram[8];
                            pe_x3 <= internal_ram[9];
                            pe_x4 <= internal_ram[10]; // Pixel 8
                            pe_accumulate <= 1;
                        end

                        1: begin
                            pe_partial_sum <= pe_result;
                            
                            acc_step <= 2;
                            mem_addr <= mem_addr + 1;
                            
                            pe_x1 <= internal_ram[11]; // Pixel 9
                            pe_x2 <= 0;
                            pe_x3 <= 0;
                            pe_x4 <= 0;
                            pe_accumulate <= 1;
                        end
                        
                        2: begin
                            // Final pass for this neuron
                            internal_ram[12+loop_cnt] <= pe_result;
                            
                            if(loop_cnt == 2) begin
                                state <= S_DIS_OUTPUT;
                                loop_cnt <= 0;
                                mem_addr <= mem_addr + 1;
                                
                                // --- FIX 4: Pre-load inputs for Discrim Output ---
                                // Discrim Output uses Discrim Hidden results (RAM 12, 13, 14)
                                // RAM 14 is being written NOW (pe_result)
                                pe_x1 <= internal_ram[12];
                                pe_x2 <= internal_ram[13];
                                pe_x3 <= pe_result; // Bypass
                                pe_x4 <= 0;
                                pe_act_sel <= 1; // Sigmoid
                                pe_accumulate <= 0;
                                // -------------------------------------------------
                            end else begin
                                loop_cnt <= loop_cnt+1;
                                acc_step <= 0;
                                mem_addr <= mem_addr+1;
                                
                                // Prepare inputs for Next Neuron (Pass 0)
                                pe_x1 <= internal_ram[3];
                                pe_x2 <= internal_ram[4];
                                pe_x3 <= internal_ram[5];
                                pe_x4 <= internal_ram[6];
                                pe_accumulate <= 0;
                            end
                        end
                    endcase
                end

                S_DIS_OUTPUT: begin
                    // Inputs valid from pre-load
                    disc_out <= pe_result;
                    state <= S_DONE;
                end

                S_DONE: begin
                    done <= 1;
                    if (!start) state <= S_IDLE;
                end
            endcase
        end
    end

endmodule

src/tb_gan3x3.v
// File         : tb_gan3x3.v
// Description  : Testbench for the gan3x3 module

`timescale 1ns/1ps
`include "gan3x3.v"

module tb_gan3x3;

    parameter DATA_WIDTH = 32;
    real float_out; 

    reg clk;
    reg rst;
    reg start;
    reg signed [DATA_WIDTH-1:0] noise_in1;
    reg signed [DATA_WIDTH-1:0] noise_in2;

    wire signed [DATA_WIDTH-1:0] disc_out;
    wire done;

    gan3x3 #(.DATA_WIDTH(DATA_WIDTH)) u_dut (
        .clk(clk),
        .rst(rst),
        .start(start),
        .noise_in1(noise_in1),
        .noise_in2(noise_in2),
        .disc_out(disc_out),
        .done(done)
    );

    // Clock Generation
    always #5 clk = ~clk;

    // Waveform Dump
    initial begin
        $dumpfile("gan_3x3.vcd");
        $dumpvars(0, tb_gan3x3);
    end

    initial begin
        clk = 0;
        rst = 0;
        start = 0;
        noise_in1 = 0;
        noise_in2 = 0;

        $display("--- Simulation Start ---");

        // Reset Sequence
        #20;
        @(negedge clk);
        rst = 1; // Release Reset
        
        // --------------------------------------------------------
        // Test Case 1: Noise [0.5, -0.2]
        // --------------------------------------------------------
        #20;
        @(negedge clk);
        $display("\n--- Test Case 1: Noise [0.5, -0.2] ---");
        noise_in1 = 32'h0000_8000;  // 0.5
        noise_in2 = 32'hFFFF_CCCD;  // -0.2
        start = 1;
        
        #10;
        @(negedge clk);
        start = 0;

        wait(done);
        @(negedge clk);

        // --- Print Results for Test Case 1 ---
        $display("Done Signal Received!");
        
        // 1. Generator Hidden Layer (G2) - stored in RAM [0..2]
        $display("\n[G2] Generator Hidden Layer Outputs:");
        $display("N1: %h", u_dut.internal_ram[0]);
        $display("N2: %h", u_dut.internal_ram[1]);
        $display("N3: %h", u_dut.internal_ram[2]);

        // 2. Generator Output Layer (G3) - stored in RAM [3..11]
        $display("\n[G3] Generated Fake Image (3x3):");
        $display("[ %h  %h  %h ]", u_dut.internal_ram[3], u_dut.internal_ram[4], u_dut.internal_ram[5]);
        $display("[ %h  %h  %h ]", u_dut.internal_ram[6], u_dut.internal_ram[7], u_dut.internal_ram[8]);
        $display("[ %h  %h  %h ]", u_dut.internal_ram[9], u_dut.internal_ram[10], u_dut.internal_ram[11]);

        // 3. Discriminator Hidden Layer (D2) - stored in RAM [12..14]
        $display("\n[D2] Discriminator Hidden Layer Outputs:");
        $display("N1: %h", u_dut.internal_ram[12]);
        $display("N2: %h", u_dut.internal_ram[13]);
        $display("N3: %h", u_dut.internal_ram[14]);

        // 4. Final Output
        float_out = $signed(disc_out) / 65536.0;
        $display("\n[D3] Discriminator Final Output:");
        $display("Raw Hex: %h", disc_out);
        $display("Probability: %0.4f", float_out);

        #100;
        $display("\n--- Simulation Complete ---");
        $finish;
    end

    // Dump Waveforms
    initial begin
        $dumpfile("gan_waveform.vcd");
        $dumpvars(0, tb_gan3x3);
    end

endmodule

src/gan_waveform.vcd
$date
	Sat Dec 20 17:19:31 2025
$end
$version
	Icarus Verilog
$end
$timescale
	1ps
$end
$scope module tb_gan3x3 $end
$var wire 1 ! done $end
$var wire 32 " disc_out [31:0] $end
$var parameter 32 # DATA_WIDTH $end
$var reg 1 $ clk $end
$var reg 32 % noise_in1 [31:0] $end
$var reg 32 & noise_in2 [31:0] $end
$var reg 1 ' rst $end
$var reg 1 ( start $end
$var real 1 ) float_out $end
$scope module u_dut $end
$var wire 1 $ clk $end
$var wire 32 * noise_in1 [31:0] $end
$var wire 32 + noise_in2 [31:0] $end
$var wire 1 ' rst $end
$var wire 1 ( start $end
$var wire 32 , w4 [31:0] $end
$var wire 32 - w3 [31:0] $end
$var wire 32 . w2 [31:0] $end
$var wire 32 / w1 [31:0] $end
$var wire 32 0 pe_result [31:0] $end
$var wire 32 1 bias [31:0] $end
$var parameter 32 2 DATA_WIDTH $end
$var parameter 3 3 S_DIS_HIDDEN $end
$var parameter 3 4 S_DIS_OUTPUT $end
$var parameter 3 5 S_DONE $end
$var parameter 3 6 S_GEN_HIDDEN $end
$var parameter 3 7 S_GEN_OUTPUT $end
$var parameter 3 8 S_IDLE $end
$var reg 2 9 acc_step [1:0] $end
$var reg 32 : disc_out [31:0] $end
$var reg 1 ! done $end
$var reg 4 ; loop_cnt [3:0] $end
$var reg 10 < mem_addr [9:0] $end
$var reg 1 = pe_accumulate $end
$var reg 2 > pe_act_sel [1:0] $end
$var reg 32 ? pe_partial_sum [31:0] $end
$var reg 32 @ pe_x1 [31:0] $end
$var reg 32 A pe_x2 [31:0] $end
$var reg 32 B pe_x3 [31:0] $end
$var reg 32 C pe_x4 [31:0] $end
$var reg 3 D state [2:0] $end
$scope module u_mem $end
$var wire 10 E addr [9:0] $end
$var wire 1 $ clk $end
$var parameter 32 F ADDR_WIDTH $end
$var parameter 32 G DATA_WIDTH $end
$var reg 32 H bias [31:0] $end
$var reg 32 I w1 [31:0] $end
$var reg 32 J w2 [31:0] $end
$var reg 32 K w3 [31:0] $end
$var reg 32 L w4 [31:0] $end
$upscope $end
$scope module u_pe $end
$var wire 2 M act_sel [1:0] $end
$var wire 32 N bias [31:0] $end
$var wire 1 $ clk $end
$var wire 32 O partial_sum_in [31:0] $end
$var wire 1 = pe_accumulate $end
$var wire 1 ' rst $end
$var wire 32 P w1 [31:0] $end
$var wire 32 Q w2 [31:0] $end
$var wire 32 R w3 [31:0] $end
$var wire 32 S w4 [31:0] $end
$var wire 32 T x1 [31:0] $end
$var wire 32 U x2 [31:0] $end
$var wire 32 V x3 [31:0] $end
$var wire 32 W x4 [31:0] $end
$var wire 32 X tanh_out_32 [31:0] $end
$var wire 16 Y tanh_out_16 [15:0] $end
$var wire 32 Z sum_shifted [31:0] $end
$var wire 32 [ sig_out_32 [31:0] $end
$var wire 16 \ sig_out_16 [15:0] $end
$var wire 64 ] p4_long [63:0] $end
$var wire 32 ^ p4 [31:0] $end
$var wire 64 _ p3_long [63:0] $end
$var wire 32 ` p3 [31:0] $end
$var wire 64 a p2_long [63:0] $end
$var wire 32 b p2 [31:0] $end
$var wire 64 c p1_long [63:0] $end
$var wire 32 d p1 [31:0] $end
$var wire 16 e lut_input [15:0] $end
$var parameter 32 f DATA_WIDTH $end
$var reg 32 g sum_raw [31:0] $end
$var reg 32 h y_out [31:0] $end
$scope module u_sig $end
$var wire 16 i z_q1_7_8 [15:0] $end
$var wire 10 j rom_address [9:0] $end
$var wire 16 k a_sigmoid [15:0] $end
$var parameter 32 l ADDRESS_BITS $end
$var parameter 32 m DATA_WIDTH $end
$var parameter 16 n NEG_CLAMP_THRESHOLD $end
$var parameter 16 o POS_CLAMP_THRESHOLD $end
$var parameter 42 p ROM_DEPTH $end
$var parameter 16 q SIGMOID_MAX_VAL $end
$var parameter 16 r SIGMOID_MIN_VAL $end
$upscope $end
$scope module u_tanh $end
$var wire 16 s z_q1_7_8 [15:0] $end
$var wire 10 t rom_address [9:0] $end
$var wire 16 u a_tanh [15:0] $end
$var parameter 32 v ADDRESS_BITS $end
$var parameter 32 w DATA_WIDTH $end
$var parameter 16 x MAX_NEGATIVE_VAL $end
$var parameter 16 y MAX_POSITIVE_VAL $end
$var parameter 16 z NEG_CLAMP_THRESHOLD $end
$var parameter 16 { POS_CLAMP_THRESHOLD $end
$var parameter 42 | ROM_DEPTH $end
$upscope $end
$upscope $end
$upscope $end
$upscope $end
$enddefinitions $end
$comment Show the parameter values. $end
$dumpall
b10000000000 |
b10100000000 {
b1111101100000000 z
b100000000 y
b1111111100000000 x
b10000 w
b1010 v
b0 r
b100000000 q
b10000000000 p
b11000000000 o
b1111101000000000 n
b10000 m
b1010 l
b100000 f
b100000 G
b1010 F
b0 8
b10 7
b1 6
b101 5
b100 4
b11 3
b100000 2
b100000 #
$end
#0
$dumpvars
b1111111100000000 u
b1110 t
b111011110 s
b1 k
b1110 j
b111011110 i
b11111111111111110000000000000000 h
b11101111001101101 g
b111011110 e
b0 d
b0 c
b0 b
b0 a
b0 `
b0 _
b0 ^
b0 ]
b1 \
b100000000 [
b111011110 Z
b1111111100000000 Y
b11111111111111110000000000000000 X
b0 W
b0 V
b0 U
b0 T
b0 S
b0 R
b11111111111111111111111010111110 Q
b11111111111111111111101000111011 P
b0 O
b11101111001101101 N
b0 M
b0 L
b0 K
b11111111111111111111111010111110 J
b11111111111111111111101000111011 I
b11101111001101101 H
b0 E
b0 D
b0 C
b0 B
b0 A
b0 @
b0 ?
b0 >
0=
b0 <
b0 ;
bx :
b0 9
b11101111001101101 1
b11111111111111110000000000000000 0
b11111111111111111111101000111011 /
b11111111111111111111111010111110 .
b0 -
b0 ,
b0 +
b0 *
r0 )
0(
0'
b0 &
b0 %
0$
bx "
0!
$end
#5000
1$
#10000
0$
#15000
1$
#20000
0$
#25000
1$
#30000
0$
#35000
1$
#40000
0$
#45000
1$
#50000
1'
0$
#55000
1$
#60000
0$
#65000
1$
#70000
1(
b11111111111111111100110011001101 &
b11111111111111111100110011001101 +
b1000000000000000 %
b1000000000000000 *
0$
#75000
b111011011 e
b111011011 i
b111011011 s
b111011011 Z
b11101101111001010 g
b1000000 b
b11111111111111111111110100011101 d
b10000000110011000100110 a
b11111111111111111100110011001101 A
b11111111111111111100110011001101 U
b1111111111111111111111111111111111111101000111011000000000000000 c
b1000000000000000 @
b1000000000000000 T
b1 D
1$
#80000
0(
0$
#85000
b1101 j
b1101 t
b110101010 e
b110101010 i
b110101010 s
b110101010 Z
b1011010 b
b111001 d
b11010101000110000 g
b11010100110011101 1
b11010100110011101 H
b11010100110011101 N
b10110100011001011011001 a
b11111111111111111111111000111101 .
b11111111111111111111111000111101 J
b11111111111111111111111000111101 Q
b1110011000000000000000 c
b1110011 /
b1110011 I
b1110011 P
b1 <
b1 E
b1 ;
1$
#90000
0$
#95000
b10000000000000000 0
b10000000000000000 h
b1111111100000000 [
b10000000000000000 X
b11111111 \
b11111111 k
b100000000 Y
b100000000 u
b1111110100 j
b1111110100 t
b1111111010001001 e
b1111111010001001 i
b1111111010001001 s
b11111111111111111111111010001001 Z
b11010111 b
b11111111111111111111110010110111 d
b11111111111111101000100111110001 g
b11111111111111101000110001100011 1
b11111111111111101000110001100011 H
b11111111111111101000110001100011 N
b110101111111111100101000 a
b11111111111111111111101111001000 .
b11111111111111111111101111001000 J
b11111111111111111111101111001000 Q
b1111111111111111111111111111111111111100101101110000000000000000 c
b11111111111111111111100101101110 /
b11111111111111111111100101101110 I
b11111111111111111111100101101110 P
b10 <
b10 E
b10 ;
1$
#100000
0$
#105000
b11111111111111110000000000000000 0
b11111111111111110000000000000000 h
b100000000 [
b11111111111111110000000000000000 X
b1 \
b1 k
b1111111100000000 Y
b1111111100000000 u
b1011 j
b1011 t
b101101110 e
b101101110 i
b101101110 s
b101101110 Z
b1011100000000000 `
b1011111001100000 b
b1100001110010101 d
b10110111011101001 g
b11111111111111110011010011110100 1
b11111111111111110011010011110100 H
b11111111111111110011010011110100 N
b10111000000000000000000000000000 _
b1011100000000000 -
b1011100000000000 K
b1011100000000000 R
b11111111111111110100000110100000 .
b11111111111111110100000110100000 J
b11111111111111110100000110100000 Q
b11111111111111110011110001101011 /
b11111111111111110011110001101011 I
b11111111111111110011110001101011 P
b10000000000000000 B
b10000000000000000 V
b10111110011000000000000000000000 a
b11111111111111110000000000000000 A
b11111111111111110000000000000000 U
b11000011100101010000000000000000 c
b11111111111111110000000000000000 @
b11111111111111110000000000000000 T
b11 <
b11 E
b0 ;
b10 D
1$
#110000
0$
#115000
b10000000000000000 0
b10000000000000000 h
b1111111100000000 [
b10000000000000000 X
b11111111 \
b11111111 k
b100000000 Y
b100000000 u
b1111111010 j
b1111111010 t
b1111111101010101 e
b1111111101010101 i
b1111111101010101 s
b11111111111111111111111101010101 Z
b11111111111111110111011100100011 `
b11111111111111110000111111100010 b
b11111111111111101001110010100101 d
b11111111111111110101010101101010 g
b100011000111000000 1
b100011000111000000 H
b100011000111000000 N
b1111111111111111111111111111111101110111001000110000000000000000 _
b11111111111111110111011100100011 -
b11111111111111110111011100100011 K
b11111111111111110111011100100011 R
b1111111111111111111111111111111100001111111000100000000000000000 a
b1111000000011110 .
b1111000000011110 J
b1111000000011110 Q
b1111111111111111111111111111111010011100101001010000000000000000 c
b10110001101011011 /
b10110001101011011 I
b10110001101011011 P
b100 <
b100 E
b1 ;
1$
#120000
0$
#125000
b11111111111111110000000000000000 0
b11111111111111110000000000000000 h
b100000000 [
b11111111111111110000000000000000 X
b1 \
b1 k
b1111111100000000 Y
b1111111100000000 u
b111 j
b111 t
b11110010 e
b11110010 i
b11110010 s
b11110010 Z
b1100011110001010 `
b1010011011110000 b
b1000101110111100 d
b1111001010011010 g
b11111111111111101111100001100100 1
b11111111111111101111100001100100 H
b11111111111111101111100001100100 N
b11000111100010100000000000000000 _
b1100011110001010 -
b1100011110001010 K
b1100011110001010 R
b10100110111100000000000000000000 a
b11111111111111110101100100010000 .
b11111111111111110101100100010000 J
b11111111111111110101100100010000 Q
b10001011101111000000000000000000 c
b11111111111111110111010001000100 /
b11111111111111110111010001000100 I
b11111111111111110111010001000100 P
b101 <
b101 E
b10 ;
1$
#130000
0$
#135000
b10000000000000000 0
b10000000000000000 h
b1111111100000000 [
b10000000000000000 X
b11111111 \
b11111111 k
b100000000 Y
b100000000 u
b1111110111 j
b1111110111 t
b1111111011100000 e
b1111111011100000 i
b1111111011100000 s
b11111111111111111111111011100000 Z
b11111111111111110110010000000101 `
b11111111111111101111111101010001 b
b11111111111111101000010010111011 d
b11111111111111101110000001100001 g
b11111100001010000 1
b11111100001010000 H
b11111100001010000 N
b1111111111111111111111111111111101100100000001010000000000000000 _
b11111111111111110110010000000101 -
b11111111111111110110010000000101 K
b11111111111111110110010000000101 R
b1111111111111111111111111111111011111111010100010000000000000000 a
b10000000010101111 .
b10000000010101111 J
b10000000010101111 Q
b1111111111111111111111111111111010000100101110110000000000000000 c
b10111101101000101 /
b10111101101000101 I
b10111101101000101 P
b110 <
b110 E
b11 ;
1$
#140000
0$
