src/sigmoid_lut.v
// File         : sigmoid_lut.v
// Description  : Sigmoid LUT for Q1.15.16 format (32-bit).

module sigmoid_lut (
    input  signed [31:0] z_in,   // Q16.16
    output signed [31:0] a_sigmoid // Q16.16
);
    localparam ADDRESS_BITS = 10;
    localparam DATA_WIDTH   = 32;
    localparam ROM_DEPTH    = 1 << ADDRESS_BITS;

    // Saturation values (Q16.16)
    localparam SIGMOID_MAX_VAL = 32'h00010000; // 1.0
    localparam SIGMOID_MIN_VAL = 32'h00000000; // 0.0

    // Clamp input magnitude at +/-6.0 (Q16.16)
    localparam POS_CLAMP_THRESHOLD = 32'h00060000; // +6.0
    localparam NEG_CLAMP_THRESHOLD = 32'hFFFA0000; // -6.0

    reg [DATA_WIDTH-1:0] SIGMOID_ROM [0:ROM_DEPTH-1];

    initial begin
        // ROM contents loaded from hex file
        $readmemh("mem/sigmoid_lut_mem.hex", SIGMOID_ROM);
    end

    // Use symmetry: compute abs(z) for lookup
    wire is_negative = z_in[31];
    wire signed [31:0] z_abs = is_negative ? -z_in : z_in;

    // Address bits selected from fractional range (resolution ~0.125)
    wire [ADDRESS_BITS-1:0] rom_address = z_abs[22:13];
    wire signed [31:0] rom_data = SIGMOID_ROM[rom_address];

    assign a_sigmoid =
        (z_in >= $signed(POS_CLAMP_THRESHOLD)) ? SIGMOID_MAX_VAL :
        (z_in <= $signed(NEG_CLAMP_THRESHOLD)) ? SIGMOID_MIN_VAL :
        (is_negative ? (SIGMOID_MAX_VAL - rom_data) : rom_data);

endmodule

src/tanh_lut.v
// File         : tanh_lut.v
// Description  : Tanh LUT for Q1.15.16 format (32-bit).

module tanh_lut (
    input  signed [31:0] z_in,   // Q16.16
    output signed [31:0] a_tanh  // Q16.16
);
    localparam ADDRESS_BITS = 10;
    localparam DATA_WIDTH   = 32;
    localparam ROM_DEPTH    = 1 << ADDRESS_BITS;

    // Output saturation values (Q16.16)
    localparam MAX_POSITIVE_VAL = 32'h00010000; // +1.0
    localparam MAX_NEGATIVE_VAL = 32'hFFFF0000; // -1.0

    // Clamp thresholds (+/-6.0 in Q16.16)
    localparam CLAMP_POS = 32'h00060000;
    localparam CLAMP_NEG = 32'hFFFA0000;

    reg [DATA_WIDTH-1:0] TANH_ROM [0:ROM_DEPTH-1];

    initial begin
        // ROM contents loaded from hex file
        $readmemh("mem/tanh_lut_mem.hex", TANH_ROM);
    end

    // Use absolute value for table lookup
    wire signed [31:0] z_abs = z_in[31] ? -z_in : z_in;

    // Address bits taken from fractional region (resolution ~0.125)
    wire [ADDRESS_BITS-1:0] rom_address = z_abs[15:6];
    wire signed [31:0] rom_data = TANH_ROM[rom_address];

    // Output with clamping and symmetry
    assign a_tanh =
        (z_in >= $signed(CLAMP_POS)) ? MAX_POSITIVE_VAL :
        (z_in <= $signed(CLAMP_NEG)) ? MAX_NEGATIVE_VAL :
        (z_in[31] ? -rom_data : rom_data);

endmodule

src/pe_neuron.v
// File         : pe_neuron.v
// Description  : Processing Element (Neuron) module

`timescale 1ns/1ps
`include "sigmoid_lut.v"
`include "tanh_lut.v"

module pe_neuron #(
    parameter DATA_WIDTH = 32
) (
    input wire clk,
    input wire rst,
    input signed [DATA_WIDTH-1:0] x1, x2, x3, x4,
    input signed [DATA_WIDTH-1:0] w1, w2, w3, w4,
    input signed [DATA_WIDTH-1:0] bias,
    
    input wire pe_accumulate,
    input wire signed [DATA_WIDTH-1:0] partial_sum_in,
    input wire [1:0] act_sel,

    output reg signed [DATA_WIDTH-1:0] y_out
);
    // Multiply: Q16.16 inputs * Q16.16 weights -> Q32.32 products
    wire signed [2*DATA_WIDTH-1:0] p1_long = x1 * w1;
    wire signed [2*DATA_WIDTH-1:0] p2_long = x2 * w2;
    wire signed [2*DATA_WIDTH-1:0] p3_long = x3 * w3;
    wire signed [2*DATA_WIDTH-1:0] p4_long = x4 * w4;

    // Shift right by 16 to get back to Q16.16
    wire signed [DATA_WIDTH-1:0] p1 = p1_long >>> 16;
    wire signed [DATA_WIDTH-1:0] p2 = p2_long >>> 16;
    wire signed [DATA_WIDTH-1:0] p3 = p3_long >>> 16;
    wire signed [DATA_WIDTH-1:0] p4 = p4_long >>> 16;

    // Sum products and bias. If accumulating, add partial_sum_in.
    reg signed [DATA_WIDTH-1:0] sum_raw;
    always @(*) begin
        sum_raw = p1 + p2 + p3 + p4 + bias;
        if (pe_accumulate) begin
            sum_raw = sum_raw + partial_sum_in;
        end
    end

    // Convert summed Q16.16 value using LUTs (tanh and sigmoid)
    wire signed [31:0] tanh_out_32, sig_out_32;

    // Pass full 32-bit Q16.16 sum to the LUTs
    tanh_lut u_tanh (
        .z_in(sum_raw),
        .a_tanh(tanh_out_32)
    );

    sigmoid_lut u_sig (
        .z_in(sum_raw), 
        .a_sigmoid(sig_out_32)
    );

    // Select activation output (0=tanh, 1=sigmoid, default=linear)
    always @(*) begin
        case (act_sel)
            2'd0: y_out = tanh_out_32; // Tanh
            2'd1: y_out = sig_out_32;  // Sigmoid
            default: y_out = sum_raw;  // Linear (passthrough)
        endcase
    end

endmodule

src/memory.v
// File: memory.v
// Description: memory module reading weights and biases from hex files

`timescale 1ns/1ps

module memory #(
    parameter DATA_WIDTH = 32,
    parameter ADDR_WIDTH = 10,
    parameter MEM_DEPTH  = 32  // Adjusted to cover all necessary addresses
)(
    input wire clk, 
    input wire [ADDR_WIDTH-1:0] addr,
    output reg signed [DATA_WIDTH-1:0] w1, w2, w3, w4, bias
);

    // Internal memory arrays
    reg [DATA_WIDTH-1:0] mem_w1   [0:MEM_DEPTH-1];
    reg [DATA_WIDTH-1:0] mem_w2   [0:MEM_DEPTH-1];
    reg [DATA_WIDTH-1:0] mem_w3   [0:MEM_DEPTH-1];
    reg [DATA_WIDTH-1:0] mem_w4   [0:MEM_DEPTH-1];
    reg [DATA_WIDTH-1:0] mem_bias [0:MEM_DEPTH-1];

    // Initialize memory from hex files
    initial begin
        $readmemh("mem/w1.hex",   mem_w1);
        $readmemh("mem/w2.hex",   mem_w2);
        $readmemh("mem/w3.hex",   mem_w3);
        $readmemh("mem/w4.hex",   mem_w4);
        $readmemh("mem/bias.hex", mem_bias);
    end

    // Combinational read logic
    always @(*) begin
        if (addr < MEM_DEPTH) begin
            w1   = mem_w1[addr];
            w2   = mem_w2[addr];
            w3   = mem_w3[addr];
            w4   = mem_w4[addr];
            bias = mem_bias[addr];
        end else begin
            w1 = 0; w2 = 0; w3 = 0; w4 = 0; bias = 0;
        end
    end

endmodule

src/gan3x3.v
// File         : gan3x3.v
// Description  : GAN 3x3 module

`timescale 1ns/1ps

`include "memory.v"
`include "pe_neuron.v"

module gan3x3 #(
    parameter DATA_WIDTH = 32
) (
    input wire clk,
    input wire rst,
    input wire start,
    input wire signed [DATA_WIDTH-1:0] noise_in1,
    input wire signed [DATA_WIDTH-1:0] noise_in2,
    output reg signed [DATA_WIDTH-1:0] disc_out,
    output reg done
);
    // Internal RAM and address
    reg signed [DATA_WIDTH-1:0] internal_ram [0:15];
    reg [9:0] mem_addr;

    // Weight outputs from memory and PE I/O
    wire signed [DATA_WIDTH-1:0] w1, w2, w3, w4, bias;
    reg signed [DATA_WIDTH-1:0] pe_x1, pe_x2, pe_x3, pe_x4;
    reg signed [DATA_WIDTH-1:0] pe_partial_sum;
    wire signed [DATA_WIDTH-1:0] pe_result;

    // PE control: accumulation and activation select
    reg pe_accumulate;
    reg [1:0] pe_act_sel; // 0=tanh, 1=sigmoid, 2=alternate tanh

    memory #(.DATA_WIDTH(DATA_WIDTH)) u_mem (
        .clk (clk), .addr(mem_addr),
        .w1(w1), .w2(w2), .w3(w3), .w4(w4), .bias(bias)
    );

    pe_neuron #(.DATA_WIDTH(DATA_WIDTH)) u_pe (
        .clk(clk),
        .rst(rst),
        .x1(pe_x1), .x2(pe_x2), .x3(pe_x3), .x4(pe_x4),
        .w1(w1), .w2(w2), .w3(w3), .w4(w4),
        .bias(bias),
        .pe_accumulate(pe_accumulate),
        .partial_sum_in(pe_partial_sum),
        .act_sel(pe_act_sel),
        .y_out(pe_result)
    );

    // Control states
    localparam S_IDLE = 3'd0;
    localparam S_GEN_HIDDEN = 3'd1;
    localparam S_GEN_OUTPUT = 3'd2;
    localparam S_DIS_HIDDEN = 3'd3;
    localparam S_DIS_OUTPUT = 3'd4;
    localparam S_DONE = 3'd5;

    reg [2:0] state;
    reg [3:0] loop_cnt;
    reg [1:0] acc_step;

    always @(posedge clk or negedge rst) begin
        if (!rst) begin
            state <= S_IDLE;
            mem_addr <= 0;
            done <= 0;
            loop_cnt <= 0;
            acc_step <= 0;
            pe_partial_sum <= 0;
            pe_x1 <= 0;
            pe_x2 <= 0;
            pe_x3 <= 0;
            pe_x4 <= 0;
            pe_accumulate <= 0;
            pe_act_sel <= 0;
        end else begin
            case (state)
                S_IDLE: begin
                    done <= 0;
                    if (start) begin
                        state <= S_GEN_HIDDEN;
                        mem_addr <= 0;
                        loop_cnt <= 0;

                        // Seed generator hidden inputs with noise
                        pe_x1 <= noise_in1;
                        pe_x2 <= noise_in2;
                        pe_x3 <= 0;
                        pe_x4 <= 0;
                        pe_act_sel <= 0; // tanh
                        pe_accumulate <= 0;
                    end
                end
            
                S_GEN_HIDDEN: begin
                    internal_ram[loop_cnt] <= pe_result;

                    if (loop_cnt == 2) begin
                        state <= S_GEN_OUTPUT;
                        loop_cnt <= 0;
                        mem_addr <= mem_addr + 1;

                        // Prepare inputs for generator output stage
                        pe_x1 <= internal_ram[0];
                        pe_x2 <= internal_ram[1];
                        pe_x3 <= pe_result;
                        pe_x4 <= 0;
                        pe_act_sel <= 0;
                        pe_accumulate <= 0;
                    end else begin
                        loop_cnt <= loop_cnt + 1;
                        mem_addr <= mem_addr + 1;
                        pe_x1 <= noise_in1;
                        pe_x2 <= noise_in2;
                        pe_x3 <= 0;
                        pe_x4 <= 0;
                    end
                end

                S_GEN_OUTPUT: begin
                    internal_ram[3 + loop_cnt] <= pe_result;

                    if (loop_cnt == 8) begin
                        state <= S_DIS_HIDDEN;
                        loop_cnt <= 0;
                        acc_step <= 0;
                        mem_addr <= mem_addr + 1;

                        // Load discriminator hidden inputs
                        pe_x1 <= internal_ram[3];
                        pe_x2 <= internal_ram[4];
                        pe_x3 <= internal_ram[5];
                        pe_x4 <= internal_ram[6];
                        pe_act_sel <= 2; // tanh variant
                        pe_accumulate <= 0;
                    end else begin
                        loop_cnt <= loop_cnt + 1;
                        mem_addr <= mem_addr + 1;

                        // Use generator hidden outputs as inputs
                        pe_x1 <= internal_ram[0];
                        pe_x2 <= internal_ram[1];
                        pe_x3 <= internal_ram[2];
                        pe_x4 <= 0;
                    end
                end

                S_DIS_HIDDEN: begin
                    // Discriminator hidden: accumulate over three passes
                    case (acc_step)
                        0: begin
                            // Save partial sum and set inputs for pass 2
                            pe_partial_sum <= pe_result;
                            acc_step <= 1;
                            mem_addr <= mem_addr + 1;
                            pe_x1 <= internal_ram[7];
                            pe_x2 <= internal_ram[8];
                            pe_x3 <= internal_ram[9];
                            pe_x4 <= internal_ram[10];
                            pe_accumulate <= 1;
                        end

                        1: begin
                            // Save partial sum and load remaining inputs
                            pe_partial_sum <= pe_result;
                            acc_step <= 2;
                            mem_addr <= mem_addr + 1;
                            pe_x1 <= internal_ram[11];
                            pe_x2 <= 0;
                            pe_x3 <= 0;
                            pe_x4 <= 0;
                            pe_act_sel <= 0;
                            pe_accumulate <= 1;
                        end
                        
                        2: begin
                            // Final pass: write result to RAM
                            internal_ram[12 + loop_cnt] <= pe_result;

                            if (loop_cnt == 2) begin
                                // Move to discriminator output stage
                                state <= S_DIS_OUTPUT;
                                loop_cnt <= 0;
                                mem_addr <= mem_addr + 1;

                                // Load D3 inputs
                                pe_x1 <= internal_ram[12];
                                pe_x2 <= internal_ram[13];
                                pe_x3 <= pe_result;
                                pe_x4 <= 0;
                                pe_act_sel <= 1; // sigmoid
                                pe_accumulate <= 0;
                            end else begin
                                // Prepare next hidden neuron
                                loop_cnt <= loop_cnt + 1;
                                acc_step <= 0;
                                mem_addr <= mem_addr + 1;
                                pe_x1 <= internal_ram[3];
                                pe_x2 <= internal_ram[4];
                                pe_x3 <= internal_ram[5];
                                pe_x4 <= internal_ram[6];
                                pe_act_sel <= 2;
                                pe_accumulate <= 0;
                            end
                        end
                    endcase
                end

                S_DIS_OUTPUT: begin
                    disc_out <= pe_result;
                    state <= S_DONE;
                end

                S_DONE: begin
                    done <= 1;
                    if (!start) state <= S_IDLE;
                end
            endcase
        end
    end

endmodule

src/tb_gan3x3.v
// File         : tb_gan3x3.v
// Description  : Testbench for the gan3x3 module

`timescale 1ns/1ps
`include "gan3x3.v"

module tb_gan3x3;

    parameter DATA_WIDTH = 32;
    real float_out; 

    reg clk;
    reg rst;
    reg start;
    reg signed [DATA_WIDTH-1:0] noise_in1;
    reg signed [DATA_WIDTH-1:0] noise_in2;

    wire signed [DATA_WIDTH-1:0] disc_out;
    wire done;

    gan3x3 #(.DATA_WIDTH(DATA_WIDTH)) u_dut (
        .clk(clk),
        .rst(rst),
        .start(start),
        .noise_in1(noise_in1),
        .noise_in2(noise_in2),
        .disc_out(disc_out),
        .done(done)
    );

    // Clock Generation
    always #5 clk = ~clk;

    initial begin
        clk = 0;
        rst = 0;
        start = 0;
        noise_in1 = 0;
        noise_in2 = 0;

        $display("--- Simulation Start ---");

        // Reset Sequence
        #50;
        @(negedge clk);
        rst = 1; // Release Reset
        
        // --------------------------------------------------------
        // Test Case 1: Noise [0.5, -0.2]
        // --------------------------------------------------------
        #20;
        @(negedge clk);
        $display("\n--- Test Case 1: Noise [0.5, -0.2] ---");
        noise_in1 = 32'h0000_FFFF;  // 0.5
        noise_in2 = 32'hFFFF_CCCD;  // -0.2
        start = 1;
        
        @(negedge clk);
        start = 0;

        wait(done);
        @(negedge clk);

        // --- Print Results for Test Case 1 ---
        $display("Done Signal Received!");
        
        // 1. Generator Hidden Layer (G2) - stored in RAM [0..2]
        $display("\n[G2] Generator Hidden Layer Outputs:");
        $display("N1: %h", u_dut.internal_ram[0]);
        $display("N2: %h", u_dut.internal_ram[1]);
        $display("N3: %h", u_dut.internal_ram[2]);

        // 2. Generator Output Layer (G3) - stored in RAM [3..11]
        $display("\n[G3] Generated Fake Image (3x3):");
        $display("[ %h  %h  %h ]", u_dut.internal_ram[3], u_dut.internal_ram[4], u_dut.internal_ram[5]);
        $display("[ %h  %h  %h ]", u_dut.internal_ram[6], u_dut.internal_ram[7], u_dut.internal_ram[8]);
        $display("[ %h  %h  %h ]", u_dut.internal_ram[9], u_dut.internal_ram[10], u_dut.internal_ram[11]);

        // 3. Discriminator Hidden Layer (D2) - stored in RAM [12..14]
        $display("\n[D2] Discriminator Hidden Layer Outputs:");
        $display("N1: %h", u_dut.internal_ram[12]);
        $display("N2: %h", u_dut.internal_ram[13]);
        $display("N3: %h", u_dut.internal_ram[14]);

        // 4. Final Output
        float_out = $signed(disc_out) / 65536.0;
        $display("\n[D3] Discriminator Final Output:");
        $display("Raw Hex: %h", disc_out);
        $display("Probability: %0.4f", float_out);

        // --------------------------------------------------------
        // Test Case 2: Noise [-1.0, 1.0]
        // --------------------------------------------------------
        #50;
        @(negedge clk); 
        $display("\n--- Test Case 2: Noise [-1.0, 1.0] ---");
        noise_in1 = 32'hFFFF_0000; // -1.0
        noise_in2 = 32'h0001_0000; //  1.0
        start = 1;
        
        @(negedge clk);
        start = 0;
        
        wait(done);
        @(negedge clk);
        
        // --- Print Results for Test Case 2 ---
        
        // 1. Generator Hidden Layer (G2)
        $display("\n[G2] Generator Hidden Layer Outputs:");
        $display("N1: %h", u_dut.internal_ram[0]);
        $display("N2: %h", u_dut.internal_ram[1]);
        $display("N3: %h", u_dut.internal_ram[2]);
        
        // 2. Generator Output Layer (G3)
        $display("\n[G3] Generated Fake Image (3x3):");
        $display("[ %h  %h  %h ]", u_dut.internal_ram[3], u_dut.internal_ram[4], u_dut.internal_ram[5]);
        $display("[ %h  %h  %h ]", u_dut.internal_ram[6], u_dut.internal_ram[7], u_dut.internal_ram[8]);
        $display("[ %h  %h  %h ]", u_dut.internal_ram[9], u_dut.internal_ram[10], u_dut.internal_ram[11]);

        // 3. Discriminator Hidden Layer (D2)
        $display("\n[D2] Discriminator Hidden Layer Outputs:");
        $display("N1: %h", u_dut.internal_ram[12]);
        $display("N2: %h", u_dut.internal_ram[13]);
        $display("N3: %h", u_dut.internal_ram[14]);

        // 4. Final Output
        float_out = $signed(disc_out) / 65536.0;
        $display("\n[D3] Discriminator Final Output:");
        $display("Raw Hex: %h", disc_out);
        $display("Probability: %0.4f", float_out);

        #100;
        $display("\n--- Simulation Complete ---");
        $finish;
    end

    // Dump Waveforms
    initial begin
        $dumpfile("gan_waveform.vcd");
        $dumpvars(0, tb_gan3x3);
    end

endmodule

src/gan_waveform.vcd
$date
	Sat Dec 20 21:41:22 2025
$end
$version
	Icarus Verilog
$end
$timescale
	1ps
$end
$scope module tb_gan3x3 $end
$var wire 1 ! done $end
$var wire 32 " disc_out [31:0] $end
$var parameter 32 # DATA_WIDTH $end
$var reg 1 $ clk $end
$var reg 32 % noise_in1 [31:0] $end
$var reg 32 & noise_in2 [31:0] $end
$var reg 1 ' rst $end
$var reg 1 ( start $end
$var real 1 ) float_out $end
$scope module u_dut $end
$var wire 1 $ clk $end
$var wire 32 * noise_in1 [31:0] $end
$var wire 32 + noise_in2 [31:0] $end
$var wire 1 ' rst $end
$var wire 1 ( start $end
$var wire 32 , w4 [31:0] $end
$var wire 32 - w3 [31:0] $end
$var wire 32 . w2 [31:0] $end
$var wire 32 / w1 [31:0] $end
$var wire 32 0 pe_result [31:0] $end
$var wire 32 1 bias [31:0] $end
$var parameter 32 2 DATA_WIDTH $end
$var parameter 3 3 S_DIS_HIDDEN $end
$var parameter 3 4 S_DIS_OUTPUT $end
$var parameter 3 5 S_DONE $end
$var parameter 3 6 S_GEN_HIDDEN $end
$var parameter 3 7 S_GEN_OUTPUT $end
$var parameter 3 8 S_IDLE $end
$var reg 2 9 acc_step [1:0] $end
$var reg 32 : disc_out [31:0] $end
$var reg 1 ! done $end
$var reg 4 ; loop_cnt [3:0] $end
$var reg 10 < mem_addr [9:0] $end
$var reg 1 = pe_accumulate $end
$var reg 2 > pe_act_sel [1:0] $end
$var reg 32 ? pe_partial_sum [31:0] $end
$var reg 32 @ pe_x1 [31:0] $end
$var reg 32 A pe_x2 [31:0] $end
$var reg 32 B pe_x3 [31:0] $end
$var reg 32 C pe_x4 [31:0] $end
$var reg 3 D state [2:0] $end
$scope module u_mem $end
$var wire 10 E addr [9:0] $end
$var wire 1 $ clk $end
$var parameter 32 F ADDR_WIDTH $end
$var parameter 32 G DATA_WIDTH $end
$var parameter 32 H MEM_DEPTH $end
$var reg 32 I bias [31:0] $end
$var reg 32 J w1 [31:0] $end
$var reg 32 K w2 [31:0] $end
$var reg 32 L w3 [31:0] $end
$var reg 32 M w4 [31:0] $end
$upscope $end
$scope module u_pe $end
$var wire 2 N act_sel [1:0] $end
$var wire 32 O bias [31:0] $end
$var wire 1 $ clk $end
$var wire 32 P partial_sum_in [31:0] $end
$var wire 1 = pe_accumulate $end
$var wire 1 ' rst $end
$var wire 32 Q w1 [31:0] $end
$var wire 32 R w2 [31:0] $end
$var wire 32 S w3 [31:0] $end
$var wire 32 T w4 [31:0] $end
$var wire 32 U x1 [31:0] $end
$var wire 32 V x2 [31:0] $end
$var wire 32 W x3 [31:0] $end
$var wire 32 X x4 [31:0] $end
$var wire 32 Y tanh_out_32 [31:0] $end
$var wire 32 Z sig_out_32 [31:0] $end
$var wire 64 [ p4_long [63:0] $end
$var wire 32 \ p4 [31:0] $end
$var wire 64 ] p3_long [63:0] $end
$var wire 32 ^ p3 [31:0] $end
$var wire 64 _ p2_long [63:0] $end
$var wire 32 ` p2 [31:0] $end
$var wire 64 a p1_long [63:0] $end
$var wire 32 b p1 [31:0] $end
$var parameter 32 c DATA_WIDTH $end
$var reg 32 d sum_raw [31:0] $end
$var reg 32 e y_out [31:0] $end
$scope module u_sig $end
$var wire 32 f rom_data [31:0] $end
$var wire 32 g z_in [31:0] $end
$var wire 32 h z_abs [31:0] $end
$var wire 10 i rom_address [9:0] $end
$var wire 1 j is_negative $end
$var wire 32 k a_sigmoid [31:0] $end
$var parameter 32 l ADDRESS_BITS $end
$var parameter 32 m DATA_WIDTH $end
$var parameter 32 n NEG_CLAMP_THRESHOLD $end
$var parameter 32 o POS_CLAMP_THRESHOLD $end
$var parameter 42 p ROM_DEPTH $end
$var parameter 32 q SIGMOID_MAX_VAL $end
$var parameter 32 r SIGMOID_MIN_VAL $end
$upscope $end
$scope module u_tanh $end
$var wire 32 s rom_data [31:0] $end
$var wire 32 t z_in [31:0] $end
$var wire 32 u z_abs [31:0] $end
$var wire 10 v rom_address [9:0] $end
$var wire 32 w a_tanh [31:0] $end
$var parameter 32 x ADDRESS_BITS $end
$var parameter 32 y CLAMP_NEG $end
$var parameter 32 z CLAMP_POS $end
$var parameter 32 { DATA_WIDTH $end
$var parameter 32 | MAX_NEGATIVE_VAL $end
$var parameter 32 } MAX_POSITIVE_VAL $end
$var parameter 42 ~ ROM_DEPTH $end
$upscope $end
$upscope $end
$upscope $end
$upscope $end
$enddefinitions $end
$comment Show the parameter values. $end
$dumpall
b10000000000 ~
b10000000000000000 }
b11111111111111110000000000000000 |
b100000 {
b1100000000000000000 z
b11111111111110100000000000000000 y
b1010 x
b0 r
b10000000000000000 q
b10000000000 p
b1100000000000000000 o
b11111111111110100000000000000000 n
b100000 m
b1010 l
b100000 c
b100000 H
b100000 G
b1010 F
b0 8
b10 7
b1 6
b101 5
b100 4
b11 3
b100000 2
b100000 #
$end
#0
$dumpvars
b1111011111111010 w
b100001001 v
b100001001110010001 u
b100001001110010001 t
b1111011111111010 s
b1110000101111011 k
0j
b10000 i
b100001001110010001 h
b100001001110010001 g
b1110000101111011 f
b1111011111111010 e
b100001001110010001 d
b0 b
b0 a
b0 `
b0 _
b0 ^
b0 ]
b0 \
b0 [
b1110000101111011 Z
b1111011111111010 Y
b0 X
b0 W
b0 V
b0 U
b0 T
b0 S
b1010011001 R
b1101101000 Q
b0 P
b100001001110010001 O
b0 N
b0 M
b0 L
b1010011001 K
b1101101000 J
b100001001110010001 I
b0 E
b0 D
b0 C
b0 B
b0 A
b0 @
b0 ?
b0 >
0=
b0 <
b0 ;
bx :
b0 9
b100001001110010001 1
b1111011111111010 0
b1101101000 /
b1010011001 .
b0 -
b0 ,
b0 +
b0 *
r0 )
0(
0'
b0 &
b0 %
0$
bx "
0!
$end
#5000
1$
#10000
0$
#15000
1$
#20000
0$
#25000
1$
#30000
0$
#35000
1$
#40000
0$
#45000
1$
#50000
1'
0$
#55000
1$
#60000
0$
#65000
1$
#70000
1(
b11111111111111111100110011001101 &
b11111111111111111100110011001101 +
b1111111111111111 %
b1111111111111111 *
0$
#75000
b1111100000111001 0
b1111100000111001 e
b1111100000111001 Y
b1111100000111001 w
b1111100000111001 s
b100001011 v
b100001011001110011 h
b100001011001110011 u
b100001011001110011 d
b100001011001110011 g
b100001011001110011 t
b11111111111111111111111101111011 `
b1101100111 b
b1111111111111111111111111111111111111111011110110000000010000101 _
b11111111111111111100110011001101 A
b11111111111111111100110011001101 V
b11011001111111110010011000 a
b1111111111111111 @
b1111111111111111 U
b1 D
1$
#80000
0(
0$
#85000
b11111111111111111110111000001000 0
b11111111111111111110111000001000 e
b1000000000000000 Z
b1000000000000000 k
b11111111111111111110111000001000 Y
b11111111111111111110111000001000 w
b1000000000000000 f
b0 i
b1000111111000 s
b1001 v
1j
b1001110111010 h
b1001110111010 u
b11111111111111111111111100111100 `
b10000000101110 b
b11111111111111111110110001000110 d
b11111111111111111110110001000110 g
b11111111111111111110110001000110 t
b11111111111111111100110011011100 1
b11111111111111111100110011011100 I
b11111111111111111100110011011100 O
b1111111111111111111111111111111111111111001111000110011100101010 _
b1111010010 .
b1111010010 K
b1111010010 R
b100000001011101101111111010001 a
b10000000101111 /
b10000000101111 J
b10000000101111 Q
b1 <
b1 E
b1 ;
1$
#90000
0$
#95000
b110011000000100 0
b110011000000100 e
b1001011110111000 Z
b1001011110111000 k
b110011000000100 Y
b110011000000100 w
b1001011110111000 f
b11 i
b110011000000100 s
b110110 v
0j
b110110011011000 h
b110110011011000 u
b10001100101 `
b11111111111111111101110001010110 b
b110110011011000 d
b110110011011000 g
b110110011011000 t
b1000110000011101 1
b1000110000011101 I
b1000110000011101 O
b100011001011001010100110100 _
b11111111111111111110101000000100 .
b11111111111111111110101000000100 K
b11111111111111111110101000000100 R
b1111111111111111111111111111111111011100010101100010001110101010 a
b11111111111111111101110001010110 /
b11111111111111111101110001010110 J
b11111111111111111101110001010110 Q
b10 <
b10 E
b10 ;
1$
#100000
0$
#105000
b11111111111111110000000100010010 0
b11111111111111110000000100010010 e
b110000100101 Z
b110000100101 k
b11111111111111110000000100010010 Y
b11111111111111110000000100010010 w
b1111001111011011 f
b11000 i
b1111111011101110 s
b110001011 v
1j
b110001011011010111 h
b110001011011010111 u
b11111111111111111111000100011111 ^
b11111111111111111111111100001011 `
b11111111111111101100110011110101 b
b11111111111111001110100100101001 d
b11111111111111001110100100101001 g
b11111111111111001110100100101001 t
b11111111111111100010110000001010 1
b11111111111111100010110000001010 I
b11111111111111100010110000001010 O
b1111111111111111111111111111111111110001000111110010011010101000 ]
b11111111111111111101101010101010 -
b11111111111111111101101010101010 L
b11111111111111111101101010101010 S
b110110100010 .
b110110100010 K
b110110100010 R
b11111111111111101100001101010111 /
b11111111111111101100001101010111 J
b11111111111111101100001101010111 Q
b110011000000100 B
b110011000000100 W
b1111111111111111111111111111111111111111000010110000100100010000 _
b11111111111111111110111000001000 A
b11111111111111111110111000001000 V
b1111111111111111111111111111111011001100111101011100011001011111 a
b1111100000111001 @
b1111100000111001 U
b11 <
b11 E
b0 ;
b10 D
1$
#110000
0$
#115000
b1111111011010100 0
b1111111011010100 e
b1111001111011011 Z
b1111001111011011 k
b1111111011010100 Y
b1111111011010100 w
b1111001111011011 f
b11000 i
b1111111011010100 s
b110000101 v
0j
b110000101100100010 h
b110000101100100010 u
b1101011111001 ^
b101001010 `
b10011110110100110 b
b110000101100100010 d
b110000101100100010 g
b110000101100100010 t
b11011000100111001 1
b11011000100111001 I
b11011000100111001 O
b11010111110011001010011000100 ]
b100001110110001 -
b100001110110001 L
b100001110110001 S
b1010010100010110100000000 _
b11111111111111111110110110100000 .
b11111111111111111110110110100000 K
b11111111111111111110110110100000 R
b100111101101001100010000101001010 a
b10100011110011010 /
b10100011110011010 J
b10100011110011010 Q
b100 <
b100 E
b1 ;
1$
#120000
0$
#125000
b1111111011110111 0
b1111111011110111 e
b1111001111011011 Z
b1111001111011011 k
b1111111011110111 Y
b1111111011110111 w
b1111001111011011 f
b11000 i
b1111111011110111 s
b110001101 v
b110001101001011001 h
b110001101001011001 u
b1101010010111 ^
b11111111111111111111111010011110 `
b10110101110101111 b
b110001101001011001 d
b110001101001011001 g
b110001101001011001 t
b11001010101110101 1
b11001010101110101 I
b11001010101110101 O
b11010100101111111001011110000 ]
b100001010111100 -
b100001010111100 L
b100001010111100 S
b1111111111111111111111111111111111111110100111100110000101110000 _
b1001110101110 .
b1001110101110 K
b1001110101110 R
b101101011101011111101101110101101 a
b10111011100010101 /
b10111011100010101 J
b10111011100010101 Q
b101 <
b101 E
b10 ;
1$
#130000
0$
#135000
b1111111011101110 0
b1111111011101110 e
b1111001111011011 Z
b1111001111011011 k
b1111111011101110 Y
b1111111011101110 w
b1111001111011011 f
b11000 i
b1111111011101110 s
b110001011 v
b110001011110000100 h
b110001011110000100 u
b1000101010010 ^
b11111111111111111111111011100111 `
b10110010001111001 b
b110001011110000100 d
b110001011110000100 g
b110001011110000100 t
b11010001011010010 1
b11010001011010010 I
b11010001011010010 O
b10001010100100111110111100000 ]
b10101101111000 -
b10101101111000 L
b10101101111000 S
b1111111111111111111111111111111111111110111001111111000010110000 _
b111110010110 .
b111110010110 K
b111110010110 R
b101100100011110011011001110111101 a
b10110111110100101 /
b10110111110100101 J
b10110111110100101 Q
b110 <
b110 E
b11 ;
1$
#140000
0$
#145000
b11111111111111110000000100011111 0
b11111111111111110000000100011111 e
b110000100101 Z
b110000100101 k
b11111111111111110000000100011111 Y
b11111111111111110000000100011111 w
b1111001111011011 f
b11000 i
b1111111011100001 s
b110001000 v
1j
b110001000001101010 h
b110001000001101010 u
b11111111111111111111000011111111 ^
b11111111111111111111110001010000 `
b11111111111111101011011011011101 b
b11111111111111001110111110010110 d
b11111111111111001110111110010110 g
b11111111111111001110111110010110 t
b11111111111111100100101101101010 1
b11111111111111100100101101101010 I
b11111111111111100100101101101010 O
b1111111111111111111111111111111111110000111111111010101101101100 ]
b11111111111111111101101001011011 -
b11111111111111111101101001011011 L
b11111111111111111101101001011011 S
b1111111111111111111111111111111111111100010100000010011000111000 _
b11010010000111 .
b11010010000111 K
b11010010000111 R
b1111111111111111111111111111111010110110110111011111101110011110 a
b11111111111111101010110010001110 /
b11111111111111101010110010001110 J
b11111111111111101010110010001110 Q
b111 <
b111 E
b100 ;
1$
#150000
0$
