src/sigmoid_lut.v
// File: sigmoid_lut.v
// Description: Sigmoid Look-Up Table (LUT) implementation with robust clamping logic.
// Format: Q1.7.8 (16 bits total)
// Size: 1024 entries (10 address bits)

module sigmoid_lut (
    input  [15:0] z_q1_7_8,     // Input Z signal (16-bit scaled integer, Q1.7.8)
    output [15:0] a_sigmoid     // Output A_sigmoid (16-bit scaled integer, Q1.7.8)
);

// Configuration Parameters
localparam ADDRESS_BITS = 10;
localparam DATA_WIDTH   = 16;
localparam ROM_DEPTH    = 1 << ADDRESS_BITS; // 1024 entries

// Q1.7.8 fixed-point values for clamping:
// Sigmoid output max is 1.0, min is 0.0.
localparam SIGMOID_MAX_VAL   = 16'h0100; // +1.0 * 256 = 256
localparam SIGMOID_MIN_VAL   = 16'h0000; // +0.0 * 256 = 0

// Thresholds for Clamping Check (Range: [-6.0, 6.0]):
// 6.0 in Q1.7.8: 16'h0600
localparam POS_CLAMP_THRESHOLD = 16'h0600; 
// -6.0 in Q1.7.8: 16'hFA00
localparam NEG_CLAMP_THRESHOLD = 16'hFA00; 

// Internal ROM array (1024 entries, 16 bits wide)
reg [DATA_WIDTH-1:0] SIGMOID_ROM [0:ROM_DEPTH-1];

// --- 1. Memory Initialization ---
initial begin
    // Load the fixed-point Sigmoid values from the .hex file
    $readmemh("mem/sigmoid_lut_mem.hex", SIGMOID_ROM);
    $display("SIGMOID_ROM initialized successfully with %0d entries.", ROM_DEPTH);
end

// --- 2. Address Generation ---
// The address is derived from the middle 10 bits [14:5] of the input Z.
wire [ADDRESS_BITS-1:0] rom_address = z_q1_7_8[14:5];

// --- 3. Combined Clamping and ROM Read Operation ---
// Uses continuous assign for combinational logic.
assign a_sigmoid = 
    // Case 1: Extreme Positive Saturation (Z >= 6.0)
    // Sigmoid(Z) -> 1.0
    ($signed(z_q1_7_8) >= $signed(POS_CLAMP_THRESHOLD)) ? SIGMOID_MAX_VAL :
    
    // Case 2: Extreme Negative Saturation (Z <= -6.0)
    // Sigmoid(Z) -> 0.0  <-- CORRECTED CLAMP VALUE
    ($signed(z_q1_7_8) <= $signed(NEG_CLAMP_THRESHOLD)) ? SIGMOID_MIN_VAL :
    
    // Case 3: Within the Critical Range (-6.0 < Z < 6.0), use the LUT
    SIGMOID_ROM[rom_address];

endmodule

src/tanh_lut.v
// File: tanh_lut.v
// Description: Tanh Look-Up Table (LUT) implementation with robust clamping logic.
// Format: Q1.7.8 (16 bits total)
// Size: 1024 entries (10 address bits)

module tanh_lut (
    input  [15:0] z_q1_7_8,     // Input Z signal (16-bit scaled integer, Q1.7.8)
    output [15:0] a_tanh        // Output A_tanh (16-bit scaled integer, Q1.7.8)
);

// Configuration Parameters
localparam ADDRESS_BITS = 10;
localparam DATA_WIDTH   = 16;
localparam ROM_DEPTH    = 1 << ADDRESS_BITS; // 1024 entries

// Q1.7.8 fixed-point values for clamping:
// +1.0 * 256 = 256
localparam MAX_POSITIVE_VAL = 16'h0100;
// -1.0 * 256 = -256 (Two's Complement: 16'hFF00)
localparam MAX_NEGATIVE_VAL = 16'hFF00;

// Thresholds for Clamping Check:
// We sampled the LUT up to 5.0. To be safe, we check inputs >= 6.0 and <= -6.0.
// 6.0 in Q1.7.8: 5.0 * 256 = 1280 (16'h0500)
localparam POS_CLAMP_THRESHOLD = 16'h0500;
// -6.0 in Q1.7.8: -5.0 * 256 = -1280 (Two's Complement: 16'hFB00)
localparam NEG_CLAMP_THRESHOLD = 16'hFB00;

// Internal ROM array (1024 entries, 16 bits wide)
reg [DATA_WIDTH-1:0] TANH_ROM [0:ROM_DEPTH-1];

// --- 1. Memory Initialization ---
initial begin
    // Load the fixed-point Tanh values from the .hex file
    $readmemh("mem/tanh_lut_mem.hex", TANH_ROM);
    $display("TANH_ROM initialized successfully with %0d entries.", ROM_DEPTH);
end

// --- 2. Address Generation ---
// The address is derived from the middle 10 bits [14:5] of the input Z.
wire [ADDRESS_BITS-1:0] rom_address = z_q1_7_8[14:5];

// --- 3. Combined Clamping and ROM Read Operation ---
// This uses a continuous assign for purely combinational logic (no clock needed for read).
// Note: $signed() casting is crucial for correct comparison in Verilog.
assign a_tanh = 
    // Case 1: Extreme Positive Saturation (Z >= 6.0)
    ($signed(z_q1_7_8) >= $signed(POS_CLAMP_THRESHOLD)) ? MAX_POSITIVE_VAL :
    
    // Case 2: Extreme Negative Saturation (Z <= -6.0)
    ($signed(z_q1_7_8) <= $signed(NEG_CLAMP_THRESHOLD)) ? MAX_NEGATIVE_VAL :
    
    // Case 3: Within the Critical Range (-6.0 < Z < 6.0), use the LUT
    TANH_ROM[rom_address];

endmodule

src/pe_neuron.v
`timescale 1ns/1ps
`include "sigmoid_lut.v"
`include "tanh_lut.v"

module pe_neuron #(
    parameter DATA_WIDTH = 32
) (
    input wire clk, // Kept for compatibility, but unused for output logic
    input wire rst,
    input signed [DATA_WIDTH-1:0] x1, x2, x3, x4,
    input signed [DATA_WIDTH-1:0] w1, w2, w3, w4,
    input signed [DATA_WIDTH-1:0] bias,
    
    input wire pe_accumulate,
    input wire signed [DATA_WIDTH-1:0] partial_sum_in,
    input wire [1:0] act_sel,

    output reg signed [DATA_WIDTH-1:0] y_out
);

    // 1. Multiply
    wire signed [DATA_WIDTH-1:0] p1 = (x1 * w1) >>> 16;
    wire signed [DATA_WIDTH-1:0] p2 = (x2 * w2) >>> 16;
    wire signed [DATA_WIDTH-1:0] p3 = (x3 * w3) >>> 16;
    wire signed [DATA_WIDTH-1:0] p4 = (x4 * w4) >>> 16;
    
    // 2. Summation (Combinational)
    reg signed [DATA_WIDTH-1:0] sum_raw;
    always @(*) begin
        // Calculate Base Sum
        sum_raw = p1 + p2 + p3 + p4 + bias;
        // Add Accumulation if enabled
        if (pe_accumulate) begin
            sum_raw = sum_raw + partial_sum_in;
        end
    end

    // 3. LUT Conversion
    wire signed [31:0] sum_shifted = sum_raw >>> 8;
    wire [15:0] lut_input;
    assign lut_input = (sum_shifted > 32'sd32767)  ? 16'h7FFF :
                       (sum_shifted < -32'sd32768) ? 16'h8000 :
                                                     sum_shifted[15:0];

    wire [15:0] tanh_out_16, sig_out_16;
    tanh_lut u_tanh (.z_q1_7_8(lut_input), .a_tanh(tanh_out_16));
    sigmoid_lut u_sig (.z_q1_7_8(lut_input), .a_sigmoid(sig_out_16));

    wire signed [31:0] tanh_out_32 = $signed(tanh_out_16) <<< 8;
    wire signed [31:0] sig_out_32  = $signed(sig_out_16)  <<< 8;

    // 4. Output Logic (Combinational - REMOVED CLOCK)
    always @(*) begin
        case (act_sel)
            2'd0: y_out = tanh_out_32; // Tanh
            2'd1: y_out = sig_out_32;  // Sigmoid
            default: y_out = sum_raw;  // Linear (Bypass)
        endcase
    end

endmodule

src/memory.v
`timescale 1ns/1ps

module memory #(
    parameter DATA_WIDTH = 32,
    parameter ADDR_WIDTH = 10
)(
    input wire clk,
    input wire [ADDR_WIDTH-1:0] addr,
    output reg signed [DATA_WIDTH-1:0] w1, w2, w3, w4, bias
);

    always @(posedge clk) begin
        case(addr)
            // ============================================================
            // 1. GENERATOR HIDDEN (G2) - Address 0-2
            // Strategy: Kill the noise. Output 0.
            // ============================================================
            10'd0: begin w1 <= 0; w2 <= 0; w3 <= 0; w4 <= 0; bias <= 0; end
            10'd1: begin w1 <= 0; w2 <= 0; w3 <= 0; w4 <= 0; bias <= 0; end
            10'd2: begin w1 <= 0; w2 <= 0; w3 <= 0; w4 <= 0; bias <= 0; end

            // ============================================================
            // 2. GENERATOR OUTPUT (G3) - Address 3-11
            // Strategy: Use BIAS to force the Checkerboard Pattern
            // [ B W B ]
            // [ W B W ]
            // [ B W B ]
            // ============================================================
            
            // Row 1
            10'd3: begin w1<=0; w2<=0; w3<=0; w4<=0; bias<=32'hFFFC_0000; end // Pix 1: BLACK (-4.0)
            10'd4: begin w1<=0; w2<=0; w3<=0; w4<=0; bias<=32'h0004_0000; end // Pix 2: WHITE (+4.0)
            10'd5: begin w1<=0; w2<=0; w3<=0; w4<=0; bias<=32'hFFFC_0000; end // Pix 3: BLACK (-4.0)

            // Row 2
            10'd6: begin w1<=0; w2<=0; w3<=0; w4<=0; bias<=32'h0004_0000; end // Pix 4: WHITE (+4.0)
            10'd7: begin w1<=0; w2<=0; w3<=0; w4<=0; bias<=32'hFFFC_0000; end // Pix 5: BLACK (-4.0)
            10'd8: begin w1<=0; w2<=0; w3<=0; w4<=0; bias<=32'h0004_0000; end // Pix 6: WHITE (+4.0)

            // Row 3
            10'd9: begin w1<=0; w2<=0; w3<=0; w4<=0; bias<=32'hFFFC_0000; end // Pix 7: BLACK (-4.0)
            10'd10:begin w1<=0; w2<=0; w3<=0; w4<=0; bias<=32'h0004_0000; end // Pix 8: WHITE (+4.0)
            10'd11:begin w1<=0; w2<=0; w3<=0; w4<=0; bias<=32'hFFFC_0000; end // Pix 9: BLACK (-4.0)

            // ============================================================
            // 3. DISCRIMINATOR HIDDEN (D2) - Address 12-20
            // Strategy: "Matched Filter". Weights match the image pattern.
            // -1 for Black pixels, +1 for White pixels.
            // ============================================================
            
            // --- Neuron 1 (The Detector) ---
            // Pass 1: Pixels 1-4 (B, W, B, W) -> Weights: -1, 1, -1, 1
            10'd12: begin 
                w1 <= 32'hFFFF_0000; // -1
                w2 <= 32'h0001_0000; //  1
                w3 <= 32'hFFFF_0000; // -1
                w4 <= 32'h0001_0000; //  1
                bias <= 0; 
            end
            
            // Pass 2: Pixels 5-8 (B, W, B, W) -> Weights: -1, 1, -1, 1
            10'd13: begin 
                w1 <= 32'hFFFF_0000; // -1
                w2 <= 32'h0001_0000; //  1
                w3 <= 32'hFFFF_0000; // -1
                w4 <= 32'h0001_0000; //  1
                bias <= 0; 
            end 

            // Pass 3: Pixel 9 (B) -> Weight: -1
            10'd14: begin 
                w1 <= 32'hFFFF_0000; // -1
                w2 <= 0; w3 <= 0; w4 <= 0; 
                bias <= 0; 
            end 

            // --- Neurons 2 & 3 (Unused / Dummy) ---
            10'd15: begin w1<=0; w2<=0; w3<=0; w4<=0; bias<=0; end 
            10'd16: begin w1<=0; w2<=0; w3<=0; w4<=0; bias<=0; end 
            10'd17: begin w1<=0; w2<=0; w3<=0; w4<=0; bias<=0; end 
            10'd18: begin w1<=0; w2<=0; w3<=0; w4<=0; bias<=0; end 
            10'd19: begin w1<=0; w2<=0; w3<=0; w4<=0; bias<=0; end 
            10'd20: begin w1<=0; w2<=0; w3<=0; w4<=0; bias<=0; end 

            // ============================================================
            // 4. DISCRIMINATOR OUTPUT (D3) - Address 21
            // Strategy: Neuron 1 found a match (Sum=9), so weight it high.
            // ============================================================
            10'd21: begin 
                w1 <= 32'h0004_0000; // High weight (+4.0) for Neuron 1
                w2 <= 0; 
                w3 <= 0; 
                w4 <= 0; 
                bias <= 0; 
            end
            
            default: begin w1<=0; w2<=0; w3<=0; w4<=0; bias<=0; end
        endcase
    end
endmodule

src/gan3x3.v
`timescale 1ns/1ps

`include "memory.v"
`include "pe_neuron.v"

module gan3x3 #(
    parameter DATA_WIDTH = 32
) (
    input wire clk,
    input wire rst,
    input wire start,
    input wire signed [DATA_WIDTH-1:0] noise_in1,
    input wire signed [DATA_WIDTH-1:0] noise_in2,
    output reg signed [DATA_WIDTH-1:0] disc_out,
    output reg done
);

// RAM
// Generator

    reg signed [DATA_WIDTH-1:0] internal_ram [0:15];

    reg [9:0] mem_addr;
    wire signed [DATA_WIDTH-1:0] w1, w2, w3, w4, bias;

    reg signed [DATA_WIDTH-1:0] pe_x1, pe_x2, pe_x3, pe_x4;
    reg signed [DATA_WIDTH-1:0] pe_partial_sum;
    wire signed [DATA_WIDTH-1:0] pe_result;

    // Kontrol
    reg pe_accumulate;
    reg [1:0] pe_act_sel; // 0 -> tanh, 1 -> sigmoid

    memory #(.DATA_WIDTH(DATA_WIDTH)) u_mem (
        .clk (clk), .addr(mem_addr),
        .w1(w1), .w2(w2), .w3(w3), .w4(w4), .bias(bias)
    );

    // Inisialisasi Neuron
    pe_neuron #(.DATA_WIDTH(DATA_WIDTH)) u_pe (
        .clk(clk),
        .rst(rst),
        .x1(pe_x1), .x2(pe_x2), .x3(pe_x3), .x4(pe_x4),
        .w1(w1), .w2(w2), .w3(w3), .w4(w4),
        .bias(bias),
        .pe_accumulate(pe_accumulate),
        .partial_sum_in(pe_partial_sum),
        .act_sel(pe_act_sel),
        .y_out(pe_result)
    );

    // Definisi state
    localparam S_IDLE = 3'd0;
    localparam S_GEN_HIDDEN = 3'd1;
    localparam S_GEN_OUTPUT = 3'd2;
    localparam S_DIS_HIDDEN = 3'd3;
    localparam S_DIS_OUTPUT = 3'd4;
    localparam S_DONE = 3'd5;

    reg [2:0] state;
    reg [3:0] loop_cnt; // tunggu neuron
    reg [1:0] acc_step; // untuk disc

    always @(posedge clk or negedge rst) begin
        if (!rst) begin
            state <= S_IDLE;
            mem_addr <= 0;
            done <= 0;
            loop_cnt <= 0;
            acc_step <= 0;
            pe_partial_sum <= 0;

            pe_x1 <= 0;
            pe_x2 <= 0;
            pe_x3 <= 0;
            pe_x4 <= 0;
            pe_accumulate <= 0;
            pe_act_sel <= 0;
        end else begin
            case (state)
                S_IDLE: begin
                    done <= 0;
                    if(start) begin
                        state <= S_GEN_HIDDEN;
                        mem_addr <= 0;
                        loop_cnt <= 0;
                    end
                end
            
                S_GEN_HIDDEN: begin
                    pe_x1 <= noise_in1;
                    pe_x2 <= noise_in2;
                    pe_x3 <= 0;
                    pe_x4 <= 0;
                    pe_accumulate <= 0;
                    pe_act_sel <= 2'd0; // tanh untuk layer hidden generator

                    internal_ram[loop_cnt] <= pe_result;

                    if (loop_cnt == 2) begin
                        state <= S_GEN_OUTPUT;
                        loop_cnt <= 0;
                        mem_addr <= mem_addr+1;
                    end else begin
                        loop_cnt <= loop_cnt+1;
                        mem_addr <= mem_addr+1;
                    end
                end

                // Output Generator
                S_GEN_OUTPUT: begin
                    pe_x1 <= internal_ram[0];
                    pe_x2 <= internal_ram[1];
                    pe_x3 <= internal_ram[2];
                    pe_x4 <= 0;
                    pe_act_sel <= 2'd0; // masih tanh

                    internal_ram[3+loop_cnt] <= pe_result;

                    if (loop_cnt == 8) begin
                        state <= S_DIS_HIDDEN;
                        loop_cnt <= 0;
                        acc_step <= 0;
                        mem_addr <= mem_addr+1;
                    end else begin
                        loop_cnt <= loop_cnt + 1;
                        mem_addr <= mem_addr + 1;
                    end
                end

                S_DIS_HIDDEN: begin
                    case (acc_step)
                        0: begin
                            pe_x1 <= internal_ram[3];
                            pe_x2 <= internal_ram[4];
                            pe_x3 <= internal_ram[5];
                            pe_x4 <= internal_ram[6];
                            pe_accumulate <= 0;
                            pe_act_sel <= 0;

                            pe_partial_sum <= pe_result;
                            acc_step <= 1;
                            mem_addr <= mem_addr +1;
                        end

                        1: begin
                            pe_x1 <= internal_ram[7];
                            pe_x2 <= internal_ram[8];
                            pe_x3 <= internal_ram[9];
                            pe_x4 <= internal_ram[10];
                            pe_accumulate <= 1;
                            pe_act_sel <= 0;

                            pe_partial_sum <= pe_result;
                            acc_step <= 2;
                            mem_addr <= mem_addr + 1;
                        end
                        
                        2: begin
                            pe_x1 <= internal_ram[11];
                            pe_x2 <= 0;
                            pe_x3 <= 0;
                            pe_x4 <= 0;
                            pe_accumulate <= 1;
                            pe_act_sel <= 0;

                            internal_ram[12+loop_cnt] <= pe_result;
                            
                            if(loop_cnt == 2) begin
                                state <= S_DIS_OUTPUT;
                                loop_cnt <= 0;
                                mem_addr <= mem_addr + 1;
                            end else begin
                                loop_cnt <= loop_cnt+1;
                                acc_step <= 0;
                                mem_addr <= mem_addr+1;
                            end
                        end
                    endcase
                end

                S_DIS_OUTPUT: begin
                    pe_x1 <= internal_ram[12];
                    pe_x2 <= internal_ram[13];
                    pe_x3 <= internal_ram[14];
                    pe_x4 <= 0;
                    pe_act_sel <= 1; // sigmoid biar sigma

                    disc_out <= pe_result;
                    state <= S_DONE;
                end

                S_DONE: begin
                    done <= 1;
                    if (!start) state <= S_IDLE;
                end
            endcase
        end
    end

endmodule

src/tb_gan3x3.v
`timescale 1ns/1ps
`include "gan3x3.v"

module tb_gan3x3;

    // ============================================================
    // 1. Parameters & Signals
    // ============================================================
    parameter DATA_WIDTH = 32;
    // Helper to print float values from Q16.16
    real float_out; 

    // Inputs to DUT
    reg clk;
    reg rst;
    reg start;
    reg signed [DATA_WIDTH-1:0] noise_in1;
    reg signed [DATA_WIDTH-1:0] noise_in2;

    // Outputs from DUT
    wire signed [DATA_WIDTH-1:0] disc_out;
    wire done;

    // ============================================================
    // 2. Instantiate the Device Under Test (DUT)
    // ============================================================
    gan3x3 #(.DATA_WIDTH(DATA_WIDTH)) u_dut (
        .clk(clk),
        .rst(rst),
        .start(start),
        .noise_in1(noise_in1),
        .noise_in2(noise_in2),
        .disc_out(disc_out),
        .done(done)
    );

    // ============================================================
    // 3. Clock Generation (10ns Period = 100 MHz)
    // ============================================================
    always #5 clk = ~clk;

    // ============================================================
    // 4. Test Sequence
    // ============================================================
    initial begin
        // Initialize Inputs
        clk = 0;
        rst = 0; // Active Low Reset in your design? Check your rst logic.
                 // Your design uses "if (!rst)" which implies Active Low.
                 // So rst=0 is RESET, rst=1 is RUN.
        start = 0;
        noise_in1 = 0;
        noise_in2 = 0;

        // --------------------------------------------------------
        // Reset Sequence
        // --------------------------------------------------------
        $display("--- Simulation Start ---");
        #50;
        rst = 1; // Release Reset
        #20;

        // --------------------------------------------------------
        // Test Case 1: Run Inference with Noise A
        // --------------------------------------------------------
        $display("\n--- Test Case 1: Noise [0.5, -0.2] ---");
        
        // Input Noise: 0.5 and -0.2 in Q16.16 Fixed Point
        // 0.5 * 65536 = 32768 = 0x8000
        // -0.2 * 65536 = -13107.2 = 0xFFFFCCCD (Twos Comp)
        noise_in1 = 32'h0000_8000; 
        noise_in2 = 32'hFFFF_CCCD;
        
        // Pulse Start
        start = 1;
        #10; 
        start = 0;

        // Wait for completion
        wait(done);
        #10; // Wait a cycle to stabilize

        // --- Print Results ---
        // Convert Q16.16 to Real for readability in console
        float_out = $signed(disc_out) / 65536.0;
        
        $display("Done Signal Received!");
        $display("Discriminator Output (Raw Hex): %h", disc_out);
        $display("Discriminator Probability: %0.4f", float_out);

        // --- Debug: Peek into Internal RAM to see the Fake Image ---
        // Accessing u_dut.internal_ram[3] to [11] (The 9 output pixels)
        $display("Generated Fake Image (3x3):");
        $display("[ %h  %h  %h ]", u_dut.internal_ram[3], u_dut.internal_ram[4], u_dut.internal_ram[5]);
        $display("[ %h  %h  %h ]", u_dut.internal_ram[6], u_dut.internal_ram[7], u_dut.internal_ram[8]);
        $display("[ %h  %h  %h ]", u_dut.internal_ram[9], u_dut.internal_ram[10], u_dut.internal_ram[11]);


        // --------------------------------------------------------
        // Test Case 2: Run Inference with different Noise
        // --------------------------------------------------------
        #50;
        $display("\n--- Test Case 2: Noise [-1.0, 1.0] ---");
        
        // Noise: -1.0 and 1.0
        noise_in1 = 32'hFFFF_0000;
        noise_in2 = 32'h0001_0000;
        
        start = 1;
        #10;
        start = 0;
        
        wait(done); // Wait for done to go High again
        #10;

        float_out = $signed(disc_out) / 65536.0;
        $display("Discriminator Output (Raw Hex): %h", disc_out);
        $display("Discriminator Probability: %0.4f", float_out);
        float_out = $signed(disc_out) / 65536.0;
        $display("Discriminator Output (Raw Hex): %h", disc_out);
        $display("Discriminator Probability: %0.4f", float_out);

        // --- ADD THIS BLOCK TO SEE THE IMAGE FOR TEST CASE 2 ---
        $display("Generated Fake Image (3x3):");
        $display("[ %h  %h  %h ]", u_dut.internal_ram[3], u_dut.internal_ram[4], u_dut.internal_ram[5]);
        $display("[ %h  %h  %h ]", u_dut.internal_ram[6], u_dut.internal_ram[7], u_dut.internal_ram[8]);
        $display("[ %h  %h  %h ]", u_dut.internal_ram[9], u_dut.internal_ram[10], u_dut.internal_ram[11]);
        // -------------------------------------------------------
        // End Simulation
        #100;
        $display("\n--- Simulation Complete ---");
        $finish;
    end

    // Optional: Dump Waveforms for GTKWave / Vivado
    initial begin
        $dumpfile("gan_waveform.vcd");
        $dumpvars(0, tb_gan3x3);
    end

endmodule

src/gan_waveform.vcd
$date
	Sat Dec 20 14:40:36 2025
$end
$version
	Icarus Verilog
$end
$timescale
	1ps
$end
$scope module tb_gan3x3 $end
$var wire 1 ! done $end
$var wire 32 " disc_out [31:0] $end
$var parameter 32 # DATA_WIDTH $end
$var reg 1 $ clk $end
$var reg 32 % noise_in1 [31:0] $end
$var reg 32 & noise_in2 [31:0] $end
$var reg 1 ' rst $end
$var reg 1 ( start $end
$var real 1 ) float_out $end
$scope module u_dut $end
$var wire 1 $ clk $end
$var wire 32 * noise_in1 [31:0] $end
$var wire 32 + noise_in2 [31:0] $end
$var wire 1 ' rst $end
$var wire 1 ( start $end
$var wire 32 , w4 [31:0] $end
$var wire 32 - w3 [31:0] $end
$var wire 32 . w2 [31:0] $end
$var wire 32 / w1 [31:0] $end
$var wire 32 0 pe_result [31:0] $end
$var wire 32 1 bias [31:0] $end
$var parameter 32 2 DATA_WIDTH $end
$var parameter 3 3 S_DIS_HIDDEN $end
$var parameter 3 4 S_DIS_OUTPUT $end
$var parameter 3 5 S_DONE $end
$var parameter 3 6 S_GEN_HIDDEN $end
$var parameter 3 7 S_GEN_OUTPUT $end
$var parameter 3 8 S_IDLE $end
$var reg 2 9 acc_step [1:0] $end
$var reg 32 : disc_out [31:0] $end
$var reg 1 ! done $end
$var reg 4 ; loop_cnt [3:0] $end
$var reg 10 < mem_addr [9:0] $end
$var reg 1 = pe_accumulate $end
$var reg 2 > pe_act_sel [1:0] $end
$var reg 32 ? pe_partial_sum [31:0] $end
$var reg 32 @ pe_x1 [31:0] $end
$var reg 32 A pe_x2 [31:0] $end
$var reg 32 B pe_x3 [31:0] $end
$var reg 32 C pe_x4 [31:0] $end
$var reg 3 D state [2:0] $end
$scope module u_mem $end
$var wire 10 E addr [9:0] $end
$var wire 1 $ clk $end
$var parameter 32 F ADDR_WIDTH $end
$var parameter 32 G DATA_WIDTH $end
$var reg 32 H bias [31:0] $end
$var reg 32 I w1 [31:0] $end
$var reg 32 J w2 [31:0] $end
$var reg 32 K w3 [31:0] $end
$var reg 32 L w4 [31:0] $end
$upscope $end
$scope module u_pe $end
$var wire 2 M act_sel [1:0] $end
$var wire 32 N bias [31:0] $end
$var wire 1 $ clk $end
$var wire 32 O partial_sum_in [31:0] $end
$var wire 1 = pe_accumulate $end
$var wire 1 ' rst $end
$var wire 32 P w1 [31:0] $end
$var wire 32 Q w2 [31:0] $end
$var wire 32 R w3 [31:0] $end
$var wire 32 S w4 [31:0] $end
$var wire 32 T x1 [31:0] $end
$var wire 32 U x2 [31:0] $end
$var wire 32 V x3 [31:0] $end
$var wire 32 W x4 [31:0] $end
$var wire 32 X tanh_out_32 [31:0] $end
$var wire 16 Y tanh_out_16 [15:0] $end
$var wire 32 Z sum_shifted [31:0] $end
$var wire 32 [ sig_out_32 [31:0] $end
$var wire 16 \ sig_out_16 [15:0] $end
$var wire 32 ] p4 [31:0] $end
$var wire 32 ^ p3 [31:0] $end
$var wire 32 _ p2 [31:0] $end
$var wire 32 ` p1 [31:0] $end
$var wire 16 a lut_input [15:0] $end
$var parameter 32 b DATA_WIDTH $end
$var reg 32 c sum_raw [31:0] $end
$var reg 32 d y_out [31:0] $end
$scope module u_sig $end
$var wire 16 e z_q1_7_8 [15:0] $end
$var wire 10 f rom_address [9:0] $end
$var wire 16 g a_sigmoid [15:0] $end
$var parameter 32 h ADDRESS_BITS $end
$var parameter 32 i DATA_WIDTH $end
$var parameter 16 j NEG_CLAMP_THRESHOLD $end
$var parameter 16 k POS_CLAMP_THRESHOLD $end
$var parameter 42 l ROM_DEPTH $end
$var parameter 16 m SIGMOID_MAX_VAL $end
$var parameter 16 n SIGMOID_MIN_VAL $end
$upscope $end
$scope module u_tanh $end
$var wire 16 o z_q1_7_8 [15:0] $end
$var wire 10 p rom_address [9:0] $end
$var wire 16 q a_tanh [15:0] $end
$var parameter 32 r ADDRESS_BITS $end
$var parameter 32 s DATA_WIDTH $end
$var parameter 16 t MAX_NEGATIVE_VAL $end
$var parameter 16 u MAX_POSITIVE_VAL $end
$var parameter 16 v NEG_CLAMP_THRESHOLD $end
$var parameter 16 w POS_CLAMP_THRESHOLD $end
$var parameter 42 x ROM_DEPTH $end
$upscope $end
$upscope $end
$upscope $end
$upscope $end
$enddefinitions $end
$comment Show the parameter values. $end
$dumpall
b10000000000 x
b10100000000 w
b1111101100000000 v
b100000000 u
b1111111100000000 t
b10000 s
b1010 r
b0 n
b100000000 m
b10000000000 l
b11000000000 k
b1111101000000000 j
b10000 i
b1010 h
b100000 b
b100000 G
b1010 F
b0 8
b10 7
b1 6
b101 5
b100 4
b11 3
b100000 2
b100000 #
$end
#0
$dumpvars
bx q
bx p
bx o
bx g
bx f
bx e
bx00000000 d
bx c
bx a
bx `
bx _
bx ^
bx ]
bx \
bx00000000 [
bx Z
bx Y
bx00000000 X
b0 W
b0 V
b0 U
b0 T
bx S
bx R
bx Q
bx P
b0 O
bx N
b0 M
bx L
bx K
bx J
bx I
bx H
b0 E
b0 D
b0 C
b0 B
b0 A
b0 @
b0 ?
b0 >
0=
b0 <
b0 ;
bx :
b0 9
bx 1
bx00000000 0
bx /
bx .
bx -
bx ,
b0 +
b0 *
r0 )
0(
0'
b0 &
b0 %
0$
bx "
0!
$end
#5000
b11111111111111110000000000000000 0
b11111111111111110000000000000000 d
b100000000 [
b11111111111111110000000000000000 X
b1 \
b1 g
b1111111100000000 Y
b1111111100000000 q
b0 f
b0 p
b0 a
b0 e
b0 o
b0 Z
b0 c
b0 ]
b0 ^
b0 _
b0 `
b0 1
b0 H
b0 N
b0 ,
b0 L
b0 S
b0 -
b0 K
b0 R
b0 .
b0 J
b0 Q
b0 /
b0 I
b0 P
1$
#10000
0$
#15000
1$
#20000
0$
#25000
1$
#30000
0$
#35000
1$
#40000
0$
#45000
1$
#50000
0$
1'
#55000
1$
#60000
0$
#65000
1$
#70000
0$
1(
b11111111111111111100110011001101 &
b11111111111111111100110011001101 +
b1000000000000000 %
b1000000000000000 *
#75000
b1 D
1$
#80000
0$
0(
#85000
b1 <
b1 E
b1 ;
b11111111111111111100110011001101 A
b11111111111111111100110011001101 U
b1000000000000000 @
b1000000000000000 T
1$
#90000
0$
#95000
b10 <
b10 E
b10 ;
1$
#100000
0$
#105000
b11 <
b11 E
b0 ;
b10 D
1$
#110000
0$
#115000
b10000000000000000 0
b10000000000000000 d
b1111111100000000 [
b10000000000000000 X
b11111111 \
b11111111 g
b100000000 Y
b100000000 q
b1111100000 f
b1111100000 p
b1111110000000000 a
b1111110000000000 e
b1111110000000000 o
b11111111111111111111110000000000 Z
b11111111111111000000000000000000 c
b11111111111111000000000000000000 1
b11111111111111000000000000000000 H
b11111111111111000000000000000000 N
b100 <
b100 E
b1 ;
b11111111111111110000000000000000 B
b11111111111111110000000000000000 V
b11111111111111110000000000000000 A
b11111111111111110000000000000000 U
b11111111111111110000000000000000 @
b11111111111111110000000000000000 T
1$
#120000
0$
#125000
b11111111111111110000000000000000 0
b11111111111111110000000000000000 d
b100000000 [
b11111111111111110000000000000000 X
b1 \
b1 g
b1111111100000000 Y
b1111111100000000 q
b100000 f
b100000 p
b10000000000 a
b10000000000 e
b10000000000 o
b10000000000 Z
b1000000000000000000 c
b1000000000000000000 1
b1000000000000000000 H
b1000000000000000000 N
b101 <
b101 E
b10 ;
1$
#130000
0$
#135000
b10000000000000000 0
b10000000000000000 d
b1111111100000000 [
b10000000000000000 X
b11111111 \
b11111111 g
b100000000 Y
b100000000 q
b1111100000 f
b1111100000 p
b1111110000000000 a
b1111110000000000 e
b1111110000000000 o
b11111111111111111111110000000000 Z
b11111111111111000000000000000000 c
b11111111111111000000000000000000 1
b11111111111111000000000000000000 H
b11111111111111000000000000000000 N
b110 <
b110 E
b11 ;
1$
#140000
0$
#145000
b11111111111111110000000000000000 0
b11111111111111110000000000000000 d
b100000000 [
b11111111111111110000000000000000 X
b1 \
b1 g
b1111111100000000 Y
b1111111100000000 q
b100000 f
b100000 p
b10000000000 a
b10000000000 e
b10000000000 o
b10000000000 Z
b1000000000000000000 c
b1000000000000000000 1
b1000000000000000000 H
b1000000000000000000 N
b111 <
b111 E
b100 ;
1$
#150000
0$
#155000
b10000000000000000 0
b10000000000000000 d
b1111111100000000 [
b10000000000000000 X
b11111111 \
b11111111 g
b100000000 Y
b100000000 q
b1111100000 f
b1111100000 p
b1111110000000000 a
b1111110000000000 e
b1111110000000000 o
b11111111111111111111110000000000 Z
b11111111111111000000000000000000 c
b11111111111111000000000000000000 1
b11111111111111000000000000000000 H
b11111111111111000000000000000000 N
b1000 <
b1000 E
b101 ;
1$
#160000
0$
#165000
b11111111111111110000000000000000 0
b11111111111111110000000000000000 d
b100000000 [
b11111111111111110000000000000000 X
b1 \
b1 g
b1111111100000000 Y
b1111111100000000 q
b100000 f
b100000 p
b10000000000 a
b10000000000 e
b10000000000 o
b10000000000 Z
b1000000000000000000 c
b1000000000000000000 1
b1000000000000000000 H
b1000000000000000000 N
b1001 <
b1001 E
b110 ;
1$
#170000
0$
#175000
b10000000000000000 0
b10000000000000000 d
b1111111100000000 [
b10000000000000000 X
b11111111 \
b11111111 g
b100000000 Y
b100000000 q
b1111100000 f
b1111100000 p
b1111110000000000 a
b1111110000000000 e
b1111110000000000 o
b11111111111111111111110000000000 Z
b11111111111111000000000000000000 c
b11111111111111000000000000000000 1
b11111111111111000000000000000000 H
b11111111111111000000000000000000 N
b1010 <
b1010 E
b111 ;
1$
#180000
0$
