src/sigmoid_lut.v
// sigmoid_lut: Sigmoid lookup table (Q8.24)
module sigmoid_lut (
    input  signed [31:0] z_in,   // Q8.24
    output signed [31:0] a_sigmoid // Q8.24
);
    localparam ADDRESS_BITS = 10;
    localparam DATA_WIDTH   = 32;
    localparam ROM_DEPTH    = 1 << ADDRESS_BITS;

    // Saturation limits (Q8.24)
    localparam signed [31:0] SIGMOID_MAX_VAL = 32'h01000000; // 1.0 (Q8.24)
    localparam signed [31:0] SIGMOID_MIN_VAL = 32'h00000000; // 0.0

    // Clamp thresholds (±6.0 Q8.24)
    localparam signed [31:0] POS_CLAMP_THRESHOLD = 32'h06000000; // +6.0
    localparam signed [31:0] NEG_CLAMP_THRESHOLD = 32'hFA000000; // -6.0 (two's complement)

    reg [DATA_WIDTH-1:0] SIGMOID_ROM [0:ROM_DEPTH-1];

    // Load ROM
    initial begin
        $readmemh("./mem/sigmoid_lut_mem.hex", SIGMOID_ROM);
    end

    // Use symmetry: sigmoid(-x) = 1 - sigmoid(x)
    wire is_negative = z_in[31];
    wire signed [31:0] z_abs = is_negative ? -z_in : z_in;

    // Address bits [26:17] index ROM (step = 2^-7)
    wire [ADDRESS_BITS-1:0] rom_address = z_abs[26:17];
    wire signed [31:0] rom_data = SIGMOID_ROM[rom_address];

    assign a_sigmoid =
        (z_in >= POS_CLAMP_THRESHOLD) ? SIGMOID_MAX_VAL :
        (z_in <= NEG_CLAMP_THRESHOLD) ? SIGMOID_MIN_VAL :
        (is_negative ? (SIGMOID_MAX_VAL - rom_data) : rom_data);

endmodule

src/tanh_lut.v
// File         : tanh_lut.v
// Description  : Tanh LUT for Q8.24 format

module tanh_lut (
    input  signed [31:0] z_in,   // Q8.24
    output signed [31:0] a_tanh  // Q8.24
);
    localparam ADDRESS_BITS = 10; 
    localparam DATA_WIDTH   = 32;
    localparam ROM_DEPTH    = 1 << ADDRESS_BITS;

    // Saturation limits (Q8.24)
    localparam signed [31:0] MAX_POSITIVE_VAL = 32'h01000000; // +1.0
    localparam signed [31:0] MAX_NEGATIVE_VAL = 32'hFF000000; // -1.0

    // Clamp thresholds (±6.0 Q8.24)
    localparam signed [31:0] CLAMP_POS = 32'h06000000; // +6.0
    localparam signed [31:0] CLAMP_NEG = 32'hFA000000; // -6.0

    reg [DATA_WIDTH-1:0] TANH_ROM [0:ROM_DEPTH-1];

    // Load ROM from hex
    initial begin
        $readmemh("./mem/tanh_lut_mem.hex", TANH_ROM);
    end
    // Use absolute value (symmetric LUT)
    wire signed [31:0] z_abs = z_in[31] ? -z_in : z_in;

    // Address: take bits [26:17] to index LUT (step = 2^-7)
    wire [ADDRESS_BITS-1:0] rom_address = z_abs[26:17];
    wire signed [31:0] rom_data = TANH_ROM[rom_address];

    // Output: clamp then apply sign
    assign a_tanh =
        (z_in >= CLAMP_POS) ? MAX_POSITIVE_VAL :
        (z_in <= CLAMP_NEG) ? MAX_NEGATIVE_VAL :
        (z_in[31] ? -rom_data : rom_data);

endmodule

src/pe_neuron.v
// File         : pe_neuron.v
// Description  : Processing Element (Neuron) module
// Fixed point   : Q8.24 (32-bit signed: 8 integer bits, 24 fractional bits)


`include "tanh_lut.v"
`include "sigmoid_lut.v"

module pe_neuron #(
    parameter DATA_WIDTH = 32
) (
    input wire clk,
    input wire rst,
    input signed [DATA_WIDTH-1:0] x1, x2, x3, x4,
    input signed [DATA_WIDTH-1:0] w1, w2, w3, w4,
    input signed [DATA_WIDTH-1:0] bias,
    input wire pe_accumulate,
    input wire signed [DATA_WIDTH-1:0] partial_sum_in,
    input wire [1:0] act_sel,
    output signed [DATA_WIDTH-1:0] y_out
);

    // Multiplication (Clocked)
    reg signed [DATA_WIDTH-1:0] p1_reg, p2_reg, p3_reg, p4_reg;
    
    // Multipliers (Combinational part)
    wire signed [2*DATA_WIDTH-1:0] p1_long = x1 * w1;
    wire signed [2*DATA_WIDTH-1:0] p2_long = x2 * w2;
    wire signed [2*DATA_WIDTH-1:0] p3_long = x3 * w3;
    wire signed [2*DATA_WIDTH-1:0] p4_long = x4 * w4;

    always @(posedge clk or negedge rst) begin
        if (!rst) begin
            p1_reg <= 0; p2_reg <= 0; p3_reg <= 0; p4_reg <= 0;
        end else begin
            // Shift down to Q8.24 and register (fractional bits = 24)
            p1_reg <= p1_long >>> 24;
            p2_reg <= p2_long >>> 24;
            p3_reg <= p3_long >>> 24;
            p4_reg <= p4_long >>> 24;
        end
    end

    // Summation (Clocked)
    reg signed [DATA_WIDTH-1:0] sum_reg;
    reg [1:0] act_sel_d1; // Delay activation select signal to match pipeline
    
    always @(posedge clk or negedge rst) begin
        if (!rst) begin
            sum_reg <= 0;
            act_sel_d1 <= 0;
        end else begin
            if (pe_accumulate)
                sum_reg <= p1_reg + p2_reg + p3_reg + p4_reg + bias + partial_sum_in;
            else
                sum_reg <= p1_reg + p2_reg + p3_reg + p4_reg + bias;
            
            // Pipeline the control signal
            act_sel_d1 <= act_sel; 
        end
    end
    
    // Activation / LUT (Clocked Output)
    wire signed [DATA_WIDTH-1:0] tanh_out, sig_out;
    reg signed [DATA_WIDTH-1:0] y_final_reg;

    // Combinational Activation Function before getting outputted to y_out/y_final_reg clocked
    tanh_lut u_tanh (.z_in(sum_reg), .a_tanh(tanh_out));
    sigmoid_lut u_sig (.z_in(sum_reg), .a_sigmoid(sig_out));

    always @(posedge clk or negedge rst) begin
        if (!rst) y_final_reg <= 0;
        else begin
            case (act_sel_d1) // Use the delayed control signal
                2'd0: y_final_reg <= tanh_out;
                2'd1: y_final_reg <= sig_out;
                default: y_final_reg <= sum_reg;
            endcase
        end
    end

    assign y_out = y_final_reg;

endmodule

src/memory.v
// File: memory.v
// Description: memory module reading weights and biases from hex files

`timescale 1ns/1ps

module memory #(
    parameter DATA_WIDTH = 32,
    parameter ADDR_WIDTH = 10,
    parameter MEM_DEPTH  = 32
)(
    input wire clk,
    input wire [ADDR_WIDTH-1:0] addr,
    output reg signed [DATA_WIDTH-1:0] w1, w2, w3, w4, bias
);

    // Internal RAM
    reg [DATA_WIDTH-1:0] mem_w1   [0:MEM_DEPTH-1];
    reg [DATA_WIDTH-1:0] mem_w2   [0:MEM_DEPTH-1];
    reg [DATA_WIDTH-1:0] mem_w3   [0:MEM_DEPTH-1];
    reg [DATA_WIDTH-1:0] mem_w4   [0:MEM_DEPTH-1];
    reg [DATA_WIDTH-1:0] mem_bias [0:MEM_DEPTH-1];

    // Load contents from hex files
    initial begin
        $readmemh("mem/w1.hex",   mem_w1);
        $readmemh("mem/w2.hex",   mem_w2);
        $readmemh("mem/w3.hex",   mem_w3);
        $readmemh("mem/w4.hex",   mem_w4);
        $readmemh("mem/bias.hex", mem_bias);
    end

    // Combinational read
    always @(*) begin
        if (addr < MEM_DEPTH) begin
            w1   = mem_w1[addr];
            w2   = mem_w2[addr];
            w3   = mem_w3[addr];
            w4   = mem_w4[addr];
            bias = mem_bias[addr];
        end else begin
            w1 = 0; w2 = 0; w3 = 0; w4 = 0; bias = 0;
        end
    end

endmodule

src/gan3x3.v
// File         : gan3x3.v
// Description  : GAN 3x3 module

`timescale 1ns/1ps

`include "memory.v"
`include "pe_neuron.v"

module gan3x3 #(
    parameter DATA_WIDTH = 32
) (
    input wire clk,
    input wire rst,
    input wire start,
    input wire signed [DATA_WIDTH-1:0] noise_in1,
    input wire signed [DATA_WIDTH-1:0] noise_in2,
    output reg signed [DATA_WIDTH-1:0] disc_out,
    output reg done

    // Internal ram debug temporary signals
    // output wire [DATA_WIDTH-1:0] ram_out_0,
    // output wire [DATA_WIDTH-1:0] ram_out_1,
    // output wire [DATA_WIDTH-1:0] ram_out_2,
    // output wire [DATA_WIDTH-1:0] ram_out_3,
    // output wire [DATA_WIDTH-1:0] ram_out_4,
    // output wire [DATA_WIDTH-1:0] ram_out_5,
    // output wire [DATA_WIDTH-1:0] ram_out_6,
    // output wire [DATA_WIDTH-1:0] ram_out_7,
    // output wire [DATA_WIDTH-1:0] ram_out_8,
    // output wire [DATA_WIDTH-1:0] ram_out_9,
    // output wire [DATA_WIDTH-1:0] ram_out_10,
    // output wire [DATA_WIDTH-1:0] ram_out_11,
    // output wire [DATA_WIDTH-1:0] ram_out_12,
    // output wire [DATA_WIDTH-1:0] ram_out_13,
    // output wire [DATA_WIDTH-1:0] ram_out_14,
    // output wire [DATA_WIDTH-1:0] ram_out_15
);
    // --- RAM ---
    reg signed [DATA_WIDTH-1:0] internal_ram [0:15];
    reg [9:0] mem_addr;

    // Internal ram debug temporary signals
    // assign ram_out_0 = internal_ram[0];
    // assign ram_out_1 = internal_ram[1];
    // assign ram_out_2 = internal_ram[2];
    // assign ram_out_3 = internal_ram[3];
    // assign ram_out_4 = internal_ram[4];
    // assign ram_out_5 = internal_ram[5];
    // assign ram_out_6 = internal_ram[6];
    // assign ram_out_7 = internal_ram[7];
    // assign ram_out_8 = internal_ram[8];
    // assign ram_out_9 = internal_ram[9];
    // assign ram_out_10 = internal_ram[10];
    // assign ram_out_11 = internal_ram[11];
    // assign ram_out_12 = internal_ram[12];
    // assign ram_out_13 = internal_ram[13];
    // assign ram_out_14 = internal_ram[14];
    // assign ram_out_15 = internal_ram[15];
    
    // Weights & PE signals
    wire signed [DATA_WIDTH-1:0] w1, w2, w3, w4, bias;
    reg signed [DATA_WIDTH-1:0] pe_x1, pe_x2, pe_x3, pe_x4;
    reg signed [DATA_WIDTH-1:0] pe_partial_sum;
    wire signed [DATA_WIDTH-1:0] pe_result;
    
    // Control
    reg pe_accumulate;
    reg [1:0] pe_act_sel; // 0 -> tanh, 1 -> sigmoid

    // Pipeline Control
    reg [1:0] pipe_cnt;
    localparam [1:0] PIPE_WAIT = 2'd3; // Kontrol pipeline

    // Instantiations
    memory #(.DATA_WIDTH(DATA_WIDTH)) u_mem (
        .clk (clk), .addr(mem_addr),
        .w1(w1), .w2(w2), .w3(w3), .w4(w4), .bias(bias)
    );
    
    pe_neuron #(.DATA_WIDTH(DATA_WIDTH)) u_pe (
        .clk(clk),
        .rst(rst),
        .x1(pe_x1), .x2(pe_x2), .x3(pe_x3), .x4(pe_x4),
        .w1(w1), .w2(w2), .w3(w3), .w4(w4),
        .bias(bias),
        .pe_accumulate(pe_accumulate),
        .partial_sum_in(pe_partial_sum),
        .act_sel(pe_act_sel),
        .y_out(pe_result)
    );

    // State
    localparam S_IDLE       = 3'd0;
    localparam S_GEN_HIDDEN = 3'd1;
    localparam S_GEN_OUTPUT = 3'd2;
    localparam S_DIS_HIDDEN = 3'd3;
    localparam S_DIS_OUTPUT = 3'd4;
    localparam S_DONE       = 3'd5;

    reg [2:0] state;
    reg [3:0] loop_cnt;
    reg [1:0] acc_step;

    always @(posedge clk or negedge rst) begin
        if (!rst) begin
            state <= S_IDLE;
            mem_addr <= 0;
            done <= 0;
            loop_cnt <= 0;
            acc_step <= 0;
            pipe_cnt <= 0;
            pe_partial_sum <= 0;
            pe_x1 <= 0; pe_x2 <= 0; pe_x3 <= 0; pe_x4 <= 0;
            pe_accumulate <= 0;
            pe_act_sel <= 0;
        end else begin
            case (state)
                S_IDLE: begin
                    done <= 0;
                    if(start) begin
                        state <= S_GEN_HIDDEN;
                        mem_addr <= 0;
                        loop_cnt <= 0;
                        pipe_cnt <= 0; // Reset pipe counter
                        
                        pe_x1 <= noise_in1;
                        pe_x2 <= noise_in2;
                        pe_x3 <= 0;
                        pe_x4 <= 0;
                        pe_act_sel <= 0; // Tanh
                        pe_accumulate <= 0;
                    end
                end
            
                S_GEN_HIDDEN: begin
                    // Tunggu pipeline
                    if (pipe_cnt < PIPE_WAIT) begin
                        pipe_cnt <= pipe_cnt + 1;
                    end else begin
                        internal_ram[loop_cnt] <= pe_result;
                        pipe_cnt <= 0; // Reset counter pipeline

                        if (loop_cnt == 2) begin
                            state <= S_GEN_OUTPUT;
                            loop_cnt <= 0;
                            mem_addr <= mem_addr + 1;
                            
                            pe_x1 <= internal_ram[0];
                            pe_x2 <= internal_ram[1];
                            pe_x3 <= pe_result; // preload
                            pe_x4 <= 0;
                            pe_act_sel <= 0;
                            pe_accumulate <= 0;
                        end else begin
                            loop_cnt <= loop_cnt + 1;
                            mem_addr <= mem_addr + 1;
                            
                            pe_x1 <= noise_in1;
                            pe_x2 <= noise_in2;
                            pe_x3 <= 0;
                            pe_x4 <= 0;
                        end
                    end
                end

                S_GEN_OUTPUT: begin
                    // Tunggu pipeline
                    if (pipe_cnt < PIPE_WAIT) begin
                        pipe_cnt <= pipe_cnt + 1;
                    end else begin

                        internal_ram[3+loop_cnt] <= pe_result;
                        pipe_cnt <= 0; 

                        if (loop_cnt == 8) begin
                            state <= S_DIS_HIDDEN;
                            loop_cnt <= 0;
                            acc_step <= 0;
                            mem_addr <= mem_addr + 1;
                            
                            // Inputs: Pixel 0-3 (RAM 3,4,5,6)
                            pe_x1 <= internal_ram[3];
                            pe_x2 <= internal_ram[4];
                            pe_x3 <= internal_ram[5];
                            pe_x4 <= internal_ram[6];
                            pe_act_sel <= 2; // bypass
                            pe_accumulate <= 0;
                        end else begin
                            loop_cnt <= loop_cnt + 1;
                            mem_addr <= mem_addr + 1;
                            
                            pe_x1 <= internal_ram[0];
                            pe_x2 <= internal_ram[1];
                            pe_x3 <= internal_ram[2];
                            pe_x4 <= 0;
                        end
                    end
                end

                S_DIS_HIDDEN: begin
                    
                    if (pipe_cnt < PIPE_WAIT) begin
                        pipe_cnt <= pipe_cnt + 1;
                    end else begin
                        pipe_cnt <= 0;

                        case (acc_step)
                            0: begin
                                pe_partial_sum <= pe_result;
                                
                                acc_step <= 1;
                                mem_addr <= mem_addr + 1;
                                
                                pe_x1 <= internal_ram[7];
                                pe_x2 <= internal_ram[8];
                                pe_x3 <= internal_ram[9];
                                pe_x4 <= internal_ram[10];
                                pe_accumulate <= 1; // Akumulasi
                            end

                            1: begin
                                pe_partial_sum <= pe_result;
                                
                                acc_step <= 2;
                                mem_addr <= mem_addr + 1;
                                
                                pe_x1 <= internal_ram[11];
                                pe_x2 <= 0;
                                pe_x3 <= 0;
                                pe_x4 <= 0;
                                pe_act_sel <= 0;
                                pe_accumulate <= 1;
                            end
                            
                            2: begin
                                internal_ram[12+loop_cnt] <= pe_result;
                                
                                if(loop_cnt == 2) begin
                                    state <= S_DIS_OUTPUT;
                                    loop_cnt <= 0;
                                    mem_addr <= mem_addr + 1;
                                    
                                    //RAM 12, 13, 14
                                    pe_x1 <= internal_ram[12];
                                    pe_x2 <= internal_ram[13];
                                    pe_x3 <= pe_result;
                                    pe_x4 <= 0;
                                    pe_act_sel <= 1; // Sigmoid
                                    pe_accumulate <= 0;
                                end else begin
                                    loop_cnt <= loop_cnt + 1;
                                    acc_step <= 0;
                                    mem_addr <= mem_addr + 1;
                                    
                                    // Pass 0
                                    pe_x1 <= internal_ram[3];
                                    pe_x2 <= internal_ram[4];
                                    pe_x3 <= internal_ram[5];
                                    pe_x4 <= internal_ram[6];
                                    pe_act_sel <= 2;    
                                    pe_accumulate <= 0;
                                end
                            end
                        endcase
                    end
                end

                S_DIS_OUTPUT: begin
                    if (pipe_cnt < PIPE_WAIT) begin
                        pipe_cnt <= pipe_cnt + 1;
                    end else begin
                        // Final Output
                        disc_out <= pe_result;
                        state <= S_DONE;
                    end
                end

                S_DONE: begin
                    done <= 1;
                    if (!start) state <= S_IDLE;
                end
                
                default: state <= S_IDLE;
            endcase
        end
    end

endmodule

src/tb_gan3x3.v
// File         : tb_gan3x3.v
// Description  : Testbench for the gan3x3 module

`timescale 1ns/1ps
`include "gan3x3.v"

module tb_gan3x3;

    parameter DATA_WIDTH = 32;
    real float_out; 

    reg clk;
    reg rst;
    reg start;
    reg signed [DATA_WIDTH-1:0] noise_in1;
    reg signed [DATA_WIDTH-1:0] noise_in2;

    wire signed [DATA_WIDTH-1:0] disc_out;
    wire done;

    gan3x3 #(.DATA_WIDTH(DATA_WIDTH)) u_dut (
        .clk(clk),
        .rst(rst),
        .start(start),
        .noise_in1(noise_in1),
        .noise_in2(noise_in2),
        .disc_out(disc_out),
        .done(done)
    );

    // Clock
    always #5 clk = ~clk;
    
    // Helper: Q8.24 to real
    function real q8_24_to_real;
        input signed [31:0] val;
        begin
            q8_24_to_real = $signed(val) / 16777216.0; // 2^24
        end
    endfunction

    integer i, r, c, idx;


    // Waveform Dump
    initial begin
        $dumpfile("gan_3x3.vcd");
        $dumpvars(0, tb_gan3x3);
    end

    initial begin
        clk = 0;
        rst = 0;
        start = 0;
        noise_in1 = 0;
        noise_in2 = 0;

        $display("Simulation start");

        // Reset
        #20; @(negedge clk); rst = 1;

        // Test case: noise [0.5, -0.2]
        #20; @(negedge clk);
        $display("Test case: noise [0.5, -0.2]");
        noise_in1 = 32'h0080_0000;  // 0.5  -> 0.5 * 2^24 = 0x00800000
        noise_in2 = 32'hFFCC_CCCD;  // -0.2 -> -0.2 * 2^24 = 0xFFCCCCCD
        start = 1;
        
        #10;
        @(negedge clk);
        start = 0;

        wait(done);
        @(negedge clk);

        $display("");
        $display("RESULTS (Q8.24)");
        $display("");

        // G2: generator hidden (RAM 0..2)
        $display("G2:");
        for (i = 0; i < 3; i = i + 1) begin
            $display("N%0d: %h (%0.6f)", i+1, u_dut.internal_ram[i], q8_24_to_real(u_dut.internal_ram[i]));
        end

        // G3: generated image (float)
        $display("");
        $display("G3: image (float)");
        $display("");
        for (r = 0; r < 3; r = r + 1) begin
            idx = 3 + r*3;
            $display("%0.6f %0.6f %0.6f",
                q8_24_to_real(u_dut.internal_ram[idx]),
                q8_24_to_real(u_dut.internal_ram[idx+1]),
                q8_24_to_real(u_dut.internal_ram[idx+2])
            );
        end
        $display("");
        $display("G3: image (hex)");
        $display("");
        for (r = 0; r < 3; r = r + 1) begin
            idx = 3 + r*3;
            $display("%h %h %h",
                u_dut.internal_ram[idx], u_dut.internal_ram[idx+1], u_dut.internal_ram[idx+2]
            );
        end
        // D2: discriminator hidden (RAM 12..14)
        $display("");
        $display("D2: hidden");
        $display("");
        for (i = 0; i < 3; i = i + 1) begin
            $display("N%0d: %h (%0.6f)", i+1, u_dut.internal_ram[12 + i], q8_24_to_real(u_dut.internal_ram[12 + i]));
        end

        // D3: final output
        float_out = q8_24_to_real(disc_out);
        $display("");
        $display("D3: final");
        $display("");
        $display("Raw: %h", disc_out);
        $display("Prob: %0.6f", float_out);

        #100;
        $display("\n--- Simulation Complete ---");
        $finish;
    end

endmodule

src/gan_3x3.vcd
$date
	Sat Jan 10 06:06:36 2026
$end
$version
	Icarus Verilog
$end
$timescale
	1ps
$end
$scope module tb_gan3x3 $end
$var wire 1 ! done $end
$var wire 32 " disc_out [31:0] $end
$var parameter 32 # DATA_WIDTH $end
$var reg 1 $ clk $end
$var reg 32 % noise_in1 [31:0] $end
$var reg 32 & noise_in2 [31:0] $end
$var reg 1 ' rst $end
$var reg 1 ( start $end
$var real 1 ) float_out $end
$var integer 32 * i [31:0] $end
$var integer 32 + idx [31:0] $end
$var integer 32 , r [31:0] $end
$scope function q8_24_to_real $end
$var reg 32 - val [31:0] $end
$upscope $end
$scope module u_dut $end
$var wire 1 $ clk $end
$var wire 32 . noise_in1 [31:0] $end
$var wire 32 / noise_in2 [31:0] $end
$var wire 1 ' rst $end
$var wire 1 ( start $end
$var wire 32 0 w4 [31:0] $end
$var wire 32 1 w3 [31:0] $end
$var wire 32 2 w2 [31:0] $end
$var wire 32 3 w1 [31:0] $end
$var wire 32 4 pe_result [31:0] $end
$var wire 32 5 bias [31:0] $end
$var parameter 32 6 DATA_WIDTH $end
$var parameter 2 7 PIPE_WAIT $end
$var parameter 3 8 S_DIS_HIDDEN $end
$var parameter 3 9 S_DIS_OUTPUT $end
$var parameter 3 : S_DONE $end
$var parameter 3 ; S_GEN_HIDDEN $end
$var parameter 3 < S_GEN_OUTPUT $end
$var parameter 3 = S_IDLE $end
$var reg 2 > acc_step [1:0] $end
$var reg 32 ? disc_out [31:0] $end
$var reg 1 ! done $end
$var reg 4 @ loop_cnt [3:0] $end
$var reg 10 A mem_addr [9:0] $end
$var reg 1 B pe_accumulate $end
$var reg 2 C pe_act_sel [1:0] $end
$var reg 32 D pe_partial_sum [31:0] $end
$var reg 32 E pe_x1 [31:0] $end
$var reg 32 F pe_x2 [31:0] $end
$var reg 32 G pe_x3 [31:0] $end
$var reg 32 H pe_x4 [31:0] $end
$var reg 2 I pipe_cnt [1:0] $end
$var reg 3 J state [2:0] $end
$scope module u_mem $end
$var wire 10 K addr [9:0] $end
$var wire 1 $ clk $end
$var parameter 32 L ADDR_WIDTH $end
$var parameter 32 M DATA_WIDTH $end
$var parameter 32 N MEM_DEPTH $end
$var reg 32 O bias [31:0] $end
$var reg 32 P w1 [31:0] $end
$var reg 32 Q w2 [31:0] $end
$var reg 32 R w3 [31:0] $end
$var reg 32 S w4 [31:0] $end
$upscope $end
$scope module u_pe $end
$var wire 2 T act_sel [1:0] $end
$var wire 32 U bias [31:0] $end
$var wire 1 $ clk $end
$var wire 32 V partial_sum_in [31:0] $end
$var wire 1 B pe_accumulate $end
$var wire 1 ' rst $end
$var wire 32 W w1 [31:0] $end
$var wire 32 X w2 [31:0] $end
$var wire 32 Y w3 [31:0] $end
$var wire 32 Z w4 [31:0] $end
$var wire 32 [ x1 [31:0] $end
$var wire 32 \ x2 [31:0] $end
$var wire 32 ] x3 [31:0] $end
$var wire 32 ^ x4 [31:0] $end
$var wire 32 _ y_out [31:0] $end
$var wire 32 ` tanh_out [31:0] $end
$var wire 32 a sig_out [31:0] $end
$var wire 64 b p4_long [63:0] $end
$var wire 64 c p3_long [63:0] $end
$var wire 64 d p2_long [63:0] $end
$var wire 64 e p1_long [63:0] $end
$var parameter 32 f DATA_WIDTH $end
$var reg 2 g act_sel_d1 [1:0] $end
$var reg 32 h p1_reg [31:0] $end
$var reg 32 i p2_reg [31:0] $end
$var reg 32 j p3_reg [31:0] $end
$var reg 32 k p4_reg [31:0] $end
$var reg 32 l sum_reg [31:0] $end
$var reg 32 m y_final_reg [31:0] $end
$scope module u_sig $end
$var wire 32 n rom_data [31:0] $end
$var wire 32 o z_in [31:0] $end
$var wire 32 p z_abs [31:0] $end
$var wire 10 q rom_address [9:0] $end
$var wire 1 r is_negative $end
$var wire 32 s a_sigmoid [31:0] $end
$var parameter 32 t ADDRESS_BITS $end
$var parameter 32 u DATA_WIDTH $end
$var parameter 32 v NEG_CLAMP_THRESHOLD $end
$var parameter 32 w POS_CLAMP_THRESHOLD $end
$var parameter 42 x ROM_DEPTH $end
$var parameter 32 y SIGMOID_MAX_VAL $end
$var parameter 32 z SIGMOID_MIN_VAL $end
$upscope $end
$scope module u_tanh $end
$var wire 32 { rom_data [31:0] $end
$var wire 32 | z_in [31:0] $end
$var wire 32 } z_abs [31:0] $end
$var wire 10 ~ rom_address [9:0] $end
$var wire 32 !" a_tanh [31:0] $end
$var parameter 32 "" ADDRESS_BITS $end
$var parameter 32 #" CLAMP_NEG $end
$var parameter 32 $" CLAMP_POS $end
$var parameter 32 %" DATA_WIDTH $end
$var parameter 32 &" MAX_NEGATIVE_VAL $end
$var parameter 32 '" MAX_POSITIVE_VAL $end
$var parameter 42 (" ROM_DEPTH $end
$upscope $end
$upscope $end
$upscope $end
$upscope $end
$enddefinitions $end
$comment Show the parameter values. $end
$dumpall
b10000000000 ("
b1000000000000000000000000 '"
b11111111000000000000000000000000 &"
b100000 %"
b110000000000000000000000000 $"
b11111010000000000000000000000000 #"
b1010 ""
b0 z
b1000000000000000000000000 y
b10000000000 x
b110000000000000000000000000 w
b11111010000000000000000000000000 v
b100000 u
b1010 t
b100000 f
b100000 N
b100000 M
b1010 L
b0 =
b10 <
b1 ;
b101 :
b100 9
b11 8
b11 7
b100000 6
b100000 #
$end
#0
$dumpvars
b0 !"
b0 ~
b0 }
b0 |
b0 {
b100000000000000000000000 s
0r
b0 q
b0 p
b0 o
b100000000000000000000000 n
b0 m
b0 l
b0 k
b0 j
b0 i
b0 h
b0 g
b0 e
b0 d
b0 c
b0 b
b100000000000000000000000 a
b0 `
b0 _
b0 ^
b0 ]
b0 \
b0 [
b0 Z
b0 Y
b101101110110110011 X
b1011101100111110 W
b0 V
b1111101010010100110101000 U
b0 T
b0 S
b0 R
b101101110110110011 Q
b1011101100111110 P
b1111101010010100110101000 O
b0 K
b0 J
b0 I
b0 H
b0 G
b0 F
b0 E
b0 D
b0 C
0B
b0 A
b0 @
bx ?
b0 >
b1111101010010100110101000 5
b0 4
b1011101100111110 3
b101101110110110011 2
b0 1
b0 0
b0 /
b0 .
bx -
bx ,
bx +
bx *
r0 )
0(
0'
b0 &
b0 %
0$
bx "
0!
$end
#5000
1$
#10000
0$
#15000
1$
#20000
1'
0$
#25000
b111000000011001110010011 a
b111000000011001110010011 s
b111101011110011101011111 `
b111101011110011101011111 !"
b111000000011001110010011 n
b11111010 q
b111101011110011101011111 {
b11111010 ~
b1111101010010100110101000 p
b1111101010010100110101000 }
b1111101010010100110101000 l
b1111101010010100110101000 o
b1111101010010100110101000 |
1$
#30000
0$
#35000
b111101011110011101011111 4
b111101011110011101011111 _
b111101011110011101011111 m
1$
#40000
1(
b11111111110011001100110011001101 &
b11111111110011001100110011001101 /
b100000000000000000000000 %
b100000000000000000000000 .
0$
#45000
b1111111111111111111111110110110101000010100110100010110001010111 d
b11111111110011001100110011001101 F
b11111111110011001100110011001101 \
b101110110011111000000000000000000000000 e
b100000000000000000000000 E
b100000000000000000000000 [
b1 J
1$
#50000
0(
0$
#55000
b11111111111111110110110101000010 i
b101110110011111 h
b1 I
1$
#60000
0$
#65000
b1111101001111010010001001 p
b1111101001111010010001001 }
b10 I
b1111101001111010010001001 l
b1111101001111010010001001 o
b1111101001111010010001001 |
1$
#70000
0$
#75000
b11 I
1$
#80000
0$
#85000
b1000011000110000111010110 5
b1000011000110000111010110 O
b1000011000110000111010110 U
b1111111111111111111111110100101011111110110011011000000111001110 d
b111000100100000110 2
b111000100100000110 Q
b111000100100000110 X
b1111110110100001010100000000000000000000000 e
b11111101101000010101 3
b11111101101000010101 P
b11111101101000010101 W
b1 A
b1 K
b1 @
b0 I
1$
#90000
0$
#95000
b101111010111110000010001 a
b101111010111110000010001 s
b110001111101010010100101 `
b110001111101010010100101 !"
b101111010111110000010001 n
b10000110 q
b110001111101010010100101 {
b10000110 ~
b1000011000010110010110111 p
b1000011000010110010110111 }
b11111111111111110100101011111110 i
b1111110110100001010 h
b1000011000010110010110111 l
b1000011000010110010110111 o
b1000011000010110010110111 |
b1 I
1$
#100000
0$
#105000
b101111101010000111001100 a
b101111101010000111001100 s
b110010100010000111011000 `
b110010100010000111011000 !"
b101111101010000111001100 n
b10001001 q
b110010100010000111011000 {
b10001001 ~
b1000100111001100111011110 p
b1000100111001100111011110 }
b10 I
b110001111101010010100101 4
b110001111101010010100101 _
b110001111101010010100101 m
b1000100111001100111011110 l
b1000100111001100111011110 o
b1000100111001100111011110 |
1$
#110000
0$
#115000
b110010100010000111011000 4
b110010100010000111011000 _
b110010100010000111011000 m
b11 I
1$
#120000
0$
#125000
b110011101101000110010110 5
b110011101101000110010110 O
b110011101101000110010110 U
b110100001000001000111111001011110111110111 d
b11111111111011111011010111010011 2
b11111111111011111011010111010011 Q
b11111111111011111011010111010011 X
b1111111111111111111100011000110001110101000000000000000000000000 e
b11111111111000110001100011101010 3
b11111111111000110001100011101010 P
b11111111111000110001100011101010 W
b10 A
b10 K
b10 @
b0 I
1$
#130000
0$
#135000
b101100101001011001111111 a
b101100101001011001111111 s
b101011110000001111000101 `
b101011110000001111000101 !"
b101100101001011001111111 n
b1101011 q
b101011110000001111000101 {
b1101011 ~
b110101100000100110011110 p
b110101100000100110011110 }
b110100001000001000 i
b11111111111100011000110001110101 h
b110101100000100110011110 l
b110101100000100110011110 o
b110101100000100110011110 |
b1 I
1$
#140000
0$
#145000
b101011100100111000001111 a
b101011100100111000001111 s
b101000111100100100001111 `
b101000111100100100001111 !"
b101011100100111000001111 n
b1100001 q
b101000111100100100001111 {
b1100001 ~
b110000111010000000010011 p
b110000111010000000010011 }
b10 I
b101011110000001111000101 4
b101011110000001111000101 _
b101011110000001111000101 m
b110000111010000000010011 l
b110000111010000000010011 o
b110000111010000000010011 |
1$
#150000
0$
#155000
b101000111100100100001111 4
b101000111100100100001111 _
b101000111100100100001111 m
b11 I
1$
#160000
0$
#165000
b1110000000111111010001001 5
b1110000000111111010001001 O
b1110000000111111010001001 U
b1110010011100110110001010001111110100110101001 c
b10110010111000111000111 1
b10110010111000111000111 R
b10110010111000111000111 Y
b11001001000001111010011 2
b11001001000001111010011 Q
b11001001000001111010011 X
b1000000000101000011000100 3
b1000000000101000011000100 P
b1000000000101000011000100 W
b101000111100100100001111 G
b101000111100100100001111 ]
b10011110101110101001110010010110110110100001000 d
b110010100010000111011000 F
b110010100010000111011000 \
b111101100011010011110011100100101101010010111100 e
b111101011110011101011111 E
b111101011110011101011111 [
b11 A
b11 K
b0 @
b10 J
b0 I
1$
#170000
0$
#175000
b110110001000111110101110 a
b110110001000111110101110 s
b111011111001000001111111 `
b111011111001000001111111 !"
b110110001000111110101110 n
b11011010 q
b111011111001000001111111 {
b11011010 ~
b1101101010100110100000110 p
b1101101010100110100000110 }
b1110010011100110110001 j
b10011110101110101001110 i
b111101100011010011110011 h
b1101101010100110100000110 l
b1101101010100110100000110 o
b1101101010100110100000110 |
b1 I
1$
#180000
0$
