src/sigmoid_lut.v
// File         : sigmoid_lut.v
// Description  : Sigmoid LUT for Q16.16 format (High Precision)

module sigmoid_lut (
    input  signed [31:0] z_in,   // Q16.16
    output signed [31:0] a_sigmoid // Q16.16
);
    localparam ADDRESS_BITS = 10;
    localparam DATA_WIDTH   = 32;
    localparam ROM_DEPTH    = 1 << ADDRESS_BITS;

    // Saturation values (Q16.16)
    localparam signed [31:0] SIGMOID_MAX_VAL = 32'h00010000; // 1.0
    localparam signed [31:0] SIGMOID_MIN_VAL = 32'h00000000; // 0.0

    // Clamp input magnitude at +/-6.0 (Q16.16)
    // LUT covers up to 8.0, so 6.0 is safe.
    localparam signed [31:0] POS_CLAMP_THRESHOLD = 32'h00060000; // +6.0
    localparam signed [31:0] NEG_CLAMP_THRESHOLD = 32'hFFFA0000; // -6.0

    reg [DATA_WIDTH-1:0] SIGMOID_ROM [0:ROM_DEPTH-1];

    initial begin
        // Ensure path matches Python script output
        $readmemh("./mem/sigmoid_lut_mem.hex", SIGMOID_ROM);
    end

    // Use symmetry: compute abs(z) for lookup
    // Sigmoid(-x) = 1 - Sigmoid(x)
    wire is_negative = z_in[31];
    wire signed [31:0] z_abs = is_negative ? -z_in : z_in;

    // Address bits selected from fractional range
    // Bit 9 corresponds to 2^-7 (0.0078125)
    // Slice [18:9] = 10 bits
    wire [ADDRESS_BITS-1:0] rom_address = z_abs[18:9];
    
    wire signed [31:0] rom_data = SIGMOID_ROM[rom_address];

    assign a_sigmoid =
        (z_in >= POS_CLAMP_THRESHOLD) ? SIGMOID_MAX_VAL :
        (z_in <= NEG_CLAMP_THRESHOLD) ? SIGMOID_MIN_VAL :
        (is_negative ? (SIGMOID_MAX_VAL - rom_data) : rom_data);

endmodule

src/tanh_lut.v
// File         : tanh_lut.v
// Description  : Tanh LUT for Q16.16 format (32-bit)
//                Updated for higher precision (Step 2^-7)

module tanh_lut (
    input  signed [31:0] z_in,   // Q16.16
    output signed [31:0] a_tanh   // Q16.16
);

    // 1024 entries match the Python generator
    localparam ADDRESS_BITS = 10; 
    localparam DATA_WIDTH   = 32;
    localparam ROM_DEPTH    = 1 << ADDRESS_BITS;

    // Saturation outputs (Q16.16)
    localparam signed [31:0] MAX_POSITIVE_VAL = 32'h00010000; // +1.0
    localparam signed [31:0] MAX_NEGATIVE_VAL = 32'hFFFF0000; // -1.0

    // Clamp thresholds (-6.0 to +6.0 in Q16.16)
    // The LUT covers 0 to 8.0, so 6.0 is safely within range.
    localparam signed [31:0] CLAMP_POS = 32'h00060000;
    localparam signed [31:0] CLAMP_NEG = 32'hFFFA0000;

    reg [DATA_WIDTH-1:0] TANH_ROM [0:ROM_DEPTH-1];

    initial begin
        $readmemh("./mem/tanh_lut_mem.hex", TANH_ROM);
    end

    // Absolute value for symmetric LUT
    wire signed [31:0] z_abs = z_in[31] ? -z_in : z_in;

    // Address extraction:
    // Q16.16 format:
    // Bit 16 = 2^0 (1.0)
    // ...
    // Bit 9  = 2^-7 (0.0078125)
    //
    // Slice [18:9] gives 10 bits. 
    // Max index (all 1s) = 1023 -> 1023 * 2^-7 = ~7.99
    wire [ADDRESS_BITS-1:0] rom_address = z_abs[18:9];

    wire signed [31:0] rom_data = TANH_ROM[rom_address];

    // Final output: clamp + restore sign
    assign a_tanh =
        (z_in >= CLAMP_POS) ? MAX_POSITIVE_VAL :
        (z_in <= CLAMP_NEG) ? MAX_NEGATIVE_VAL :
        (z_in[31] ? -rom_data : rom_data);

endmodule

src/pe_neuron.v
// File         : pe_neuron.v
// Description  : Processing Element (Neuron) module

// sum_reg is on clock edge
// sig_out and tanh_out is combinational
// y_out and y_final_reg is clocked
// So for a single pass, it needs 1 clock (on any edge)


`include "tanh_lut.v"
`include "sigmoid_lut.v"

module pe_neuron #(
    parameter DATA_WIDTH = 32
) (
    input wire clk,
    input wire rst,
    input signed [DATA_WIDTH-1:0] x1, x2, x3, x4,
    input signed [DATA_WIDTH-1:0] w1, w2, w3, w4,
    input signed [DATA_WIDTH-1:0] bias,
    input wire pe_accumulate,
    input wire signed [DATA_WIDTH-1:0] partial_sum_in,
    input wire [1:0] act_sel,
    output signed [DATA_WIDTH-1:0] y_out
);

    // --- STAGE 1: Multiplication (Clocked) ---
    // Similar to neuronOp p1_reg
    reg signed [DATA_WIDTH-1:0] p1_reg, p2_reg, p3_reg, p4_reg;
    
    // Multipliers (Combinational part)
    wire signed [2*DATA_WIDTH-1:0] p1_long = x1 * w1;
    wire signed [2*DATA_WIDTH-1:0] p2_long = x2 * w2;
    wire signed [2*DATA_WIDTH-1:0] p3_long = x3 * w3;
    wire signed [2*DATA_WIDTH-1:0] p4_long = x4 * w4;

    always @(posedge clk or negedge rst) begin
        if (!rst) begin
            p1_reg <= 0; p2_reg <= 0; p3_reg <= 0; p4_reg <= 0;
        end else begin
            // Shift down to Q16.16 immediately and register
            p1_reg <= p1_long >>> 16;
            p2_reg <= p2_long >>> 16;
            p3_reg <= p3_long >>> 16;
            p4_reg <= p4_long >>> 16;
        end
    end

    // --- STAGE 2: Summation (Clocked) ---
    // Similar to neuronOp y_int_reg
    reg signed [DATA_WIDTH-1:0] sum_reg;
    reg [1:0] act_sel_d1, act_sel_d2; // Delay activation select signal to match pipeline
    
    always @(posedge clk or negedge rst) begin
        if (!rst) begin
            sum_reg <= 0;
            act_sel_d1 <= 0;
        end else begin
            if (pe_accumulate)
                sum_reg <= p1_reg + p2_reg + p3_reg + p4_reg + bias + partial_sum_in;
            else
                sum_reg <= p1_reg + p2_reg + p3_reg + p4_reg + bias;
            
            // Pipeline the control signal too!
            act_sel_d1 <= act_sel; 
        end
    end

    // --- STAGE 3: Activation / LUT (Clocked Output) ---
    wire signed [DATA_WIDTH-1:0] tanh_out, sig_out;
    reg signed [DATA_WIDTH-1:0] y_final_reg;

    tanh_lut u_tanh (.z_in(sum_reg), .a_tanh(tanh_out));
    sigmoid_lut u_sig (.z_in(sum_reg), .a_sigmoid(sig_out));

    always @(posedge clk or negedge rst) begin
        if (!rst) y_final_reg <= 0;
        else begin
            case (act_sel_d1) // Use the delayed control signal
                2'd0: y_final_reg <= tanh_out;
                2'd1: y_final_reg <= sig_out;
                default: y_final_reg <= sum_reg;
            endcase
        end
    end

    assign y_out = y_final_reg;

endmodule

src/memory.v
// File: memory.v
// Description: memory module reading weights and biases from hex files

`timescale 1ns/1ps

module memory #(
    parameter DATA_WIDTH = 32,
    parameter ADDR_WIDTH = 10,
    parameter MEM_DEPTH  = 32
)(
    input wire clk,
    input wire [ADDR_WIDTH-1:0] addr,
    output reg signed [DATA_WIDTH-1:0] w1, w2, w3, w4, bias
);

    // Internal RAM
    reg [DATA_WIDTH-1:0] mem_w1   [0:MEM_DEPTH-1];
    reg [DATA_WIDTH-1:0] mem_w2   [0:MEM_DEPTH-1];
    reg [DATA_WIDTH-1:0] mem_w3   [0:MEM_DEPTH-1];
    reg [DATA_WIDTH-1:0] mem_w4   [0:MEM_DEPTH-1];
    reg [DATA_WIDTH-1:0] mem_bias [0:MEM_DEPTH-1];

    // Load contents from hex files
    initial begin
        $readmemh("mem/w1.hex",   mem_w1);
        $readmemh("mem/w2.hex",   mem_w2);
        $readmemh("mem/w3.hex",   mem_w3);
        $readmemh("mem/w4.hex",   mem_w4);
        $readmemh("mem/bias.hex", mem_bias);
    end

    // Combinational read
    always @(*) begin
        if (addr < MEM_DEPTH) begin
            w1   = mem_w1[addr];
            w2   = mem_w2[addr];
            w3   = mem_w3[addr];
            w4   = mem_w4[addr];
            bias = mem_bias[addr];
        end else begin
            w1 = 0; w2 = 0; w3 = 0; w4 = 0; bias = 0;
        end
    end

endmodule

src/gan3x3.v
// File         : gan3x3.v
// Description  : GAN 3x3 module

`timescale 1ns/1ps

`include "memory.v"
`include "pe_neuron.v"

module gan3x3 #(
    parameter DATA_WIDTH = 32
) (
    input wire clk,
    input wire rst,
    input wire start,
    input wire signed [DATA_WIDTH-1:0] noise_in1,
    input wire signed [DATA_WIDTH-1:0] noise_in2,
    output reg signed [DATA_WIDTH-1:0] disc_out,
    output reg done,

    output wire [DATA_WIDTH-1:0] ram_out_0,
    output wire [DATA_WIDTH-1:0] ram_out_1,
    output wire [DATA_WIDTH-1:0] ram_out_2,
    output wire [DATA_WIDTH-1:0] ram_out_3,
    output wire [DATA_WIDTH-1:0] ram_out_4,
    output wire [DATA_WIDTH-1:0] ram_out_5,
    output wire [DATA_WIDTH-1:0] ram_out_6,
    output wire [DATA_WIDTH-1:0] ram_out_7,
    output wire [DATA_WIDTH-1:0] ram_out_8,
    output wire [DATA_WIDTH-1:0] ram_out_9,
    output wire [DATA_WIDTH-1:0] ram_out_10,
    output wire [DATA_WIDTH-1:0] ram_out_11,
    output wire [DATA_WIDTH-1:0] ram_out_12,
    output wire [DATA_WIDTH-1:0] ram_out_13,
    output wire [DATA_WIDTH-1:0] ram_out_14,
    output wire [DATA_WIDTH-1:0] ram_out_15
);
    // --- RAM ---
    reg signed [DATA_WIDTH-1:0] internal_ram [0:15];
    reg [9:0] mem_addr;

    assign ram_out_0 = internal_ram[0];
    assign ram_out_1 = internal_ram[1];
    assign ram_out_2 = internal_ram[2];
    assign ram_out_3 = internal_ram[3];
    assign ram_out_4 = internal_ram[4];
    assign ram_out_5 = internal_ram[5];
    assign ram_out_6 = internal_ram[6];
    assign ram_out_7 = internal_ram[7];
    assign ram_out_8 = internal_ram[8];
    assign ram_out_9 = internal_ram[9];
    assign ram_out_10 = internal_ram[10];
    assign ram_out_11 = internal_ram[11];
    assign ram_out_12 = internal_ram[12];
    assign ram_out_13 = internal_ram[13];
    assign ram_out_14 = internal_ram[14];
    assign ram_out_15 = internal_ram[15];
    
    // --- Weights & PE signals ---
    wire signed [DATA_WIDTH-1:0] w1, w2, w3, w4, bias;
    reg signed [DATA_WIDTH-1:0] pe_x1, pe_x2, pe_x3, pe_x4;
    reg signed [DATA_WIDTH-1:0] pe_partial_sum;
    wire signed [DATA_WIDTH-1:0] pe_result;
    
    // --- Control ---
    reg pe_accumulate;
    reg [1:0] pe_act_sel; // 0 -> tanh, 1 -> sigmoid

    // --- Pipeline Control ---
    reg [1:0] pipe_cnt;
    localparam [1:0] PIPE_WAIT = 2'd3; // Kontrol pipeline

    // --- Instantiations ---
    memory #(.DATA_WIDTH(DATA_WIDTH)) u_mem (
        .clk (clk), .addr(mem_addr),
        .w1(w1), .w2(w2), .w3(w3), .w4(w4), .bias(bias)
    );
    
    pe_neuron #(.DATA_WIDTH(DATA_WIDTH)) u_pe (
        .clk(clk),
        .rst(rst),
        .x1(pe_x1), .x2(pe_x2), .x3(pe_x3), .x4(pe_x4),
        .w1(w1), .w2(w2), .w3(w3), .w4(w4),
        .bias(bias),
        .pe_accumulate(pe_accumulate),
        .partial_sum_in(pe_partial_sum),
        .act_sel(pe_act_sel),
        .y_out(pe_result)
    );

    // State
    localparam S_IDLE       = 3'd0;
    localparam S_GEN_HIDDEN = 3'd1;
    localparam S_GEN_OUTPUT = 3'd2;
    localparam S_DIS_HIDDEN = 3'd3;
    localparam S_DIS_OUTPUT = 3'd4;
    localparam S_DONE       = 3'd5;

    reg [2:0] state;
    reg [3:0] loop_cnt;
    reg [1:0] acc_step;

    always @(posedge clk or negedge rst) begin
        if (!rst) begin
            state <= S_IDLE;
            mem_addr <= 0;
            done <= 0;
            loop_cnt <= 0;
            acc_step <= 0;
            pipe_cnt <= 0;
            pe_partial_sum <= 0;
            pe_x1 <= 0; pe_x2 <= 0; pe_x3 <= 0; pe_x4 <= 0;
            pe_accumulate <= 0;
            pe_act_sel <= 0;
        end else begin
            case (state)
                S_IDLE: begin
                    done <= 0;
                    if(start) begin
                        state <= S_GEN_HIDDEN;
                        mem_addr <= 0;
                        loop_cnt <= 0;
                        pipe_cnt <= 0; // Reset pipe counter
                        
                        pe_x1 <= noise_in1;
                        pe_x2 <= noise_in2;
                        pe_x3 <= 0;
                        pe_x4 <= 0;
                        pe_act_sel <= 0; // Tanh
                        pe_accumulate <= 0;
                    end
                end
            
                S_GEN_HIDDEN: begin
                    // Tunggu pipeline
                    if (pipe_cnt < PIPE_WAIT) begin
                        pipe_cnt <= pipe_cnt + 1;
                    end else begin
                        internal_ram[loop_cnt] <= pe_result;
                        pipe_cnt <= 0; // Reset counter pipeline

                        if (loop_cnt == 2) begin
                            state <= S_GEN_OUTPUT;
                            loop_cnt <= 0;
                            mem_addr <= mem_addr + 1;
                            
                            pe_x1 <= internal_ram[0];
                            pe_x2 <= internal_ram[1];
                            pe_x3 <= pe_result; // preload
                            pe_x4 <= 0;
                            pe_act_sel <= 0;
                            pe_accumulate <= 0;
                        end else begin
                            loop_cnt <= loop_cnt + 1;
                            mem_addr <= mem_addr + 1;
                            
                            pe_x1 <= noise_in1;
                            pe_x2 <= noise_in2;
                            pe_x3 <= 0;
                            pe_x4 <= 0;
                        end
                    end
                end

                S_GEN_OUTPUT: begin
                    // Tunggu pipeline
                    if (pipe_cnt < PIPE_WAIT) begin
                        pipe_cnt <= pipe_cnt + 1;
                    end else begin

                        internal_ram[3+loop_cnt] <= pe_result;
                        pipe_cnt <= 0; 

                        if (loop_cnt == 8) begin
                            state <= S_DIS_HIDDEN;
                            loop_cnt <= 0;
                            acc_step <= 0;
                            mem_addr <= mem_addr + 1;
                            
                            // Inputs: Pixel 0-3 (RAM 3,4,5,6)
                            pe_x1 <= internal_ram[3];
                            pe_x2 <= internal_ram[4];
                            pe_x3 <= internal_ram[5];
                            pe_x4 <= internal_ram[6];
                            pe_act_sel <= 2; // bypass
                            pe_accumulate <= 0;
                        end else begin
                            loop_cnt <= loop_cnt + 1;
                            mem_addr <= mem_addr + 1;
                            
                            pe_x1 <= internal_ram[0];
                            pe_x2 <= internal_ram[1];
                            pe_x3 <= internal_ram[2];
                            pe_x4 <= 0;
                        end
                    end
                end

                S_DIS_HIDDEN: begin
                    
                    if (pipe_cnt < PIPE_WAIT) begin
                        pipe_cnt <= pipe_cnt + 1;
                    end else begin
                        pipe_cnt <= 0;

                        case (acc_step)
                            0: begin
                                pe_partial_sum <= pe_result;
                                
                                acc_step <= 1;
                                mem_addr <= mem_addr + 1;
                                
                                pe_x1 <= internal_ram[7];
                                pe_x2 <= internal_ram[8];
                                pe_x3 <= internal_ram[9];
                                pe_x4 <= internal_ram[10];
                                pe_accumulate <= 1; // Akumulasi
                            end

                            1: begin
                                pe_partial_sum <= pe_result;
                                
                                acc_step <= 2;
                                mem_addr <= mem_addr + 1;
                                
                                pe_x1 <= internal_ram[11];
                                pe_x2 <= 0;
                                pe_x3 <= 0;
                                pe_x4 <= 0;
                                pe_act_sel <= 0;
                                pe_accumulate <= 1;
                            end
                            
                            2: begin
                                internal_ram[12+loop_cnt] <= pe_result;
                                
                                if(loop_cnt == 2) begin
                                    state <= S_DIS_OUTPUT;
                                    loop_cnt <= 0;
                                    mem_addr <= mem_addr + 1;
                                    
                                    //RAM 12, 13, 14
                                    pe_x1 <= internal_ram[12];
                                    pe_x2 <= internal_ram[13];
                                    pe_x3 <= pe_result;
                                    pe_x4 <= 0;
                                    pe_act_sel <= 1; // Sigmoid
                                    pe_accumulate <= 0;
                                end else begin
                                    loop_cnt <= loop_cnt + 1;
                                    acc_step <= 0;
                                    mem_addr <= mem_addr + 1;
                                    
                                    // Pass 0
                                    pe_x1 <= internal_ram[3];
                                    pe_x2 <= internal_ram[4];
                                    pe_x3 <= internal_ram[5];
                                    pe_x4 <= internal_ram[6];
                                    pe_act_sel <= 2;    
                                    pe_accumulate <= 0;
                                end
                            end
                        endcase
                    end
                end

                S_DIS_OUTPUT: begin
                    if (pipe_cnt < PIPE_WAIT) begin
                        pipe_cnt <= pipe_cnt + 1;
                    end else begin
                        // Final Output
                        disc_out <= pe_result;
                        state <= S_DONE;
                    end
                end

                S_DONE: begin
                    done <= 1;
                    if (!start) state <= S_IDLE;
                end
                
                default: state <= S_IDLE;
            endcase
        end
    end

endmodule

src/tb_gan3x3.v
// File         : tb_gan3x3.v
// Description  : Testbench for the gan3x3 module

`timescale 1ns/1ps
`include "gan3x3.v"

module tb_gan3x3;

    parameter DATA_WIDTH = 32;
    real float_out; 

    reg clk;
    reg rst;
    reg start;
    reg signed [DATA_WIDTH-1:0] noise_in1;
    reg signed [DATA_WIDTH-1:0] noise_in2;

    wire signed [DATA_WIDTH-1:0] disc_out;
    wire done;

    gan3x3 #(.DATA_WIDTH(DATA_WIDTH)) u_dut (
        .clk(clk),
        .rst(rst),
        .start(start),
        .noise_in1(noise_in1),
        .noise_in2(noise_in2),
        .disc_out(disc_out),
        .done(done)
    );

    // Clock Generation
    always #5 clk = ~clk;

    // Waveform Dump
    initial begin
        $dumpfile("gan_3x3.vcd");
        $dumpvars(0, tb_gan3x3);
    end

    initial begin
        clk = 0;
        rst = 0;
        start = 0;
        noise_in1 = 0;
        noise_in2 = 0;

        $display("--- Simulation Start ---");

        // Reset Sequence
        #20;
        @(negedge clk);
        rst = 1; // Release Reset
        
        // --------------------------------------------------------
        // Test Case 1: Noise [0.5, -0.2]
        // --------------------------------------------------------
        #20;
        @(negedge clk);
        $display("\n--- Test Case 1: Noise [0.5, -0.2] ---");
        noise_in1 = 32'h0000_8000;  // 0.5
        noise_in2 = 32'hFFFF_CCCD;  // -0.2
        start = 1;
        
        #10;
        @(negedge clk);
        start = 0;

        wait(done);
        @(negedge clk);

        // --- Print Results for Test Case 1 ---
        $display("Done Signal Received!");
        
        // 1. Generator Hidden Layer (G2) - stored in RAM [0..2]
        $display("\n[G2] Generator Hidden Layer Outputs:");
        $display("N1: %h", u_dut.internal_ram[0]);
        $display("N2: %h", u_dut.internal_ram[1]);
        $display("N3: %h", u_dut.internal_ram[2]);

        // 2. Generator Output Layer (G3) - stored in RAM [3..11]
        $display("\n[G3] Generated Fake Image (3x3):");
        $display("[ %h  %h  %h ]", u_dut.internal_ram[3], u_dut.internal_ram[4], u_dut.internal_ram[5]);
        $display("[ %h  %h  %h ]", u_dut.internal_ram[6], u_dut.internal_ram[7], u_dut.internal_ram[8]);
        $display("[ %h  %h  %h ]", u_dut.internal_ram[9], u_dut.internal_ram[10], u_dut.internal_ram[11]);

        // 3. Discriminator Hidden Layer (D2) - stored in RAM [12..14]
        $display("\n[D2] Discriminator Hidden Layer Outputs:");
        $display("N1: %h", u_dut.internal_ram[12]);
        $display("N2: %h", u_dut.internal_ram[13]);
        $display("N3: %h", u_dut.internal_ram[14]);

        // 4. Final Output
        float_out = $signed(disc_out) / 65536.0;
        $display("\n[D3] Discriminator Final Output:");
        $display("Raw Hex: %h", disc_out);
        $display("Probability: %0.4f", float_out);

        // // --------------------------------------------------------
        // // Test Case 2: Noise [-1.0, 1.0]
        // // --------------------------------------------------------
        // #50;
        // @(negedge clk); 
        // $display("\n--- Test Case 2: Noise [-1.0, 1.0] ---");
        // noise_in1 = 32'h0000_8000; // -1.0
        // noise_in2 = 32'hFFFF_CCCD; //  1.0
        // start = 1;
        
        // @(negedge clk);
        // start = 0;
        
        // wait(done);
        // @(negedge clk);
        
        // // --- Print Results for Test Case 2 ---
        
        // // 1. Generator Hidden Layer (G2)
        // $display("\n[G2] Generator Hidden Layer Outputs:");
        // $display("N1: %h", u_dut.internal_ram[0]);
        // $display("N2: %h", u_dut.internal_ram[1]);
        // $display("N3: %h", u_dut.internal_ram[2]);
        
        // // 2. Generator Output Layer (G3)
        // $display("\n[G3] Generated Fake Image (3x3):");
        // $display("[ %h  %h  %h ]", u_dut.internal_ram[3], u_dut.internal_ram[4], u_dut.internal_ram[5]);
        // $display("[ %h  %h  %h ]", u_dut.internal_ram[6], u_dut.internal_ram[7], u_dut.internal_ram[8]);
        // $display("[ %h  %h  %h ]", u_dut.internal_ram[9], u_dut.internal_ram[10], u_dut.internal_ram[11]);

        // // 3. Discriminator Hidden Layer (D2)
        // $display("\n[D2] Discriminator Hidden Layer Outputs:");
        // $display("N1: %h", u_dut.internal_ram[12]);
        // $display("N2: %h", u_dut.internal_ram[13]);
        // $display("N3: %h", u_dut.internal_ram[14]);

        // // 4. Final Output
        // float_out = $signed(disc_out) / 65536.0;
        // $display("\n[D3] Discriminator Final Output:");
        // $display("Raw Hex: %h", disc_out);
        // $display("Probability: %0.4f", float_out);

        #100;
        $display("\n--- Simulation Complete ---");
        $finish;
    end

    // Dump Waveforms
    initial begin
        $dumpfile("gan_waveform.vcd");
        $dumpvars(0, tb_gan3x3);
    end

endmodule

src/gan_3x3.vcd
$date
	Sat Jan 10 04:20:07 2026
$end
$version
	Icarus Verilog
$end
$timescale
	1ps
$end
$scope module tb_gan3x3 $end
$var wire 1 ! done $end
$var wire 32 " disc_out [31:0] $end
$var parameter 32 # DATA_WIDTH $end
$var reg 1 $ clk $end
$var reg 32 % noise_in1 [31:0] $end
$var reg 32 & noise_in2 [31:0] $end
$var reg 1 ' rst $end
$var reg 1 ( start $end
$var real 1 ) float_out $end
$scope module u_dut $end
$var wire 1 $ clk $end
$var wire 32 * noise_in1 [31:0] $end
$var wire 32 + noise_in2 [31:0] $end
$var wire 32 , ram_out_0 [31:0] $end
$var wire 32 - ram_out_1 [31:0] $end
$var wire 32 . ram_out_10 [31:0] $end
$var wire 32 / ram_out_11 [31:0] $end
$var wire 32 0 ram_out_12 [31:0] $end
$var wire 32 1 ram_out_13 [31:0] $end
$var wire 32 2 ram_out_14 [31:0] $end
$var wire 32 3 ram_out_15 [31:0] $end
$var wire 32 4 ram_out_2 [31:0] $end
$var wire 32 5 ram_out_3 [31:0] $end
$var wire 32 6 ram_out_4 [31:0] $end
$var wire 32 7 ram_out_5 [31:0] $end
$var wire 32 8 ram_out_6 [31:0] $end
$var wire 32 9 ram_out_7 [31:0] $end
$var wire 32 : ram_out_8 [31:0] $end
$var wire 32 ; ram_out_9 [31:0] $end
$var wire 1 ' rst $end
$var wire 1 ( start $end
$var wire 32 < w4 [31:0] $end
$var wire 32 = w3 [31:0] $end
$var wire 32 > w2 [31:0] $end
$var wire 32 ? w1 [31:0] $end
$var wire 32 @ pe_result [31:0] $end
$var wire 32 A bias [31:0] $end
$var parameter 32 B DATA_WIDTH $end
$var parameter 2 C PIPE_WAIT $end
$var parameter 3 D S_DIS_HIDDEN $end
$var parameter 3 E S_DIS_OUTPUT $end
$var parameter 3 F S_DONE $end
$var parameter 3 G S_GEN_HIDDEN $end
$var parameter 3 H S_GEN_OUTPUT $end
$var parameter 3 I S_IDLE $end
$var reg 2 J acc_step [1:0] $end
$var reg 32 K disc_out [31:0] $end
$var reg 1 ! done $end
$var reg 4 L loop_cnt [3:0] $end
$var reg 10 M mem_addr [9:0] $end
$var reg 1 N pe_accumulate $end
$var reg 2 O pe_act_sel [1:0] $end
$var reg 32 P pe_partial_sum [31:0] $end
$var reg 32 Q pe_x1 [31:0] $end
$var reg 32 R pe_x2 [31:0] $end
$var reg 32 S pe_x3 [31:0] $end
$var reg 32 T pe_x4 [31:0] $end
$var reg 2 U pipe_cnt [1:0] $end
$var reg 3 V state [2:0] $end
$scope module u_mem $end
$var wire 10 W addr [9:0] $end
$var wire 1 $ clk $end
$var parameter 32 X ADDR_WIDTH $end
$var parameter 32 Y DATA_WIDTH $end
$var parameter 32 Z MEM_DEPTH $end
$var reg 32 [ bias [31:0] $end
$var reg 32 \ w1 [31:0] $end
$var reg 32 ] w2 [31:0] $end
$var reg 32 ^ w3 [31:0] $end
$var reg 32 _ w4 [31:0] $end
$upscope $end
$scope module u_pe $end
$var wire 2 ` act_sel [1:0] $end
$var wire 32 a bias [31:0] $end
$var wire 1 $ clk $end
$var wire 32 b partial_sum_in [31:0] $end
$var wire 1 N pe_accumulate $end
$var wire 1 ' rst $end
$var wire 32 c w1 [31:0] $end
$var wire 32 d w2 [31:0] $end
$var wire 32 e w3 [31:0] $end
$var wire 32 f w4 [31:0] $end
$var wire 32 g x1 [31:0] $end
$var wire 32 h x2 [31:0] $end
$var wire 32 i x3 [31:0] $end
$var wire 32 j x4 [31:0] $end
$var wire 32 k y_out [31:0] $end
$var wire 32 l tanh_out [31:0] $end
$var wire 32 m sig_out [31:0] $end
$var wire 64 n p4_long [63:0] $end
$var wire 64 o p3_long [63:0] $end
$var wire 64 p p2_long [63:0] $end
$var wire 64 q p1_long [63:0] $end
$var parameter 32 r DATA_WIDTH $end
$var reg 2 s act_sel_d1 [1:0] $end
$var reg 32 t p1_reg [31:0] $end
$var reg 32 u p2_reg [31:0] $end
$var reg 32 v p3_reg [31:0] $end
$var reg 32 w p4_reg [31:0] $end
$var reg 32 x sum_reg [31:0] $end
$var reg 32 y y_final_reg [31:0] $end
$scope module u_sig $end
$var wire 32 z rom_data [31:0] $end
$var wire 32 { z_in [31:0] $end
$var wire 32 | z_abs [31:0] $end
$var wire 10 } rom_address [9:0] $end
$var wire 1 ~ is_negative $end
$var wire 32 !" a_sigmoid [31:0] $end
$var parameter 32 "" ADDRESS_BITS $end
$var parameter 32 #" DATA_WIDTH $end
$var parameter 32 $" NEG_CLAMP_THRESHOLD $end
$var parameter 32 %" POS_CLAMP_THRESHOLD $end
$var parameter 42 &" ROM_DEPTH $end
$var parameter 32 '" SIGMOID_MAX_VAL $end
$var parameter 32 (" SIGMOID_MIN_VAL $end
$upscope $end
$scope module u_tanh $end
$var wire 32 )" rom_data [31:0] $end
$var wire 32 *" z_in [31:0] $end
$var wire 32 +" z_abs [31:0] $end
$var wire 10 ," rom_address [9:0] $end
$var wire 32 -" a_tanh [31:0] $end
$var parameter 32 ." ADDRESS_BITS $end
$var parameter 32 /" CLAMP_NEG $end
$var parameter 32 0" CLAMP_POS $end
$var parameter 32 1" DATA_WIDTH $end
$var parameter 32 2" MAX_NEGATIVE_VAL $end
$var parameter 32 3" MAX_POSITIVE_VAL $end
$var parameter 42 4" ROM_DEPTH $end
$upscope $end
$upscope $end
$upscope $end
$upscope $end
$scope module tb_gan3x3 $end
$scope module u_dut $end
$scope module u_mem $end
$upscope $end
$scope module u_pe $end
$scope module u_sig $end
$upscope $end
$scope module u_tanh $end
$upscope $end
$upscope $end
$upscope $end
$upscope $end
$enddefinitions $end
$comment Show the parameter values. $end
$dumpall
b10000000000 4"
b10000000000000000 3"
b11111111111111110000000000000000 2"
b100000 1"
b1100000000000000000 0"
b11111111111110100000000000000000 /"
b1010 ."
b0 ("
b10000000000000000 '"
b10000000000 &"
b1100000000000000000 %"
b11111111111110100000000000000000 $"
b100000 #"
b1010 ""
b100000 r
b100000 Z
b100000 Y
b1010 X
b0 I
b10 H
b1 G
b101 F
b100 E
b11 D
b11 C
b100000 B
b100000 #
$end
#0
$dumpvars
b0 -"
b0 ,"
b0 +"
b0 *"
b0 )"
b1000000000000000 !"
0~
b0 }
b0 |
b0 {
b1000000000000000 z
b0 y
b0 x
b0 w
b0 v
b0 u
b0 t
b0 s
b0 q
b0 p
b0 o
b0 n
b1000000000000000 m
b0 l
b0 k
b0 j
b0 i
b0 h
b0 g
b0 f
b0 e
b11011100 d
b10001001 c
b0 b
b11001101000100111 a
b0 `
b0 _
b0 ^
b11011100 ]
b10001001 \
b11001101000100111 [
b0 W
b0 V
b0 U
b0 T
b0 S
b0 R
b0 Q
b0 P
b0 O
0N
b0 M
b0 L
bx K
b0 J
b11001101000100111 A
b0 @
b10001001 ?
b11011100 >
b0 =
b0 <
bx ;
bx :
bx 9
bx 8
bx 7
bx 6
bx 5
bx 4
bx 3
bx 2
bx 1
bx 0
bx /
bx .
bx -
bx ,
b0 +
b0 *
r0 )
0(
0'
b0 &
b0 %
0$
bx "
0!
$end
#5000
1$
#10000
0$
#15000
1$
#20000
1'
0$
#25000
b1101010100001101 m
b1101010100001101 !"
b1110110000000001 l
b1110110000000001 -"
b1101010100001101 z
b11001101 }
b1110110000000001 )"
b11001101 ,"
b11001101000100111 |
b11001101000100111 +"
b11001101000100111 x
b11001101000100111 {
b11001101000100111 *"
1$
#30000
0$
#35000
b1110110000000001 @
b1110110000000001 k
b1110110000000001 y
1$
#40000
1(
b11111111111111111100110011001101 &
b11111111111111111100110011001101 +
b1000000000000000 %
b1000000000000000 *
0$
#45000
b1111111111111111111111111111111111111111110101000000000000101100 p
b11111111111111111100110011001101 R
b11111111111111111100110011001101 h
b10001001000000000000000 q
b1000000000000000 Q
b1000000000000000 g
b1 V
1$
#50000
0(
0$
#55000
b11111111111111111111111111010100 u
b1000100 t
b1 U
1$
#60000
0$
#65000
b11001101000111111 |
b11001101000111111 +"
b10 U
b11001101000111111 x
b11001101000111111 {
b11001101000111111 *"
1$
#70000
0$
#75000
b11 U
1$
#80000
0$
#85000
b11111111111111110111001111000111 A
b11111111111111110111001111000111 [
b11111111111111110111001111000111 a
b1111111111111111111111111111111111111110111110010000000100000111 p
b10100100011 >
b10100100011 ]
b10100100011 d
b1110001000010000000000000000 q
b1110001000010 ?
b1110001000010 \
b1110001000010 c
b1 M
b1 W
b1 L
b0 U
b1110110000000001 ,
1$
#90000
0$
#95000
b101110111011001 m
b101110111011001 !"
b11111111111111111000000001111000 l
b11111111111111111000000001111000 -"
b1010001000100111 z
b1000110 }
b111111110001000 )"
b1000110 ,"
1~
b1000110000100001 |
b1000110000100001 +"
b11111111111111111111111011111001 u
b111000100001 t
b11111111111111110111001111011111 x
b11111111111111110111001111011111 {
b11111111111111110111001111011111 *"
b1 U
1$
#100000
0$
#105000
b110000100011111 m
b110000100011111 !"
b11111111111111111000101101000111 l
b11111111111111111000101101000111 -"
b1001111011100001 z
b111111 }
b111010010111001 )"
b111111 ,"
b111111100011111 |
b111111100011111 +"
b10 U
b11111111111111111000000001111000 @
b11111111111111111000000001111000 k
b11111111111111111000000001111000 y
b11111111111111111000000011100001 x
b11111111111111111000000011100001 {
b11111111111111111000000011100001 *"
1$
#110000
0$
